Workbook

Sheet MARE MX
G1: F | U1: =COUNTA(B3:B561) -> 488 | V1: =SUM(V3:V561) -> 147639.6 | W1: =SUM(W3:W561) -> 152066.18 | X1: =SUM(X3:X561) -> 161268.61 | Y1: =SUM(Y3:Y561) -> 165755.69 | Z1: =SUM(Z3:Z561) -> 170217.87 | AA1: =SUM(AA3:AA561) -> 190347.44 | AB1: =SUM(AB3:AB561) -> 182605.61 | AC1: =SUM(AC3:AC561) -> 184136.46 | AD1: =SUM(AD3:AD561) -> 175678.97 | AT1: =COUNTIF(AT$3:AT$555,"*OK*") -> 5 | AU1: =COUNTIF(AU$3:AU$555,"*OK*") -> 1 | AV1: =COUNTIF(AV$3:AV$555,"*OK*") -> 28 | AW1: =COUNTIF(AW$3:AW$555,"*OK*") -> 5 | AX1: =COUNTIF(AX$3:AX$555,"*OK*") -> 13 | AY1: =COUNTIF(AY$3:AY$555,"*OK*") -> 7 | AZ1: =COUNTIF(AZ$3:AZ$555,"*OK*") -> 11 | BA1: =COUNTIF(BA$3:BA$555,"*OK*") -> 2 | ... BI1: =COUNTIF(BI$3:BI$555,"*OK*") -> 2
A2: ID Geo | B2: RFC | C2: Facturación actual USD | D2: Cross | E2: KAM | F2: CLIENTE | G2: Grupo | H2: Facturación Total | I2: Cartera | J2: Facturado por partner | K2: Enganche otro | L2: Zoho | M2: Cuadrante (MARE + Retener) | N2: Comentario | O2: Nombre | P2: Teléfono | Q2: Correo | R2: GeoCoffee | S2: Tag | T2: Implementando? | U2: Rubro zoho | V2: Enero | W2: Febrero | X2: Marzo | Y2: Abril | Z2: Mayo | AA2: Junio | AB2: Julio | AC2: Agosto | AD2: Septiembre | AE2: Usuarios activos | AF2: Usuarios potenciales (Claude) | AH2: Estado | AI2: Estado Claude | AJ2: Rubro Claude | AK2: Descripción breve de la empresa y a que se dedica | AL2: Rubro | AM2: Primera factura | AN2: Escala comunicación | AO2: Periodicidad | AP2: Operación actual cliente con GV | AQ2: Acción especifica | AR2: Sistema de Nómina | AS2: Nos usa para pagar nómina? | AT2: Alertas | AU2: Integración (VC) | AV2: Permisos y vacaciones | AW2: Planif. Inteligente | AX2: BI | AY2: RAM | AZ2: Acceso | BA2: Comedor | BB2: VictorIA | BC2: Optimizador Turnos | BD2: Marcaje WPP | BE2: WF Cambio de turno | BF2: Plan Pro | BG2: Plan Enterprise | BH2: Formularios | BI2: Upselling | BJ2: Suma Ops | BK2: Arrienda equipos? | BL2: Puntaje Cross | BM2: Riesgo | BN2: Referido/Referencia | BO2: MEDIO DE GESTIÓN | BP2: Orden | BQ2: MEDIO DE CONTACTO | CL2: # Productos OK | CN2: # Productos OP
A3: 29157-37879-36085-37826-36099-38471 | B3: CCO210827216 | C3: =AD3 -> 5979.3046 | D3: 1 | E3: Dafne de la Rosa | F3: J&T EXPRESS CONEJO CORRIENDO | G3: CONEJO CORRIENDO | H3: =IF(LEN(TRIM($G3&""))=0, $C3, SUMIF($G$3:$G$561, TRIM($G3), $C$3:$C$561)) -> 0 | I3: ENTERPRISE | L3: =HYPERLINK("https://crm.zoho.com/crm/org685875245/tab/Accounts/3525045000260992026","https://crm.zoho.com/crm/org685875245/tab/Accounts/3525045000260992026") -> https://crm.zoho.com/crm/org685875245/tab/Accounts/3525045000260992026 | M3: Expandir | O3: Angel | P3: 5615572088 | Q3: angel.olvera@jtexpress.mx | R3: Invitado | U3: - | V3: 2440.36 | W3: 3186.1 | X3: 4304.34 | Y3: 4411.64 | Z3: 4070.0878 | AA3: 5804.78 | AB3: 5002.2185 | AC3: 5772.7131 | AD3: 5979.3046 | AE3: 3582 | AF3: 1355 | AH3: CDMX | AI3: CDMX | AJ3: Logística | AK3: Empresa de mensajería y logística de última milla, parte del grupo internacional J&T Express, con operaciones en toda la República Mexicana. | AL3: Logistica | AR3: Sicoss | AS3: SI | BJ3: =COUNTIF(AT3:BI3,"*OP*") -> 0 | BK3: NO | BL3: =(COUNTIF(AT3:AV3,"*OK*")*3) + (COUNTIF(AW3:AY3,"*OK*")*2) + COUNTIF(AZ3:BB3,"*OK*")+COUNTIF(BK3:BK3,"SI")*0.5 -> 0 | BM3: =IF(BL3<0.6,"Demasiado Riesgo",IF(BL3<=5,"Riesgo Medio",IF(BL3<=11,"Riesgo Bajo","Cliente Blindado"))) -> Demasiado Riesgo | BO3: CON 7 REGIONES CORREO DAFN | BP3: 0 | BQ3: Correo y Llamada | CL3: =COUNTIF(AT3:BH3,"*OK*") -> 0 | CN3: =COUNTIF(AT3:BH3,"*OP*") -> 0
A4: 24596 | B4: SPI180316RR7 | C4: =AD4 -> 5311.2583 | D4: =COUNTIF(AT4:BH4,"*OK*") -> 0 | E4: Raúl Campos | F4: SYD PROYECTOS INTEGRALES (Antromex) | G4: ANTROMEX | H4: =IF(LEN(TRIM($G4&""))=0, $C4, SUMIF($G$3:$G$561, TRIM($G4), $C$3:$C$561)) -> 5311.2583 | I4: ENTERPRISE | L4: =HYPERLINK("https://crm.zoho.com/crm/org685875245/tab/Accounts/3525045000297139312","https://crm.zoho.com/crm/org685875245/tab/Accounts/3525045000297139312") -> https://crm.zoho.com/crm/org685875245/tab/Accounts/3525045000297139312 | M4: Mantener | O4: Marlen Serafin Marlen Serafin | P4: +523112565488 | Q4: rhantromexgdl@gmail.com | U4: - | V4: 4855.91 | W4: 5513.91 | X4: 5601.06 | Y4: 5689.01 | Z4: 5229.4379 | AA4: 5285.23 | AB4: 5332.1193 | AC4: 5485.3039 | AD4: 5311.2583 | AE4: 4909 | AF4: 120 | AI4: Jalisco | AJ4: Construcción | AK4: Empresa constructora con sede en Zapopan, Jalisco, especializada en proyectos integrales de construcción e infraestructura para clientes industriales y corporativos. | AN4: 2. Videollamada | AO4: Semanal | BJ4: =COUNTIF(AT4:BI4,"*OP*") -> 0 | BL4: =(COUNTIF(AT4:AV4,"*OK*")*3) + (COUNTIF(AW4:AY4,"*OK*")*2) + COUNTIF(AZ4:BB4,"*OK*")+COUNTIF(BK4:BK4,"SI")*0.5 -> 0 | BM4: =IF(BL4<0.6,"Demasiado Riesgo",IF(BL4<=5,"Riesgo Medio",IF(BL4<=11,"Riesgo Bajo","Cliente Blindado"))) -> Demasiado Riesgo | BP4: 0 | CL4: =COUNTIF(AT4:BH4,"*OK*") -> 0 | CN4: =COUNTIF(AT4:BH4,"*OP*") -> 0
A5: 7126 | B5: SIR110727BB4 | C5: =AD5 -> 4026.7108 | D5: =COUNTIF(AT5:BH5,"*OK*") -> 0 | E5: Raúl Campos | F5: SERVICIOS INTEGRALES RAMPER(SIRAMPER) | H5: =IF(LEN(TRIM($G5&""))=0, $C5, SUMIF($G$3:$G$561, TRIM($G5), $C$3:$C$561)) -> 4026.7108 | I5: ENTERPRISE | L5: =HYPERLINK("https://crm.zoho.com/crm/org685875245/tab/Accounts/3525045000108826075","https://crm.zoho.com/crm/org685875245/tab/Accounts/3525045000108826075") -> https://crm.zoho.com/crm/org685875245/tab/Accounts/3525045000108826075 | M5: Expandir | O5: Sandy | P5: 5212231138687 | Q5: lopez3664@gmail.com | R5: No están en CDMX | U5: - | V5: 4214.41 | W5: 3964.51 | X5: 3887.79 | Y5: 4227.64 | Z5: 4237.0509 | AA5: 4182.77 | AB5: 4869.1067 | AC5: 4990.7675 | AD5: 4026.7108 | AE5: 1065 | AF5: 600 | AI5: Puebla | AJ5: Outsourcing | AK5: Empresa de outsourcing de servicios de limpieza industrial, conserjería, jardinería y control de plagas, con presencia en 12 estados de México. | AN5: 2. Videollamada | AO5: Semanal | AR5: Contpaqi | BJ5: =COUNTIF(AT5:BI5,"*OP*") -> 0 | BL5: =(COUNTIF(AT5:AV5,"*OK*")*3) + (COUNTIF(AW5:AY5,"*OK*")*2) + COUNTIF(AZ5:BB5,"*OK*")+COUNTIF(BK5:BK5,"SI")*0.5 -> 0 | BM5: =IF(BL5<0.6,"Demasiado Riesgo",IF(BL5<=5,"Riesgo Medio",IF(BL5<=11,"Riesgo Bajo","Cliente Blindado"))) -> Demasiado Riesgo | BP5: 0 | CL5: =COUNTIF(AT5:BH5,"*OK*") -> 0 | CN5: =COUNTIF(AT5:BH5,"*OP*") -> 0
A6: 38530 | B6: DLO1006168N3 | C6: =AD6 -> 4522.0701 | D6: =COUNTIF(AX6:BI6,"OK") -> 0 | E6: Dafne de la Rosa | F6: DICKA LOGISTICS | H6: =IF(LEN(TRIM($G6&""))=0, $C6, SUMIF($G$3:$G$561, TRIM($G6), $C$3:$C$561)) -> 4522.0701 | I6: ENTERPRISE | L6: =HYPERLINK("https://crm.zoho.com/crm/org685875245/tab/Accounts/3525045000545668197","https://crm.zoho.com/crm/org685875245/tab/Accounts/3525045000545668197") -> https://crm.zoho.com/crm/org685875245/tab/Accounts/3525045000545668197 | T6: SI | AA6: 4030.2629 | AB6: 3626.841 | AC6: 4797.4035 | AD6: 4522.0701 | BJ6: =COUNTIF(AT6:BI6,"*OP*") -> 0 | BL6: =(COUNTIF(AT6:AV6,"*OK*")*3) + (COUNTIF(AW6:AY6,"*OK*")*2) + COUNTIF(AZ6:BB6,"*OK*")+COUNTIF(BK6:BK6,"SI")*0.5 -> 0 | BM6: =IF(BL6<0.6,"Demasiado Riesgo",IF(BL6<=5,"Riesgo Medio",IF(BL6<=11,"Riesgo Bajo","Cliente Blindado"))) -> Demasiado Riesgo | CL6: =COUNTIF(AT6:BH6,"*OK*") -> 0
B7: TEK240710P99 | C7: =AD7 -> 4041.9426 | D7: =COUNTIF(AT7:BH7,"*OK*") -> 0 | E7: Raúl Campos | F7: TECNO ESPECIALIZADOS KIURT | H7: =IF(LEN(TRIM($G7&""))=0, $C7, SUMIF($G$3:$G$561, TRIM($G7), $C$3:$C$561)) -> 4041.9426 | I7: ENTERPRISE | J7: TECNO ESPECIALIZADOS KIURT | U7: - | V7: 2852.64 | W7: 2862.77 | X7: 2889.44 | Y7: 3071.38 | Z7: 3295.2622 | AA7: 3510.54 | AC7: 3977.2561 | AD7: 4041.9426 | AF7: 200 | AI7: CDMX | AJ7: Tecnología | AK7: Empresa de tecnología y servicios especializados en soluciones de control de acceso y asistencia, opera como partner de implementación tecnológica. | BJ7: =COUNTIF(AT7:BI7,"*OP*") -> 0 | BL7: =(COUNTIF(AT7:AV7,"*OK*")*3) + (COUNTIF(AW7:AY7,"*OK*")*2) + COUNTIF(AZ7:BB7,"*OK*")+COUNTIF(BK7:BK7,"SI")*0.5 -> 0 | BM7: =IF(BL7<0.6,"Demasiado Riesgo",IF(BL7<=5,"Riesgo Medio",IF(BL7<=11,"Riesgo Bajo","Cliente Blindado"))) -> Demasiado Riesgo | BP7: 0 | CL7: =COUNTIF(AT7:BH7,"*OK*") -> 0 | CN7: =COUNTIF(AT7:BH7,"*OP*") -> 0
A8: 21115 | B8: IPG970717QU9 | C8: =AD8 -> 3750.85 | D8: =COUNTIF(AT8:BH8,"*OK*") -> 1 | E8: Raúl Campos | F8: ABSORMEX CMPC TISSUE | G8: SOFTYS | H8: =IF(LEN(TRIM($G8&""))=0, $C8, SUMIF($G$3:$G$561, TRIM($G8), $C$3:$C$561)) -> 6088.85 | I8: ENTERPRISE | K8: FDP | L8: =HYPERLINK("https://crm.zoho.com/crm/org685875245/tab/Accounts/3525045000374250631","https://crm.zoho.com/crm/org685875245/tab/Accounts/3525045000374250631") -> https://crm.zoho.com/crm/org685875245/tab/Accounts/3525045000374250631 | M8: Mantener | O8: Jessica | P8: 5534151683 | Q8: jessica.romero@softys.com | U8: - | V8: 2906 | W8: 2906 | X8: 3706 | Y8: 2906 | Z8: 2906 | AA8: 3750.85 | AB8: 3750.85 | AC8: 3750.85 | AD8: 3750.85 | AE8: 3242 | AF8: 2000 | AI8: Nuevo León | AJ8: Manufactura | AK8: Fabricante mexicano de productos higiénicos como papel tissue, pañales y artículos de incontinencia bajo el grupo CMPC, con plantas en García NL, Altamira Tamps y Cuautitlán EDOMEX. | AN8: 2. Videollamada | AO8: Diario | AY8: OK(032026) | BJ8: =COUNTIF(AT8:BI8,"*OP*") -> 0 | BL8: =(COUNTIF(AT8:AV8,"*OK*")*3) + (COUNTIF(AW8:AY8,"*OK*")*2) + COUNTIF(AZ8:BB8,"*OK*")+COUNTIF(BK8:BK8,"SI")*0.5 -> 2 | BM8: =IF(BL8<0.6,"Demasiado Riesgo",IF(BL8<=5,"Riesgo Medio",IF(BL8<=11,"Riesgo Bajo","Cliente Blindado"))) -> Riesgo Medio | BN8: Ambos | BP8: 0 | CL8: =COUNTIF(AT8:BH8,"*OK*") -> 1 | CN8: =COUNTIF(AT8:BH8,"*OP*") -> 0
A9: 30644 | B9: GJU880623116 | C9: =AD9 -> 3430.4636 | D9: =COUNTIF(AT9:BH9,"*OK*") -> 0 | E9: Raúl Campos | F9: GRUPO JULIO | G9: JULIO | H9: =IF(LEN(TRIM($G9&""))=0, $C9, SUMIF($G$3:$G$561, TRIM($G9), $C$3:$C$561)) -> 4176.8213 | I9: ENTERPRISE | L9: =HYPERLINK("https://crm.zoho.com/crm/org685875245/tab/Accounts/3525045000446689264","https://crm.zoho.com/crm/org685875245/tab/Accounts/3525045000446689264") -> https://crm.zoho.com/crm/org685875245/tab/Accounts/3525045000446689264 | M9: Expandir | O9: Eduardo | P9: 7751341466 | Q9: eduardo_delrioo@proymoda.com | R9: Ver si invitamos, fue al evento anterior | U9: 17. Retail Enterprise | V9: 2436.17 | W9: 2750.35 | X9: 3261.23 | Y9: 3380.57 | Z9: 3430.9087 | AA9: 3436.49 | AB9: 3516.2948 | AC9: 3652.4096 | AD9: 3430.4636 | AE9: 1624 | AF9: 1300 | AI9: CDMX | AJ9: Retail | AK9: Cadena mexicana de moda femenina con más de 40 años, con 107 tiendas propias y presencia en corners de Palacio de Hierro y Liverpool a nivel nacional y en Colombia. | AN9: 2. Videollamada | AS9: SI | BJ9: =COUNTIF(AT9:BI9,"*OP*") -> 0 | BK9: NO | BL9: =(COUNTIF(AT9:AV9,"*OK*")*3) + (COUNTIF(AW9:AY9,"*OK*")*2) + COUNTIF(AZ9:BB9,"*OK*")+COUNTIF(BK9:BK9,"SI")*0.5 -> 0 | BM9: =IF(BL9<0.6,"Demasiado Riesgo",IF(BL9<=5,"Riesgo Medio",IF(BL9<=11,"Riesgo Bajo","Cliente Blindado"))) -> Demasiado Riesgo | BP9: 0 | CL9: =COUNTIF(AT9:BH9,"*OK*") -> 0 | CN9: =COUNTIF(AT9:BH9,"*OP*") -> 0
A10: 21746 | B10: SIT890317V85 | C10: =AD10 -> 2469.2638 | D10: =COUNTIF(AT10:BH10,"*OK*") -> 0 | E10: Raúl Campos | F10: SISTEMAS INTEGRALES PARA EL TRANSPORTE(SINTRA) | H10: =IF(LEN(TRIM($G10&""))=0, $C10, SUMIF($G$3:$G$561, TRIM($G10), $C$3:$C$561)) -> 2469.2638 | I10: ENTERPRISE | L10: =HYPERLINK("https://crm.zoho.com/crm/org685875245/tab/Accounts/3525045000235830157","https://crm.zoho.com/crm/org685875245/tab/Accounts/3525045000235830157") -> https://crm.zoho.com/crm/org685875245/tab/Accounts/3525045000235830157 | M10: Expandir | O10: Joanna | P10: 5574683122 | Q10: joanna.ruiz@sintra.com.mx | R10: Invitado | U10: - | V10: 2248.55 | W10: 2266.22 | X10: 2393.43 | Y10: 2366.17 | Z10: 2521.1147 | AA10: 2517.37 | AB10: 2581.0536 | AC10: 2631.0647 | AD10: 2469.2638 | AE10: 1061 | AF10: 500 | AI10: CDMX | AJ10: Transporte | AK10: Empresa fundada en 1989 especializada en consultoría, ingeniería y mantenimiento de sistemas de transporte masivo (metro, tren ligero) en México y Latinoamérica. | AN10: 4. Whatsapp | AR10: SAP | AS10: SI | BJ10: =COUNTIF(AT10:BI10,"*OP*") -> 0 | BK10: NO | BL10: =(COUNTIF(AT10:AV10,"*OK*")*3) + (COUNTIF(AW10:AY10,"*OK*")*2) + COUNTIF(AZ10:BB10,"*OK*")+COUNTIF(BK10:BK10,"SI")*0.5 -> 0 | BM10: =IF(BL10<0.6,"Demasiado Riesgo",IF(BL10<=5,"Riesgo Medio",IF(BL10<=11,"Riesgo Bajo","Cliente Blindado"))) -> Demasiado Riesgo | BP10: 0 | CL10: =COUNTIF(AT10:BH10,"*OK*") -> 0 | CN10: =COUNTIF(AT10:BH10,"*OP*") -> 0
A11: 20338 | B11: SAT170927Q91 | C11: =AD11 -> 2258.1678 | D11: =COUNTIF(AT11:BH11,"*OK*") -> 0 | E11: Raúl Campos | F11: SERVICIOS ADMINISTRATIVOS TRANSFORMANDO LA EDUCACION DE MEXICO(Innova Schools) | H11: =IF(LEN(TRIM($G11&""))=0, $C11, SUMIF($G$3:$G$561, TRIM($G11), $C$3:$C$561)) -> 2258.1678 | I11: ENTERPRISE | L11: =HYPERLINK("https://crm.zoho.com/crm/org685875245/tab/Accounts/3525045000188435082","https://crm.zoho.com/crm/org685875245/tab/Accounts/3525045000188435082") -> https://crm.zoho.com/crm/org685875245/tab/Accounts/3525045000188435082 | M11: Mantener | N11: Cliente nos comenta que la baja de marcas se debe al periodo vacacional de abril | O11: Jadiel | P11: 7714167383 | Q11: jadiel.ake@innovaschools.edu.mx | R11: Registrado | U11: - | V11: 2241.41 | W11: 2295.53 | X11: 2210.88 | Y11: 2185.94 | Z11: 2239.7269 | AA11: 2191.06 | AB11: 2197.4221 | AC11: 2465.3354 | AD11: 2258.1678 | AE11: 938 | AF11: 500 | AI11: CDMX | AJ11: Educación | AK11: Red de colegios privados Innova Schools en México, con propuesta educativa innovadora orientada a habilidades del siglo XXI. | AN11: 2. Videollamada | AQ11: Sirve para nómina como relaciones laborales | AR11: Compaq | BJ11: =COUNTIF(AT11:BI11,"*OP*") -> 0 | BL11: =(COUNTIF(AT11:AV11,"*OK*")*3) + (COUNTIF(AW11:AY11,"*OK*")*2) + COUNTIF(AZ11:BB11,"*OK*")+COUNTIF(BK11:BK11,"SI")*0.5 -> 0 | BM11: =IF(BL11<0.6,"Demasiado Riesgo",IF(BL11<=5,"Riesgo Medio",IF(BL11<=11,"Riesgo Bajo","Cliente Blindado"))) -> Demasiado Riesgo | BP11: 0 | CL11: =COUNTIF(AT11:BH11,"*OK*") -> 0 | CN11: =COUNTIF(AT11:BH11,"*OP*") -> 0
A12: 28362 | B12: OOM960429832 | C12: =AD12 -> 2140.3863 | D12: =COUNTIF(AT12:BH12,"*OK*") -> 1 | E12: Raúl Campos | F12: OPERADORA OMX | H12: =IF(LEN(TRIM($G12&""))=0, $C12, SUMIF($G$3:$G$561, TRIM($G12), $C$3:$C$561)) -> 2140.3863 | I12: ENTERPRISE | M12: Alcanzar | O12: Jasiel | P12: 1111111111 | Q12: shantal.reyes@officemax.com.mx | R12: Invitar | U12: - | V12: 2635.78 | W12: 2477.12 | X12: 2238.1 | Y12: 2313.69 | Z12: 2169.8897 | AA12: 2173.35 | AB12: 2337.4804 | AC12: 2365.8489 | AD12: 2140.3863 | AE12: 2225 | AF12: 3000 | AI12: CDMX | AJ12: Retail | AK12: Razón social de OfficeMax México, cadena de 93 tiendas especializadas en artículos de oficina, papelería, tecnología y servicios de impresión. | AN12: 4. Whatsapp | AS12: SI | AT12: OP (Q3) | AU12: OP (Q3) | AV12: OK (negociación inicial) | BJ12: =COUNTIF(AT12:BI12,"*OP*") -> 2 | BK12: NO | BL12: =(COUNTIF(AT12:AV12,"*OK*")*3) + (COUNTIF(AW12:AY12,"*OK*")*2) + COUNTIF(AZ12:BB12,"*OK*")+COUNTIF(BK12:BK12,"SI")*0.5 -> 3 | BM12: =IF(BL12<0.6,"Demasiado Riesgo",IF(BL12<=5,"Riesgo Medio",IF(BL12<=11,"Riesgo Bajo","Cliente Blindado"))) -> Riesgo Medio | BP12: 0 | CL12: =COUNTIF(AT12:BH12,"*OK*") -> 1 | CN12: =COUNTIF(AT12:BH12,"*OP*") -> 2
A13: 21115 | B13: PIM810710R32 | C13: =AD13 -> 2338 | D13: =COUNTIF(AT13:BH13,"*OK*") -> 1 | E13: Raúl Campos | F13: PRODUCTOS INTERNACIONALES MABE | G13: SOFTYS | H13: =IF(LEN(TRIM($G13&""))=0, $C13, SUMIF($G$3:$G$561, TRIM($G13), $C$3:$C$561)) -> 6088.85 | I13: ENTERPRISE | K13: FDP | L13: =HYPERLINK("https://crm.zoho.com/crm/org685875245/tab/Accounts/3525045000133599062","https://crm.zoho.com/crm/org685875245/tab/Accounts/3525045000133599062") -> https://crm.zoho.com/crm/org685875245/tab/Accounts/3525045000133599062 | M13: Mantener | O13: Jessica | P13: 5534151683 | Q13: jessica.romero@softys.com | U13: - | V13: 2338 | W13: 2338 | X13: 2338 | Y13: 2338 | Z13: 2338 | AA13: 2338 | AB13: 2338 | AC13: 2338 | AD13: 2338 | AE13: 3242 | AF13: 3000 | AI13: CDMX | AJ13: Manufactura | AK13: Empresa del Grupo SOFTYS (CMPC), fabricante y distribuidora de productos de consumo masivo para el hogar a nivel nacional e internacional. | AN13: 2. Videollamada | AO13: Diario | AS13: SI | AZ13: OK(092025) | BA13: OP | BJ13: =COUNTIF(AT13:BI13,"*OP*") -> 1 | BK13: NO | BL13: =(COUNTIF(AT13:AV13,"*OK*")*3) + (COUNTIF(AW13:AY13,"*OK*")*2) + COUNTIF(AZ13:BB13,"*OK*")+COUNTIF(BK13:BK13,"SI")*0.5 -> 1 | BM13: =IF(BL13<0.6,"Demasiado Riesgo",IF(BL13<=5,"Riesgo Medio",IF(BL13<=11,"Riesgo Bajo","Cliente Blindado"))) -> Riesgo Medio | CL13: =COUNTIF(AT13:BH13,"*OK*") -> 1 | CN13: =COUNTIF(AT13:BH13,"*OP*") -> 1
A14: 31120 | B14: VAL110809NA0 | C14: =AD14 -> 1952.8145 | D14: =COUNTIF(AT14:BH14,"*OK*") -> 2 | E14: Dafne de la Rosa | F14: VALKIPRO | G14: COPERVA | H14: =IF(LEN(TRIM($G14&""))=0, $C14, SUMIF($G$3:$G$561, TRIM($G14), $C$3:$C$561)) -> 1952.8145 | I14: ENTERPRISE | L14: =HYPERLINK("https://crm.zoho.com/crm/org685875245/tab/Accounts/3525045000467366531","https://crm.zoho.com/crm/org685875245/tab/Accounts/3525045000467366531") -> https://crm.zoho.com/crm/org685875245/tab/Accounts/3525045000467366531 | M14: Expandir | N14: Seguimiento a requerimiento solicitado de SI. Fecha de entrega 07 de julio. | O14: Alejandro | P14: 5560455654 | Q14: avalencia@coperva.com | R14: Invitado | U14: - | V14: 1653.11 | W14: 2016.69 | X14: 1954.18 | Y14: 2017.09 | Z14: 2044.2295 | AA14: 2021.82 | AB14: 1399.2923 | AC14: 2076.353 | AD14: 1952.8145 | AE14: 661 | AF14: 636 | AH14: CDMX | AI14: CDMX | AJ14: Outsourcing | AK14: Empresa de outsourcing especializada en servicios de call center y cobranza, opera bajo la marca Coperva atendiendo a instituciones financieras. | AL14: Call Center Cobranza | AS14: SI | AY14: OK(022026) | AZ14: OK(112025) | BJ14: =COUNTIF(AT14:BI14,"*OP*") -> 0 | BK14: NO | BL14: =(COUNTIF(AT14:AV14,"*OK*")*3) + (COUNTIF(AW14:AY14,"*OK*")*2) + COUNTIF(AZ14:BB14,"*OK*")+COUNTIF(BK14:BK14,"SI")*0.5 -> 3 | BM14: =IF(BL14<0.6,"Demasiado Riesgo",IF(BL14<=5,"Riesgo Medio",IF(BL14<=11,"Riesgo Bajo","Cliente Blindado"))) -> Riesgo Medio | BO14: cobrar a base datos | BP14: 0 | BQ14: Llamada | CL14: =COUNTIF(AT14:BH14,"*OK*") -> 2 | CN14: =COUNTIF(AT14:BH14,"*OP*") -> 0
A15: 3115 | B15: LAP9408085S6 | C15: =AD15 -> 1912.2517 | D15: =COUNTIF(AT15:BH15,"*OK*") -> 0 | E15: Raúl Campos | F15: LAPI | H15: =IF(LEN(TRIM($G15&""))=0, $C15, SUMIF($G$3:$G$561, TRIM($G15), $C$3:$C$561)) -> 1912.2517 | I15: ENTERPRISE | L15: =HYPERLINK("https://crm.zoho.com/crm/org685875245/tab/Accounts/3525045000152712240","https://crm.zoho.com/crm/org685875245/tab/Accounts/3525045000152712240") -> https://crm.zoho.com/crm/org685875245/tab/Accounts/3525045000152712240 | M15: Mantener | N15: Presupuesto anual ir mapeando oportunidad para tenerla lista al final del Q3 Sesión semana del 25 de mayo, se está consiguiendo reu | O15: Alejandro | P15: 5631826460 | Q15: alejandro.martinez@grupolapi.com.mx | R15: Invitado | U15: 15. Planta Productiva | V15: 2009.84 | W15: 2008 | X15: 1913.59 | Y15: 1975.19 | Z15: 2001.7678 | AA15: 1979.82 | AB15: 1996.5198 | AC15: 2033.224 | AD15: 1912.2517 | AE15: 1002 | AF15: 1177 | AI15: CDMX | AJ15: Salud | AK15: Laboratorio médico mexicano con más de 30 años de experiencia, ofrece análisis clínicos, estudios de gabinete e imagenología para empresas e instituciones públicas y privadas. | AN15: 4. Whatsapp | BJ15: =COUNTIF(AT15:BI15,"*OP*") -> 0 | BL15: =(COUNTIF(AT15:AV15,"*OK*")*3) + (COUNTIF(AW15:AY15,"*OK*")*2) + COUNTIF(AZ15:BB15,"*OK*")+COUNTIF(BK15:BK15,"SI")*0.5 -> 0 | BM15: =IF(BL15<0.6,"Demasiado Riesgo",IF(BL15<=5,"Riesgo Medio",IF(BL15<=11,"Riesgo Bajo","Cliente Blindado"))) -> Demasiado Riesgo | BP15: 0 | CL15: =COUNTIF(AT15:BH15,"*OK*") -> 0 | CN15: =COUNTIF(AT15:BH15,"*OP*") -> 0
A16: 31781 | B16: GFS230216MD6 | C16: =AD16 -> 1651.2081 | D16: 1 | E16: Dafne de la Rosa | F16: GRUPO FERROCARRILERO DEL SURESTE | G16: GFS | H16: =IF(LEN(TRIM($G16&""))=0, $C16, SUMIF($G$3:$G$561, TRIM($G16), $C$3:$C$561)) -> 1651.2081 | I16: ENTERPRISE | L16: =HYPERLINK("https://crm.zoho.com/crm/org685875245/tab/Accounts/3525045000478422670","https://crm.zoho.com/crm/org685875245/tab/Accounts/3525045000478422670") -> https://crm.zoho.com/crm/org685875245/tab/Accounts/3525045000478422670 | M16: Expandir | N16: Reu viernes 9am | O16: Adriana | P16: 5219622197821 | Q16: adrianatomas08@gmail.com | R16: No en CDMX | S16: Mapeada en junio, julio, agosto | U16: 3. Construcción | V16: 2193.26 | W16: 2095.65 | X16: 1721.32 | Y16: 1776.73 | Z16: 1831.5447 | AA16: 1806.37 | AB16: 1816.466 | AC16: 1805.3797 | AD16: 1651.2081 | AE16: 822 | AF16: 1260 | AH16: Chiapas | AI16: Chiapas | AJ16: Construcción | AK16: Empresa constructora regional enfocada en obras de infraestructura y proyectos de ingeniería civil en el sureste de México. | AL16: Construcción | AR16: Contpaqi | AS16: SI | AV16: OP (550, puede ser perdido) | AW16: OP | AX16: OP | BJ16: =COUNTIF(AT16:BI16,"*OP*") -> 3 | BL16: =(COUNTIF(AT16:AV16,"*OK*")*3) + (COUNTIF(AW16:AY16,"*OK*")*2) + COUNTIF(AZ16:BB16,"*OK*")+COUNTIF(BK16:BK16,"SI")*0.5 -> 0 | BM16: =IF(BL16<0.6,"Demasiado Riesgo",IF(BL16<=5,"Riesgo Medio",IF(BL16<=11,"Riesgo Bajo","Cliente Blindado"))) -> Demasiado Riesgo | BO16: COBRAR A ISAAC | BP16: 0 | BQ16: Correo y Llamada | CL16: =COUNTIF(AT16:BH16,"*OK*") -> 0 | CN16: =COUNTIF(AT16:BH16,"*OP*") -> 3
A17: 26102 | B17: TFV220408B62 | C17: =AD17 -> 1944.5673 | D17: =COUNTIF(AT17:BH17,"*OK*") -> 1 | E17: Dafne de la Rosa | F17: TAKE FLIGHT VENTURES | G17: BIRDMAN | H17: =IF(LEN(TRIM($G17&""))=0, $C17, SUMIF($G$3:$G$561, TRIM($G17), $C$3:$C$561)) -> 1944.5673 | I17: ENTERPRISE | L17: =HYPERLINK("https://crm.zoho.com/crm/org685875245/tab/Accounts/3525045000344765038","https://crm.zoho.com/crm/org685875245/tab/Accounts/3525045000344765038") -> https://crm.zoho.com/crm/org685875245/tab/Accounts/3525045000344765038 | M17: Mantener | N17: Brinda seguimiento. | O17: Cristo Rodriguez | Q17: c.rodriguez@vidabirdman.com | R17: No en CDMX | S17: Mapeada en agosto | U17: 17. Retail Enterprise | V17: 1244.95 | W17: 1189.61 | X17: 1274.89 | Y17: 1289.62 | Z17: 1283.7946 | AA17: 1467.56 | AB17: 1549.2671 | AC17: 1799.0799 | AD17: 1944.5673 | AE17: 526 | AF17: 150 | AH17: Jalisco | AI17: Jalisco | AJ17: Agrícola | AK17: Empresa de agricultura tecnificada e innovación agropecuaria con operaciones en Jalisco, enfocada en sistemas de cultivo y producción de alimentos. | AL17: Planta Productiva | AS17: SI | AZ17: OK(062025) | BJ17: =COUNTIF(AT17:BI17,"*OP*") -> 0 | BK17: SI | BL17: =(COUNTIF(AT17:AV17,"*OK*")*3) + (COUNTIF(AW17:AY17,"*OK*")*2) + COUNTIF(AZ17:BB17,"*OK*")+COUNTIF(BK17:BK17,"SI")*0.5 -> 1.5 | BM17: =IF(BL17<0.6,"Demasiado Riesgo",IF(BL17<=5,"Riesgo Medio",IF(BL17<=11,"Riesgo Bajo","Cliente Blindado"))) -> Riesgo Medio | BO17: cobro sofia envió correodaf team | BP17: 0 | BQ17: Correo | CL17: =COUNTIF(AT17:BH17,"*OK*") -> 1 | CN17: =COUNTIF(AT17:BH17,"*OP*") -> 0
A18: 26808 | B18: EMS970314UZ7 | C18: =AD18 -> 1620.7506 | D18: =COUNTIF(AT18:BH18,"*OK*") -> 0 | E18: Raúl Campos | F18: EULEN DE SEGURIDAD PRIVADA SA DE CV | G18: EULEN | H18: =IF(LEN(TRIM($G18&""))=0, $C18, SUMIF($G$3:$G$561, TRIM($G18), $C$3:$C$561)) -> 3660.4305 | I18: ENTERPRISE | L18: =HYPERLINK("https://crm.zoho.com/crm/org685875245/tab/Accounts/3525045000269312009","https://crm.zoho.com/crm/org685875245/tab/Accounts/3525045000269312009") -> https://crm.zoho.com/crm/org685875245/tab/Accounts/3525045000269312009 | M18: Expandir | O18: Juan Carlos Espinoza | Q18: jcespinoza@eulen.com | U18: 12. Outsourcing Seguridad | V18: 2001.8 | W18: 1993.95 | X18: 1888.74 | Y18: 1968.47 | Z18: 1954.2222 | AA18: 1945.82 | AB18: 1939.534 | AC18: 1782.8998 | AD18: 1620.7506 | AE18: 3424 | AF18: 3060 | AI18: CDMX | AJ18: Seguridad Privada | AK18: Empresa española EULEN con operaciones en México, proveedora de servicios de seguridad privada, vigilancia y protección para corporativos e industria. | AN18: 1. Reuniones presenciales | AU18: OP (Q3) | AV18: OP (Q3) | AY18: OP (Q4) | BI18: OP | BJ18: =COUNTIF(AT18:BI18,"*OP*") -> 4 | BL18: =(COUNTIF(AT18:AV18,"*OK*")*3) + (COUNTIF(AW18:AY18,"*OK*")*2) + COUNTIF(AZ18:BB18,"*OK*")+COUNTIF(BK18:BK18,"SI")*0.5 -> 0 | BM18: =IF(BL18<0.6,"Demasiado Riesgo",IF(BL18<=5,"Riesgo Medio",IF(BL18<=11,"Riesgo Bajo","Cliente Blindado"))) -> Demasiado Riesgo | BP18: 0 | CL18: =COUNTIF(AT18:BH18,"*OK*") -> 0 | CN18: =COUNTIF(AT18:BH18,"*OP*") -> 3
A19: 37069 | B19: ASU961217L85 | C19: =AD19 -> 1103.7528 | D19: =COUNTIF(AX19:BI19,"OK") -> 0 | E19: Raúl Campos | F19: AFORE SURA | H19: =IF(LEN(TRIM($G19&""))=0, $C19, SUMIF($G$3:$G$561, TRIM($G19), $C$3:$C$561)) -> 1103.7528 | I19: ENTERPRISE | O19: María | P19: 5533971794 | Q19: maria.gudino@suramexico.com | R19: Invitado | T19: SI | Z19: 1019.0818 | AA19: 1007.91 | AB19: 1016.4101 | AC19: 1727.5069 | AD19: 1103.7528 | AE19: 241 | AW19: OP (Q3) | AX19: OP (Q3) | BJ19: =COUNTIF(AT19:BI19,"*OP*") -> 2 | BL19: =(COUNTIF(AT19:AV19,"*OK*")*3) + (COUNTIF(AW19:AY19,"*OK*")*2) + COUNTIF(AZ19:BB19,"*OK*")+COUNTIF(BK19:BK19,"SI")*0.5 -> 0 | BM19: =IF(BL19<0.6,"Demasiado Riesgo",IF(BL19<=5,"Riesgo Medio",IF(BL19<=11,"Riesgo Bajo","Cliente Blindado"))) -> Demasiado Riesgo | BP19: 0 | CL19: =COUNTIF(AT19:BH19,"*OK*") -> 0 | CN19: =COUNTIF(AT19:BH19,"*OP*") -> 2
A20: 32725 | B20: IDI910119FX2 | C20: =AD20 -> 1779.8013 | D20: =COUNTIF(AT20:BH20,"*OK*") -> 1 | E20: Dafne de la Rosa | F20: IMPULSORA DE DESARROLLO INTEGRAL (Idinsa) | G20: IDINSA | H20: =IF(LEN(TRIM($G20&""))=0, $C20, SUMIF($G$3:$G$561, TRIM($G20), $C$3:$C$561)) -> 1779.8013 | I20: ENTERPRISE | L20: =HYPERLINK("https://crm.zoho.com/crm/org685875245/tab/Accounts/3525045000416193121","https://crm.zoho.com/crm/org685875245/tab/Accounts/3525045000416193121") -> https://crm.zoho.com/crm/org685875245/tab/Accounts/3525045000416193121 | M20: Expandir | N20: Seguimiento a proyecto terminado Tlalpan | O20: Benjamin | P20: 5546087437 | Q20: bmondragon@grupoidinsa.com | U20: - | V20: 1621.79 | W20: 1899.63 | X20: 2064.25 | Y20: 2613.52 | Z20: 2817.7265 | AA20: 3838.96 | AB20: 2439.1536 | AC20: 1725.1598 | AD20: 1779.8013 | AE20: 2147 | AF20: 3000 | AH20: CDMX | AI20: CDMX | AJ20: Construcción | AK20: Empresa constructora e inmobiliaria (IDINSA) con operaciones en CDMX, especializada en desarrollo de proyectos de infraestructura y edificación. | AL20: Construcción | AR20: Contpaqi | AS20: SI | AX20: OK (Q2) | BJ20: =COUNTIF(AT20:BI20,"*OP*") -> 0 | BL20: =(COUNTIF(AT20:AV20,"*OK*")*3) + (COUNTIF(AW20:AY20,"*OK*")*2) + COUNTIF(AZ20:BB20,"*OK*")+COUNTIF(BK20:BK20,"SI")*0.5 -> 2 | BM20: =IF(BL20<0.6,"Demasiado Riesgo",IF(BL20<=5,"Riesgo Medio",IF(BL20<=11,"Riesgo Bajo","Cliente Blindado"))) -> Riesgo Medio | BO20: COBRAR A EDGAR | BP20: 0 | BQ20: Llamada | CL20: =COUNTIF(AT20:BH20,"*OK*") -> 1 | CN20: =COUNTIF(AT20:BH20,"*OP*") -> 0
A21: 21102 | B21: FME870213IRA | C21: =AD21 -> 1610.3477 | D21: =COUNTIF(AT21:BH21,"*OK*") -> 0 | E21: Raúl Campos | F21: FRUEHAUF DE MEXICO | H21: =IF(LEN(TRIM($G21&""))=0, $C21, SUMIF($G$3:$G$561, TRIM($G21), $C$3:$C$561)) -> 1610.3477 | I21: ENTERPRISE | L21: =HYPERLINK("https://crm.zoho.com/crm/org685875245/tab/Accounts/3525045000199863226","https://crm.zoho.com/crm/org685875245/tab/Accounts/3525045000199863226") -> https://crm.zoho.com/crm/org685875245/tab/Accounts/3525045000199863226 | M21: Mantener | O21: Miriam Vega Vega granados | P21: +525512482560 | Q21: mvega@fruehauf.mx | U21: 15. Planta Productiva | V21: 1627.97 | W21: 1653.86 | X21: 1582.48 | Y21: 1628.98 | Z21: 1660.2541 | AA21: 1633.05 | AB21: 1662.5564 | AC21: 1701.7468 | AD21: 1610.3477 | AE21: 708 | AF21: 800 | AI21: Estado de México | AJ21: Manufactura | AK21: Líder en fabricación de remolques y semirremolques en México con más de 100 años de historia, con planta en Coacalco EDOMEX. Parte del Grupo Fultra. | AN21: 4. Whatsapp | AS21: SI | AT21: OP (hacer demo) | AU21: OP (Q3-SAP) | AV21: NO- usan SAP | AW21: OP (Q3) | BJ21: =COUNTIF(AT21:BI21,"*OP*") -> 3 | BL21: =(COUNTIF(AT21:AV21,"*OK*")*3) + (COUNTIF(AW21:AY21,"*OK*")*2) + COUNTIF(AZ21:BB21,"*OK*")+COUNTIF(BK21:BK21,"SI")*0.5 -> 0 | BM21: =IF(BL21<0.6,"Demasiado Riesgo",IF(BL21<=5,"Riesgo Medio",IF(BL21<=11,"Riesgo Bajo","Cliente Blindado"))) -> Demasiado Riesgo | BN21: Ambos | BP21: 0 | CL21: =COUNTIF(AT21:BH21,"*OK*") -> 0 | CN21: =COUNTIF(AT21:BH21,"*OP*") -> 3
A22: 3946 | B22: FME140425HBA | C22: =AD22 -> 1605.0248 | D22: =COUNTIF(AT22:BH22,"*OK*") -> 0 | E22: Raúl Campos | F22: FLEX-TEC MEXICO | H22: =IF(LEN(TRIM($G22&""))=0, $C22, SUMIF($G$3:$G$561, TRIM($G22), $C$3:$C$561)) -> 1605.0248 | I22: ENTERPRISE | L22: =HYPERLINK("https://crm.zoho.com/crm/org685875245/tab/Accounts/3525045000025417377","https://crm.zoho.com/crm/org685875245/tab/Accounts/3525045000025417377") -> https://crm.zoho.com/crm/org685875245/tab/Accounts/3525045000025417377 | M22: Expandir | N22: Aún no hay reunión | O22: Arturo benjamín Gomez olivo | P22: +528287683234 | Q22: kary_benjamin@hotmail.com | R22: No están en CDMX | U22: - | V22: 1686.99 | W22: 1802.97 | X22: 1790.42 | Y22: 1873.76 | Z22: 1906.7852 | AA22: 1852.39 | AB22: 1641.9793 | AC22: 1627.1865 | AD22: 1605.0248 | AE22: 685 | AF22: 500 | AI22: Nuevo León | AJ22: Manufactura | AK22: Empresa manufacturera especializada en fabricación de mangueras, ductos y componentes flexibles para uso industrial y automotriz. | AN22: 4. Whatsapp | BJ22: =COUNTIF(AT22:BI22,"*OP*") -> 0 | BL22: =(COUNTIF(AT22:AV22,"*OK*")*3) + (COUNTIF(AW22:AY22,"*OK*")*2) + COUNTIF(AZ22:BB22,"*OK*")+COUNTIF(BK22:BK22,"SI")*0.5 -> 0 | BM22: =IF(BL22<0.6,"Demasiado Riesgo",IF(BL22<=5,"Riesgo Medio",IF(BL22<=11,"Riesgo Bajo","Cliente Blindado"))) -> Demasiado Riesgo | CL22: =COUNTIF(AT22:BH22,"*OK*") -> 0
A23: 24950 | B23: TDS240110H51 | C23: =AD23 -> 1387.4172 | D23: =COUNTIF(AT23:BH23,"*OK*") -> 0 | E23: Raúl Campos | F23: TDSYSTEM | H23: =IF(LEN(TRIM($G23&""))=0, $C23, SUMIF($G$3:$G$561, TRIM($G23), $C$3:$C$561)) -> 1387.4172 | I23: ENTERPRISE | M23: Expandir | N23: Es normal pero por renuencia con algunos centros. Pero con lo de la reforma esta situación debe de ir mejorando. Pagan $17 por usuario, pagaron mucho mucho tiempo hasta los 1000 usuarios a pesar de que tenían menos. | O23: Christian | P23: 5559677516 | Q23: christian_soad@hotmail.com | R23: No están en CDMX | U23: - | V23: 1287.8 | W23: 1324.06 | X23: 1313.45 | Y23: 1206.49 | Z23: 1212.9037 | AA23: 1505.86 | AB23: 1407.0711 | AC23: 1525.6515 | AD23: 1387.4172 | AE23: 1366 | AF23: 1500 | AI23: Puebla | AJ23: Tecnología | AK23: T-Systems México, filial de Deutsche Telekom, proveedora de servicios de tecnología de la información, cloud computing, seguridad y SAP para grandes empresas. | AN23: 4. Whatsapp | AQ23: Generar plan atractivo, han visto varios módulos pero no concretan | AS23: SI | BJ23: =COUNTIF(AT23:BI23,"*OP*") -> 0 | BK23: NO | BL23: =(COUNTIF(AT23:AV23,"*OK*")*3) + (COUNTIF(AW23:AY23,"*OK*")*2) + COUNTIF(AZ23:BB23,"*OK*")+COUNTIF(BK23:BK23,"SI")*0.5 -> 0 | BM23: =IF(BL23<0.6,"Demasiado Riesgo",IF(BL23<=5,"Riesgo Medio",IF(BL23<=11,"Riesgo Bajo","Cliente Blindado"))) -> Demasiado Riesgo | BP23: 0 | CL23: =COUNTIF(AT23:BH23,"*OK*") -> 0 | CN23: =COUNTIF(AT23:BH23,"*OP*") -> 0
A24: 33731 | B24: FRU1410043E6 | C24: =AD24 -> 1368.6534 | D24: =COUNTIF(AT24:BH24,"*OK*") -> 0 | E24: Dafne de la Rosa | F24: FRUNATURAL | H24: =IF(LEN(TRIM($G24&""))=0, $C24, SUMIF($G$3:$G$561, TRIM($G24), $C$3:$C$561)) -> 1368.6534 | I24: ENTERPRISE | L24: =HYPERLINK("https://crm.zoho.com/crm/org685875245/tab/Accounts/3525045000505513537","https://crm.zoho.com/crm/org685875245/tab/Accounts/3525045000505513537") -> https://crm.zoho.com/crm/org685875245/tab/Accounts/3525045000505513537 | M24: Expandir | N24: No tienen autorizado presupuesto. | O24: Paulo | P24: 3321541149 | Q24: recursoshumanos@frunatural.com | R24: Invitado | S24: Mapeada en junio | U24: 22. Turismo, Hotelería y Gastronomía | V24: 1218.08 | W24: 1170.61 | X24: 1135.45 | Y24: 1315.65 | Z24: 1446.5878 | AA24: 1419.3 | AB24: 1428.9665 | AC24: 1471.6669 | AD24: 1368.6534 | AE24: 569 | AF24: 250 | AI24: Jalisco | AJ24: Manufactura | AK24: Empresa productora y comercializadora de frutas y verduras procesadas, jugos y productos naturales con operaciones en Jalisco. | AL24: Produccion | AV24: OP | AW24: NO - turnos fijos | BJ24: =COUNTIF(AT24:BI24,"*OP*") -> 1 | BL24: =(COUNTIF(AT24:AV24,"*OK*")*3) + (COUNTIF(AW24:AY24,"*OK*")*2) + COUNTIF(AZ24:BB24,"*OK*")+COUNTIF(BK24:BK24,"SI")*0.5 -> 0 | BM24: =IF(BL24<0.6,"Demasiado Riesgo",IF(BL24<=5,"Riesgo Medio",IF(BL24<=11,"Riesgo Bajo","Cliente Blindado"))) -> Demasiado Riesgo | BO24: cobro daniela inf en otra base de dat | BP24: 0 | BQ24: Correo y Whats | CL24: =COUNTIF(AT24:BH24,"*OK*") -> 0 | CN24: =COUNTIF(AT24:BH24,"*OP*") -> 1
A25: 17458 | B25: DCM000125IY6 | C25: =AD25 -> 1417.5 | D25: =COUNTIF(AT25:BH25,"*OK*") -> 4 | E25: Raúl Campos | F25: DESPEGAR.COM MEXICO (Bestday) | H25: =IF(LEN(TRIM($G25&""))=0, $C25, SUMIF($G$3:$G$561, TRIM($G25), $C$3:$C$561)) -> 1417.5 | I25: ENTERPRISE | L25: =HYPERLINK("https://crm.zoho.com/crm/org685875245/tab/Accounts/3525045000069562306","https://crm.zoho.com/crm/org685875245/tab/Accounts/3525045000069562306") -> https://crm.zoho.com/crm/org685875245/tab/Accounts/3525045000069562306 | M25: Expandir | O25: Matias | P25: 9981364214 | Q25: matias.corso@despegar.com | R25: Referido best day invitado | U25: - | V25: 1417.5 | W25: 1417.5 | X25: 1417.5 | Y25: 1417.5 | Z25: 1417.5 | AA25: 1417.5 | AB25: 1417.5 | AC25: 1417.5 | AD25: 1417.5 | AE25: 949 | AF25: 800 | AI25: CDMX | AJ25: Turismo y Gastronomía | AK25: Filial mexicana de Despegar.com, la principal agencia de viajes online de Latinoamérica, comercializa vuelos, hoteles y paquetes turísticos. | AN25: 2. Videollamada | AT25: OK(062026) | AV25: OK | AW25: OK(062026) | AX25: OK | BJ25: =COUNTIF(AT25:BI25,"*OP*") -> 0 | BK25: NO | BL25: =(COUNTIF(AT25:AV25,"*OK*")*3) + (COUNTIF(AW25:AY25,"*OK*")*2) + COUNTIF(AZ25:BB25,"*OK*")+COUNTIF(BK25:BK25,"SI")*0.5 -> 10 | BM25: =IF(BL25<0.6,"Demasiado Riesgo",IF(BL25<=5,"Riesgo Medio",IF(BL25<=11,"Riesgo Bajo","Cliente Blindado"))) -> Riesgo Bajo | BP25: 0 | CL25: =COUNTIF(AT25:BH25,"*OK*") -> 4 | CN25: =COUNTIF(AT25:BH25,"*OP*") -> 0
A26: 26081 | B26: AJE010718ET5 | C26: =AD26 -> 1370.9895 | D26: =COUNTIF(AT26:BH26,"*OK*") -> 1 | E26: Raúl Campos | F26: AJEMEX | H26: =IF(LEN(TRIM($G26&""))=0, $C26, SUMIF($G$3:$G$561, TRIM($G26), $C$3:$C$561)) -> 1370.9895 | I26: ENTERPRISE | L26: =HYPERLINK("https://crm.zoho.com/crm/org685875245/tab/Accounts/3525045000316185373","https://crm.zoho.com/crm/org685875245/tab/Accounts/3525045000316185373") -> https://crm.zoho.com/crm/org685875245/tab/Accounts/3525045000316185373 | M26: Expandir | O26: Brigham Lopez | Q26: brigham.lopez@ajemexconsultores.mx | U26: 15. Planta Productiva | V26: 1333.25 | W26: 1406.47 | X26: 1356.38 | Y26: 1365.71 | Z26: 1402.0428 | AA26: 1353.09 | AB26: 1396.1418 | AC26: 1400.4378 | AD26: 1370.9895 | AE26: 943 | AF26: 1500 | AI26: Puebla | AJ26: Manufactura | AK26: Filial mexicana del Grupo AJE, fabricante y distribuidora de bebidas como Big Cola, con planta en Huejotzingo Puebla y distribución nacional. | AN26: 4. Whatsapp | AS26: SI | AW26: OK (Q1) | BB26: OP (Q3) | BI26: OP (Q2) | BJ26: =COUNTIF(AT26:BI26,"*OP*") -> 2 | BK26: NO | BL26: =(COUNTIF(AT26:AV26,"*OK*")*3) + (COUNTIF(AW26:AY26,"*OK*")*2) + COUNTIF(AZ26:BB26,"*OK*")+COUNTIF(BK26:BK26,"SI")*0.5 -> 2 | BM26: =IF(BL26<0.6,"Demasiado Riesgo",IF(BL26<=5,"Riesgo Medio",IF(BL26<=11,"Riesgo Bajo","Cliente Blindado"))) -> Riesgo Medio | BN26: Ambos | BP26: 0 | CL26: =COUNTIF(AT26:BH26,"*OK*") -> 1 | CN26: =COUNTIF(AT26:BH26,"*OP*") -> 1
A27: 38318 | B27: UEE200721NC6 | C27: =AD27 -> 1371.4128 | D27: =COUNTIF(AX27:BI27,"OK") -> 0 | E27: Dafne de la Rosa | F27: UNIVERSIDAD DE EXCELENCIA EDUCATIVA MEXICO (UEEM) | G27: UEEM | H27: =IF(LEN(TRIM($G27&""))=0, $C27, SUMIF($G$3:$G$561, TRIM($G27), $C$3:$C$561)) -> 1371.4128 | I27: ENTERPRISE | L27: =HYPERLINK("https://crm.zoho.com/crm/org685875245/tab/Accounts/3525045000380249726","https://crm.zoho.com/crm/org685875245/tab/Accounts/3525045000380249726") -> https://crm.zoho.com/crm/org685875245/tab/Accounts/3525045000380249726 | O27: Areli | P27: 5555555555 | Q27: coordrecursoshumanos@institutoueem.edu.mx | S27: No pueden ir | T27: SI | U27: 7. Educación | AA27: 1354.16 | AB27: 1368.466 | AC27: 1393.6239 | AD27: 1371.4128 | AE27: 392 | BJ27: =COUNTIF(AT27:BI27,"*OP*") -> 0 | BL27: =(COUNTIF(AT27:AV27,"*OK*")*3) + (COUNTIF(AW27:AY27,"*OK*")*2) + COUNTIF(AZ27:BB27,"*OK*")+COUNTIF(BK27:BK27,"SI")*0.5 -> 0 | BM27: =IF(BL27<0.6,"Demasiado Riesgo",IF(BL27<=5,"Riesgo Medio",IF(BL27<=11,"Riesgo Bajo","Cliente Blindado"))) -> Demasiado Riesgo | BO27: en implementación dar seguiento | BP27: 0 | BQ27: Pendiente | CL27: =COUNTIF(AT27:BH27,"*OK*") -> 0 | CN27: =COUNTIF(AT27:BH27,"*OP*") -> 0
A28: 21541 | B28: PQM140212C74 | C28: =AD28 -> 1276.1038 | D28: =COUNTIF(AT28:BH28,"*OK*") -> 0 | E28: Raúl Campos | F28: PROVEEDORA DE QUIMICOS Y MEDICAMENTOS CARE LAB (DAROVI) | G28: DAROVI | H28: =IF(LEN(TRIM($G28&""))=0, $C28, SUMIF($G$3:$G$561, TRIM($G28), $C$3:$C$561)) -> 2111.8102 | I28: ENTERPRISE | L28: =HYPERLINK("https://crm.zoho.com/crm/org685875245/tab/Accounts/3525045000152361120","https://crm.zoho.com/crm/org685875245/tab/Accounts/3525045000152361120") -> https://crm.zoho.com/crm/org685875245/tab/Accounts/3525045000152361120 | M28: Expandir | N28: Op mapeada | O28: Ruth Ines Loredo leon | P28: +525513333636 | Q28: ruth.loredo@farmacosdarovi.com.mx | U28: - | V28: 1170.52 | W28: 1169.45 | X28: 1114.47 | Y28: 1150.34 | Z28: 2046.1938 | AA28: 1321.19 | AB28: 1332.3384 | AC28: 1356.8323 | AD28: 1276.1038 | AE28: 1099 | AF28: 200 | AI28: CDMX | AJ28: Salud | AK28: Empresa del grupo DAROVI proveedora de químicos, reactivos y medicamentos para el sector salud e industria farmacéutica en México. | AN28: 4. Whatsapp | AQ28: Retomar contacto, admin no contesta mucho. A ella se le puede ofrecer permisos y vacaciones | AV28: OP | AZ28: OP (Q3) | BJ28: =COUNTIF(AT28:BI28,"*OP*") -> 2 | BL28: =(COUNTIF(AT28:AV28,"*OK*")*3) + (COUNTIF(AW28:AY28,"*OK*")*2) + COUNTIF(AZ28:BB28,"*OK*")+COUNTIF(BK28:BK28,"SI")*0.5 -> 0 | BM28: =IF(BL28<0.6,"Demasiado Riesgo",IF(BL28<=5,"Riesgo Medio",IF(BL28<=11,"Riesgo Bajo","Cliente Blindado"))) -> Demasiado Riesgo | CL28: =COUNTIF(AT28:BH28,"*OK*") -> 0
A29: 33503 | B29: GTC1701097U7 | C29: =AD29 -> 916.1148 | D29: =COUNTIF(AT29:BH29,"*OK*") -> 1 | E29: Dafne de la Rosa | F29: GTC TERMO CONTROL | G29: GTC | H29: =IF(LEN(TRIM($G29&""))=0, $C29, SUMIF($G$3:$G$561, TRIM($G29), $C$3:$C$561)) -> 916.1148 | I29: ENTERPRISE | L29: =HYPERLINK("https://crm.zoho.com/crm/org685875245/tab/Accounts/3525045000363350205","https://crm.zoho.com/crm/org685875245/tab/Accounts/3525045000363350205") -> https://crm.zoho.com/crm/org685875245/tab/Accounts/3525045000363350205 | M29: Mantener | N29: Se busca el horario disponible para la demos con SICOSS.* | O29: Aremi | P29: 5218123504160 | Q29: nominas@gtc.com.mx | R29: Invitado | S29: Mapeada en junio | U29: 3. Construcción | V29: 962.87 | W29: 961.98 | X29: 1265.51 | Y29: 1306.25 | Z29: 1323.8242 | AA29: 1552.84 | AB29: 1339.3387 | AC29: 1344.6271 | AD29: 916.1148 | AE29: 428 | AF29: 200 | AH29: CDMX | AI29: CDMX | AJ29: Construcción | AK29: Empresa especializada en sistemas de impermeabilización, aislamiento térmico y control de temperatura para proyectos de construcción industrial y comercial. | AL29: Construcción | AS29: SI | AU29: OP (Q3 - Op con Tada o Sicoss, eligiendo ERP) | AV29: OP (Q3) | AW29: NO - turnos sin mucha rotación | AX29: OK(102025) | BJ29: =COUNTIF(AT29:BI29,"*OP*") -> 2 | BK29: NO | BL29: =(COUNTIF(AT29:AV29,"*OK*")*3) + (COUNTIF(AW29:AY29,"*OK*")*2) + COUNTIF(AZ29:BB29,"*OK*")+COUNTIF(BK29:BK29,"SI")*0.5 -> 2 | BM29: =IF(BL29<0.6,"Demasiado Riesgo",IF(BL29<=5,"Riesgo Medio",IF(BL29<=11,"Riesgo Bajo","Cliente Blindado"))) -> Riesgo Medio | BO29: en base de datos | BP29: 0 | BQ29: Llamada | CL29: =COUNTIF(AT29:BH29,"*OK*") -> 1 | CN29: =COUNTIF(AT29:BH29,"*OP*") -> 2
A30: 34024 | B30: GEA130523698 | C30: =AD30 -> 1235.4305 | D30: =COUNTIF(AT30:BH30,"*OK*") -> 0 | E30: Raúl Campos | F30: GRUPO EMPRESARIAL ARAN (Prestamo Yes) | H30: =IF(LEN(TRIM($G30&""))=0, $C30, SUMIF($G$3:$G$561, TRIM($G30), $C$3:$C$561)) -> 1235.4305 | I30: ENTERPRISE | M30: Alcanzar | O30: Janeth | P30: 8120108953 | Q30: administradorrh@prestamosyes.com | R30: No están en CDMX | U30: 5. Consultoria | V30: 1262.51 | W30: 1310.15 | X30: 1213.82 | Y30: 1280.31 | Z30: 1316.7761 | AA30: 1306.57 | AB30: 1343.1709 | AC30: 1326.6127 | AD30: 1235.4305 | AE30: 329 | AF30: 400 | AI30: CDMX | AJ30: Banca y Finanzas | AK30: Grupo financiero que opera el producto Préstamo Yes, plataforma de préstamos personales y microcréditos para personas y pequeñas empresas en México. | AL30: Banco y Finanzas | AW30: OP (Q2) | BJ30: =COUNTIF(AT30:BI30,"*OP*") -> 1 | BL30: =(COUNTIF(AT30:AV30,"*OK*")*3) + (COUNTIF(AW30:AY30,"*OK*")*2) + COUNTIF(AZ30:BB30,"*OK*")+COUNTIF(BK30:BK30,"SI")*0.5 -> 0 | BM30: =IF(BL30<0.6,"Demasiado Riesgo",IF(BL30<=5,"Riesgo Medio",IF(BL30<=11,"Riesgo Bajo","Cliente Blindado"))) -> Demasiado Riesgo | BP30: 0 | CL30: =COUNTIF(AT30:BH30,"*OK*") -> 0 | CN30: =COUNTIF(AT30:BH30,"*OP*") -> 1
A31: 26808 | B31: EMS970314UZ7 | C31: =AD31 -> 1259.0508 | D31: =COUNTIF(AT31:BH31,"*OK*") -> 0 | E31: Raúl Campos | F31: EULEN MEXICO DE SERVICIOS SA DE CV | G31: EULEN | H31: =IF(LEN(TRIM($G31&""))=0, $C31, SUMIF($G$3:$G$561, TRIM($G31), $C$3:$C$561)) -> 3660.4305 | I31: ENTERPRISE | L31: =HYPERLINK("https://crm.zoho.com/crm/org685875245/tab/Accounts/3525045000269312009","https://crm.zoho.com/crm/org685875245/tab/Accounts/3525045000269312009") -> https://crm.zoho.com/crm/org685875245/tab/Accounts/3525045000269312009 | M31: Expandir | U31: - | V31: 1227.06 | W31: 1269.21 | X31: 1157.99 | Y31: 1184.6 | Z31: 1204.1803 | AA31: 1200.46 | AB31: 1198.6033 | AC31: 1310.7107 | AD31: 1259.0508 | AE31: 3424 | AF31: 3060 | AI31: CDMX | AJ31: Outsourcing | AK31: Filial mexicana del Grupo EULEN España, proveedora de servicios de limpieza, mantenimiento y facility management para grandes corporativos. | AN31: 1. Reuniones presenciales | AW31: OP | BJ31: =COUNTIF(AT31:BI31,"*OP*") -> 1 | BL31: =(COUNTIF(AT31:AV31,"*OK*")*3) + (COUNTIF(AW31:AY31,"*OK*")*2) + COUNTIF(AZ31:BB31,"*OK*")+COUNTIF(BK31:BK31,"SI")*0.5 -> 0 | BM31: =IF(BL31<0.6,"Demasiado Riesgo",IF(BL31<=5,"Riesgo Medio",IF(BL31<=11,"Riesgo Bajo","Cliente Blindado"))) -> Demasiado Riesgo | BP31: 0 | CL31: =COUNTIF(AT31:BH31,"*OK*") -> 0 | CN31: =COUNTIF(AT31:BH31,"*OP*") -> 1
A32: 36114 | B32: ASC951228IM0 | C32: =AD32 -> 1184.4371 | D32: =COUNTIF(AT32:BH32,"*OK*") -> 0 | E32: Dafne de la Rosa | F32: ALMACENADORA SUR SA DE CV ORGANIZACION AUXILIAR DEL CREDITO | H32: =IF(LEN(TRIM($G32&""))=0, $C32, SUMIF($G$3:$G$561, TRIM($G32), $C$3:$C$561)) -> 1184.4371 | I32: ENTERPRISE | L32: =HYPERLINK("https://crm.zoho.com/crm/org685875245/tab/Accounts/3525045000417780328","https://crm.zoho.com/crm/org685875245/tab/Accounts/3525045000417780328") -> https://crm.zoho.com/crm/org685875245/tab/Accounts/3525045000417780328 | O32: David | P32: 5619964263 | Q32: david.rocha@alsur.com.mx | R32: No pueden ir | T32: SI | U32: - | X32: 770.08 | Y32: 806.84 | Z32: 807.9863 | AA32: 885.52 | AB32: 1079.3307 | AC32: 1298.7988 | AD32: 1184.4371 | AE32: 490 | AF32: 500 | AI32: CDMX | AJ32: Logística | AK32: Organización auxiliar del crédito dedicada a servicios de almacenamiento, certificación de inventarios y financiamiento sobre mercancías en depósito. | BJ32: =COUNTIF(AT32:BI32,"*OP*") -> 0 | BL32: =(COUNTIF(AT32:AV32,"*OK*")*3) + (COUNTIF(AW32:AY32,"*OK*")*2) + COUNTIF(AZ32:BB32,"*OK*")+COUNTIF(BK32:BK32,"SI")*0.5 -> 0 | BM32: =IF(BL32<0.6,"Demasiado Riesgo",IF(BL32<=5,"Riesgo Medio",IF(BL32<=11,"Riesgo Bajo","Cliente Blindado"))) -> Demasiado Riesgo | BO32: implementación dar seguimiento | BP32: 0 | BQ32: Pendiente | CL32: =COUNTIF(AT32:BH32,"*OK*") -> 0 | CN32: =COUNTIF(AT32:BH32,"*OP*") -> 0
A33: 6588 | B33: SHN571001I66 | C33: =AD33 -> 1211.0927 | D33: =COUNTIF(AT33:BH33,"*OK*") -> 1 | E33: Raúl Campos | F33: SCHETTINO | G33: SCHETTINO | H33: =IF(LEN(TRIM($G33&""))=0, $C33, SUMIF($G$3:$G$561, TRIM($G33), $C$3:$C$561)) -> 2091.1148 | I33: ENTERPRISE | L33: =HYPERLINK("https://crm.zoho.com/crm/org685875245/tab/Accounts/3525045000079373188","https://crm.zoho.com/crm/org685875245/tab/Accounts/3525045000079373188") -> https://crm.zoho.com/crm/org685875245/tab/Accounts/3525045000079373188 | M33: Mantener | O33: Varios | Q33: lespinoza@schettino.com.mx marina.la.0891@gmail.com mlujan@schettino.com.mx josecarmelomendez_@hotmail.com nominas@mexicanadearroz.com.mx denniel.sevilla@gmail.com | R33: No están en CDMX | U33: 15. Planta Productiva | V33: 1803.81 | W33: 1787.44 | X33: 1790.94 | Y33: 1778.47 | Z33: 1512.3312 | AA33: 1823.83 | AB33: 1825.5624 | AC33: 1282.134 | AD33: 1211.0927 | AE33: 858 | AF33: 800 | AI33: CDMX | AJ33: Manufactura | AK33: Grupo alimentario mexicano productor de arroz, salsas y alimentos procesados, con distribución nacional a través de múltiples marcas y plantas de producción. | AN33: 4. Whatsapp | AS33: SI | AT33: OP (Q3) | BD33: OK ($0) | BJ33: =COUNTIF(AT33:BI33,"*OP*") -> 1 | BK33: NO | BL33: =(COUNTIF(AT33:AV33,"*OK*")*3) + (COUNTIF(AW33:AY33,"*OK*")*2) + COUNTIF(AZ33:BB33,"*OK*")+COUNTIF(BK33:BK33,"SI")*0.5 -> 0 | BM33: =IF(BL33<0.6,"Demasiado Riesgo",IF(BL33<=5,"Riesgo Medio",IF(BL33<=11,"Riesgo Bajo","Cliente Blindado"))) -> Demasiado Riesgo | BP33: 0 | CL33: =COUNTIF(AT33:BH33,"*OK*") -> 1 | CN33: =COUNTIF(AT33:BH33,"*OP*") -> 1
A34: 20005 | B34: OCM050331BC9 | C34: =AD34 -> 1606.2913 | D34: =COUNTIF(AT34:BH34,"*OK*") -> 1 | E34: Raúl Campos | F34: CONCESIONARIA MEXIQUENSE | G34: ALEATICA | H34: =IF(LEN(TRIM($G34&""))=0, $C34, SUMIF($G$3:$G$561, TRIM($G34), $C$3:$C$561)) -> 4240.7286 | I34: ENTERPRISE | K34: FDP | M34: Mantener | N34: Tienen Formas de Pago y Personalizaciones | O34: Monica | P34: 5560790550 | Q34: monica.espino@aleatica.com | R34: Registrado | U34: - | V34: i | W34: 1242.47 | X34: 1190.68 | Y34: 1226.73 | Z34: 1233.9902 | AA34: 1231.89 | AB34: 1239.9742 | AC34: 1281.5472 | AD34: 1606.2913 | AE34: 1417 | AF34: 500 | AI34: Estado de México | AJ34: Transporte | AK34: Empresa concesionaria del Grupo Aleatica que opera la autopista Circuito Exterior Mexiquense, red vial de peaje en el Estado de México. | AN34: 2. Videollamada | AY34: OK(102025) | BJ34: =COUNTIF(AT34:BI34,"*OP*") -> 0 | BL34: =(COUNTIF(AT34:AV34,"*OK*")*3) + (COUNTIF(AW34:AY34,"*OK*")*2) + COUNTIF(AZ34:BB34,"*OK*")+COUNTIF(BK34:BK34,"SI")*0.5 -> 2 | BM34: =IF(BL34<0.6,"Demasiado Riesgo",IF(BL34<=5,"Riesgo Medio",IF(BL34<=11,"Riesgo Bajo","Cliente Blindado"))) -> Riesgo Medio | BP34: 0 | CL34: =COUNTIF(AT34:BH34,"*OK*") -> 1 | CN34: =COUNTIF(AT34:BH34,"*OP*") -> 0
A35: 22501 | B35: PLQ9002286Q6 | C35: =AD35 -> 1401.5552 | D35: =COUNTIF(AT35:BH35,"*OK*") -> 2 | E35: Dafne de la Rosa | F35: PRODUCTOS LACTEOS LA QUINTA | H35: =IF(LEN(TRIM($G35&""))=0, $C35, SUMIF($G$3:$G$561, TRIM($G35), $C$3:$C$561)) -> 1401.5552 | I35: ENTERPRISE | L35: =HYPERLINK("https://crm.zoho.com/crm/org685875245/tab/Accounts/3525045000240910580","https://crm.zoho.com/crm/org685875245/tab/Accounts/3525045000240910580") -> https://crm.zoho.com/crm/org685875245/tab/Accounts/3525045000240910580 | M35: Mantener | N35: Solicito un equipo mas. | O35: Victor daniel Alvarado reyes | P35: +524423919373 | Q35: valvarado@lacteoslaquinta.com.mx | U35: 15. Planta Productiva | V35: 1167.9 | W35: 1166.83 | X35: 1156.68 | Y35: 1205.44 | Z35: 1250.8895 | AA35: 1248.74 | AB35: 1128.0958 | AC35: 1252.7348 | AD35: 1401.5552 | AE35: 489 | AF35: 200 | AH35: Queretaro | AI35: Querétaro | AJ35: Manufactura | AK35: Empresa productora de lácteos como leche, quesos y derivados en Querétaro, con distribución regional en el Bajío y zona centro de México. | AL35: Planta Productiva | AS35: SI | AV35: OK(092024) | AX35: OK(092024) | BJ35: =COUNTIF(AT35:BI35,"*OP*") -> 0 | BK35: NO | BL35: =(COUNTIF(AT35:AV35,"*OK*")*3) + (COUNTIF(AW35:AY35,"*OK*")*2) + COUNTIF(AZ35:BB35,"*OK*")+COUNTIF(BK35:BK35,"SI")*0.5 -> 5 | BM35: =IF(BL35<0.6,"Demasiado Riesgo",IF(BL35<=5,"Riesgo Medio",IF(BL35<=11,"Riesgo Bajo","Cliente Blindado"))) -> Riesgo Medio | BO35: victor albarado | BP35: 0 | BQ35: Correo y Llamada | CL35: =COUNTIF(AT35:BH35,"*OK*") -> 2 | CN35: =COUNTIF(AT35:BH35,"*OP*") -> 0
A36: 37414 | B36: TER060227LR4 | C36: =AD36 -> 1176.1589 | D36: =COUNTIF(AX36:BI36,"OK") -> 0 | E36: Raúl Campos | F36: TRANSPORTES ESPECIALIZADOS RUGA | H36: =IF(LEN(TRIM($G36&""))=0, $C36, SUMIF($G$3:$G$561, TRIM($G36), $C$3:$C$561)) -> 1176.1589 | I36: ENTERPRISE | L36: =HYPERLINK("https://crm.zoho.com/crm/org685875245/tab/Accounts/3525045000578056486","https://crm.zoho.com/crm/org685875245/tab/Accounts/3525045000578056486") -> https://crm.zoho.com/crm/org685875245/tab/Accounts/3525045000578056486 | O36: Fernanda | P36: +52 1 55 4186 6494 | T36: SI | U36: 16. Logistica | X36: 1718 | Y36: 1755.95 | Z36: 1702.9758 | AA36: 1716.36 | AB36: 1275.6983 | AC36: 1252.6772 | AD36: 1176.1589 | AE36: 598 | AL36: Logística | BJ36: =COUNTIF(AT36:BI36,"*OP*") -> 0 | BL36: =(COUNTIF(AT36:AV36,"*OK*")*3) + (COUNTIF(AW36:AY36,"*OK*")*2) + COUNTIF(AZ36:BB36,"*OK*")+COUNTIF(BK36:BK36,"SI")*0.5 -> 0 | BM36: =IF(BL36<0.6,"Demasiado Riesgo",IF(BL36<=5,"Riesgo Medio",IF(BL36<=11,"Riesgo Bajo","Cliente Blindado"))) -> Demasiado Riesgo | BP36: 0 | CL36: =COUNTIF(AT36:BH36,"*OK*") -> 0 | CN36: =COUNTIF(AT36:BH36,"*OP*") -> 0
A37: 26084 | B37: GSO060706CM5 | C37: =AD37 -> 1232.1274 | D37: =COUNTIF(AT37:BH37,"*OK*") -> 1 | E37: Dafne de la Rosa | F37: GLORY GLOBAL SOLUTIONS MEXICO | H37: =IF(LEN(TRIM($G37&""))=0, $C37, SUMIF($G$3:$G$561, TRIM($G37), $C$3:$C$561)) -> 1232.1274 | I37: ENTERPRISE | L37: =HYPERLINK("https://crm.zoho.com/crm/org685875245/tab/Accounts/3525045000212428171","https://crm.zoho.com/crm/org685875245/tab/Accounts/3525045000212428171") -> https://crm.zoho.com/crm/org685875245/tab/Accounts/3525045000212428171 | M37: Mantener | N37: Se tiene reunion con la TI aignada el 23 de junio para validar reunion con cliente. | O37: Aída Adsali Rojas Sánchez | P37: +525627178422 | Q37: aida.rojas@mx.glory-global.com | R37: Invitado | U37: 20. Servicios | V37: 1089.82 | W37: 1088.82 | X37: 1031.23 | Y37: 1061.12 | Z37: 831.4564 | AA37: 834.69 | AB37: 859.1604 | AC37: 1252.2266 | AD37: 1232.1274 | AE37: 374 | AF37: 324 | AH37: CDMX | AI37: CDMX | AJ37: Tecnología | AK37: Filial mexicana de Glory Global Solutions, empresa japonesa especializada en soluciones de automatización para manejo de efectivo, cajas registradoras y equipos bancarios. | AL37: Servicios | AS37: SI | AU37: OP (ERP) | AX37: OK(052025) | BJ37: =COUNTIF(AT37:BI37,"*OP*") -> 1 | BK37: NO | BL37: =(COUNTIF(AT37:AV37,"*OK*")*3) + (COUNTIF(AW37:AY37,"*OK*")*2) + COUNTIF(AZ37:BB37,"*OK*")+COUNTIF(BK37:BK37,"SI")*0.5 -> 2 | BM37: =IF(BL37<0.6,"Demasiado Riesgo",IF(BL37<=5,"Riesgo Medio",IF(BL37<=11,"Riesgo Bajo","Cliente Blindado"))) -> Riesgo Medio | BO37: base de datos | BP37: 0 | BQ37: correo mensaje | CL37: =COUNTIF(AT37:BH37,"*OK*") -> 1 | CN37: =COUNTIF(AT37:BH37,"*OP*") -> 1
A38: 21150 | B38: ACM040107U93 | C38: =AD38 -> 1250 | D38: =COUNTIF(AT38:BH38,"*OK*") -> 2 | E38: Raúl Campos | F38: ALIMENTOS CENTRALIZADOS DE MEXICO (AxionLog) | H38: =IF(LEN(TRIM($G38&""))=0, $C38, SUMIF($G$3:$G$561, TRIM($G38), $C$3:$C$561)) -> 1250 | I38: ENTERPRISE | L38: =HYPERLINK("https://crm.zoho.com/crm/org685875245/tab/Accounts/3525045000188390027","https://crm.zoho.com/crm/org685875245/tab/Accounts/3525045000188390027") -> https://crm.zoho.com/crm/org685875245/tab/Accounts/3525045000188390027 | M38: Mantener | N38: Se está cerrando anualidad, si incluyen los modulos dentro, aplicar dcto | O38: JIMEN SABRINA SABRINA MIJALOVICH | P38: +525550915700 | Q38: jimena.mijalovich@axionlog.com | R38: Registrado | U38: 16. Logistica | V38: 1359.76 | W38: 1358.51 | X38: 1294.64 | Y38: 1336.32 | Z38: 1288 | AA38: 1250 | AB38: 1250 | AC38: 1250 | AD38: 1250 | AE38: 1285 | AF38: 300 | AI38: CDMX | AJ38: Manufactura | AK38: Empresa dedicada a la producción y distribución centralizada de alimentos procesados y preparados para el sector institucional y de consumo masivo. | AN38: 4. Whatsapp | AR38: SAP | AV38: OK(032025) | AX38: OK(032025) | BJ38: =COUNTIF(AT38:BI38,"*OP*") -> 0 | BL38: =(COUNTIF(AT38:AV38,"*OK*")*3) + (COUNTIF(AW38:AY38,"*OK*")*2) + COUNTIF(AZ38:BB38,"*OK*")+COUNTIF(BK38:BK38,"SI")*0.5 -> 5 | BM38: =IF(BL38<0.6,"Demasiado Riesgo",IF(BL38<=5,"Riesgo Medio",IF(BL38<=11,"Riesgo Bajo","Cliente Blindado"))) -> Riesgo Medio | BP38: 0 | CL38: =COUNTIF(AT38:BH38,"*OK*") -> 2 | CN38: =COUNTIF(AT38:BH38,"*OP*") -> 0
A39: 20103 | B39: CRM191212EV3 | C39: =AD39 -> 1103.5833 | D39: =COUNTIF(AT39:BH39,"*OK*") -> 0 | E39: Raúl Campos | F39: CORPORACION DE RESTAURANTES MAXIMUS | H39: =IF(LEN(TRIM($G39&""))=0, $C39, SUMIF($G$3:$G$561, TRIM($G39), $C$3:$C$561)) -> 1103.5833 | I39: ENTERPRISE | L39: =HYPERLINK("https://crm.zoho.com/crm/org685875245/tab/Accounts/3525045000394740282","https://crm.zoho.com/crm/org685875245/tab/Accounts/3525045000394740282") -> https://crm.zoho.com/crm/org685875245/tab/Accounts/3525045000394740282 | M39: Alcanzar | N39: El contacto es más con la persona de sistemas. | O39: Arturo | P39: 5555555555 | Q39: it@grupomaximus.com.mx | R39: Registrado | U39: - | V39: 1299.95 | W39: 1216.24 | X39: 1172.74 | Y39: 1203.43 | Z39: 1183.857 | AA39: 1174.41 | AB39: 1219.9929 | AC39: 1224.2573 | AD39: 1103.5833 | AE39: 384 | AF39: 600 | AI39: CDMX | AJ39: Turismo y Gastronomía | AK39: Corporativo restaurantero que opera múltiples marcas y conceptos de gastronomía en México, con presencia en centros comerciales y zonas comerciales del país. | AN39: 4. Whatsapp | AT39: OP (Q3) | AV39: OP (Q3) | AW39: OP (Q3) | BA39: OP (Q3) | BJ39: =COUNTIF(AT39:BI39,"*OP*") -> 4 | BL39: =(COUNTIF(AT39:AV39,"*OK*")*3) + (COUNTIF(AW39:AY39,"*OK*")*2) + COUNTIF(AZ39:BB39,"*OK*")+COUNTIF(BK39:BK39,"SI")*0.5 -> 0 | BM39: =IF(BL39<0.6,"Demasiado Riesgo",IF(BL39<=5,"Riesgo Medio",IF(BL39<=11,"Riesgo Bajo","Cliente Blindado"))) -> Demasiado Riesgo | BP39: 0 | CL39: =COUNTIF(AT39:BH39,"*OK*") -> 0 | CN39: =COUNTIF(AT39:BH39,"*OP*") -> 4
A40: 26664 | B40: BAC920106U98 | C40: =AD40 -> 1212.7483 | D40: =COUNTIF(AT40:BH40,"*OK*") -> 0 | E40: Raúl Campos | F40: BIODIST (DICIPA) | H40: =IF(LEN(TRIM($G40&""))=0, $C40, SUMIF($G$3:$G$561, TRIM($G40), $C$3:$C$561)) -> 1212.7483 | I40: ENTERPRISE | L40: =HYPERLINK("https://crm.zoho.com/crm/org685875245/tab/Accounts/3525045000118304484","https://crm.zoho.com/crm/org685875245/tab/Accounts/3525045000118304484") -> https://crm.zoho.com/crm/org685875245/tab/Accounts/3525045000118304484 | M40: Mantener | O40: Karla | P40: 5550932000 | Q40: samantha.macias@dicipa.com.mx | R40: Registrado | U40: - | V40: 1092.5 | W40: 1104.54 | X40: 1079.95 | Y40: 1118.99 | Z40: 1158.5989 | AA40: 1154.47 | AB40: 1193.0142 | AC40: 1222.8683 | AD40: 1212.7483 | AE40: 1110 | AF40: 200 | AI40: CDMX | AJ40: Salud | AK40: Distribuidora farmacéutica del grupo DICIPA, especializada en distribución de medicamentos y productos biotecnológicos para el sector salud. | AN40: 2. Videollamada | AS40: SI | BJ40: =COUNTIF(AT40:BI40,"*OP*") -> 0 | BK40: NO | BL40: =(COUNTIF(AT40:AV40,"*OK*")*3) + (COUNTIF(AW40:AY40,"*OK*")*2) + COUNTIF(AZ40:BB40,"*OK*")+COUNTIF(BK40:BK40,"SI")*0.5 -> 0 | BM40: =IF(BL40<0.6,"Demasiado Riesgo",IF(BL40<=5,"Riesgo Medio",IF(BL40<=11,"Riesgo Bajo","Cliente Blindado"))) -> Demasiado Riesgo | BP40: 0 | CL40: =COUNTIF(AT40:BH40,"*OK*") -> 0 | CN40: =COUNTIF(AT40:BH40,"*OP*") -> 0
A41: 34962 | B41: CTS160922QLA | C41: =AD41 -> 1276.3797 | D41: =COUNTIF(AT41:BH41,"*OK*") -> 0 | E41: Raúl Campos | F41: CORPORATE TRAVEL SERVICES WORLDWIDE (Altour) | H41: =IF(LEN(TRIM($G41&""))=0, $C41, SUMIF($G$3:$G$561, TRIM($G41), $C$3:$C$561)) -> 1276.3797 | I41: ENTERPRISE | L41: =HYPERLINK("https://crm.zoho.com/crm/org685875245/tab/Accounts/3525045000375387064","https://crm.zoho.com/crm/org685875245/tab/Accounts/3525045000375387064") -> https://crm.zoho.com/crm/org685875245/tab/Accounts/3525045000375387064 | O41: Viridiana | P41: 5546354050 | Q41: VVILLA@ALTOUR.MX | T41: SI | U41: 20. Servicios | V41: 1148.48 | W41: 1220.45 | X41: 1113.36 | Y41: 1128.68 | Z41: 1143.8673 | AA41: 1203.32 | AB41: 1196.8747 | AC41: 1216.7657 | AD41: 1276.3797 | AE41: 569 | AF41: 60000 | AI41: CDMX | AJ41: Turismo y Gastronomía | AK41: Agencia de viajes corporativos (Altour) especializada en gestión de viajes de negocios, reservaciones y logística de eventos para empresas. | AW41: OP(Q3) | AY41: OP(Q3) | BJ41: =COUNTIF(AT41:BI41,"*OP*") -> 2 | BL41: =(COUNTIF(AT41:AV41,"*OK*")*3) + (COUNTIF(AW41:AY41,"*OK*")*2) + COUNTIF(AZ41:BB41,"*OK*")+COUNTIF(BK41:BK41,"SI")*0.5 -> 0 | BM41: =IF(BL41<0.6,"Demasiado Riesgo",IF(BL41<=5,"Riesgo Medio",IF(BL41<=11,"Riesgo Bajo","Cliente Blindado"))) -> Demasiado Riesgo | BP41: 0 | CL41: =COUNTIF(AT41:BH41,"*OK*") -> 0 | CN41: =COUNTIF(AT41:BH41,"*OP*") -> 2
A42: 32312 | B42: Y5459737101 | C42: =AD42 -> 1167.7704 | D42: =COUNTIF(AT42:BH42,"*OK*") -> 0 | E42: Dafne de la Rosa | F42: LATAM LOGISTICS (TOUS) | G42: TOUS | H42: =IF(LEN(TRIM($G42&""))=0, $C42, SUMIF($G$3:$G$561, TRIM($G42), $C$3:$C$561)) -> 1167.7704 | I42: ENTERPRISE | M42: Expandir | N42: Reu lunes 7 | O42: Enmanuelle | P42: 5215651211275 | Q42: elopezr@tous.com | R42: Invitado | S42: Mapeada en agosto | U42: - | V42: 1044.07 | W42: 1388.5 | X42: 1179.63 | Y42: 1219.89 | Z42: 1217.8143 | AA42: 1247.89 | AB42: 1219.2311 | AC42: 1154.8008 | AD42: 1167.7704 | AE42: 531 | AF42: 300 | AH42: CDMX | AI42: CDMX | AJ42: Logística | AK42: Empresa de logística y distribución que opera la cadena de suministro para marcas como TOUS en México, con servicios de almacenaje y última milla. | AL42: Retail | AR42: Contpaqi | BJ42: =COUNTIF(AT42:BI42,"*OP*") -> 0 | BL42: =(COUNTIF(AT42:AV42,"*OK*")*3) + (COUNTIF(AW42:AY42,"*OK*")*2) + COUNTIF(AZ42:BB42,"*OK*")+COUNTIF(BK42:BK42,"SI")*0.5 -> 0 | BM42: =IF(BL42<0.6,"Demasiado Riesgo",IF(BL42<=5,"Riesgo Medio",IF(BL42<=11,"Riesgo Bajo","Cliente Blindado"))) -> Demasiado Riesgo | BO42: base de datos | BP42: 0 | BQ42: Correo y Llamada | CL42: =COUNTIF(AT42:BH42,"*OK*") -> 0 | CN42: =COUNTIF(AT42:BH42,"*OP*") -> 0
A43: 31768 | B43: HUGA6603043Y5 | C43: =AD43 -> 1051.2152 | D43: =COUNTIF(AT43:BH43,"*OK*") -> 0 | E43: Karla Patiño | F43: ANTONIO HUERTA GARZA (Comex) | H43: =IF(LEN(TRIM($G43&""))=0, $C43, SUMIF($G$3:$G$561, TRIM($G43), $C$3:$C$561)) -> 1051.2152 | I43: ENTERPRISE | M43: Mantener | O43: Hannia | P43: 2321189646 | Q43: hanniaricano@icloud.com | U43: - | V43: 413.5 | W43: 399.9 | X43: 1036.2 | Y43: 1072.81 | Z43: 1083.9512 | AA43: 1046 | AB43: 1127.1141 | AC43: 1147.835 | AD43: 1051.2152 | AE43: 333 | AF43: 50 | AI43: Durango | AJ43: Retail | AK43: Persona física o empresa familiar relacionada con la distribución y comercialización de materiales y productos en la región de Durango, posiblemente vinculada al sector de materiales para construcción. | AS43: SI | BJ43: =COUNTIF(AT43:BI43,"*OP*") -> 0 | BK43: NO | BL43: =(COUNTIF(AT43:AV43,"*OK*")*3) + (COUNTIF(AW43:AY43,"*OK*")*2) + COUNTIF(AZ43:BB43,"*OK*")+COUNTIF(BK43:BK43,"SI")*0.5 -> 0 | BM43: =IF(BL43<0.6,"Demasiado Riesgo",IF(BL43<=5,"Riesgo Medio",IF(BL43<=11,"Riesgo Bajo","Cliente Blindado"))) -> Demasiado Riesgo | BP43: 0 | CL43: =COUNTIF(AT43:BH43,"*OK*") -> 0 | CN43: =COUNTIF(AT43:BH43,"*OP*") -> 0
A44: 20569 | B44: GCM920629960 | C44: =AD44 -> 1085.0993 | D44: =COUNTIF(AT44:BH44,"*OK*") -> 0 | E44: Raúl Campos | F44: GRUPO CONVERSE DE MEXICO | H44: =IF(LEN(TRIM($G44&""))=0, $C44, SUMIF($G$3:$G$561, TRIM($G44), $C$3:$C$561)) -> 1085.0993 | I44: ENTERPRISE | L44: =HYPERLINK("https://crm.zoho.com/crm/org685875245/tab/Accounts/3525045000191388216","https://crm.zoho.com/crm/org685875245/tab/Accounts/3525045000191388216") -> https://crm.zoho.com/crm/org685875245/tab/Accounts/3525045000191388216 | M44: Mantener | O44: Kimberly | P44: 5615932702 | Q44: kimberly.arizmendi@converse.com.mx | R44: No están en CDMX | U44: 17. Retail Enterprise | V44: 1389.15 | W44: 1273.66 | X44: 1165.78 | Y44: 1134.58 | Z44: 1148.6219 | AA44: 1100.12 | AB44: 1133.8965 | AC44: 1128.1987 | AD44: 1085.0993 | AE44: 328 | AF44: 800 | AI44: CDMX | AJ44: Retail | AK44: Operadora de la marca Converse en México, gestiona tiendas de calzado y accesorios deportivos en los principales centros comerciales del país. | AN44: 4. Whatsapp | AS44: SI | BJ44: =COUNTIF(AT44:BI44,"*OP*") -> 0 | BK44: NO | BL44: =(COUNTIF(AT44:AV44,"*OK*")*3) + (COUNTIF(AW44:AY44,"*OK*")*2) + COUNTIF(AZ44:BB44,"*OK*")+COUNTIF(BK44:BK44,"SI")*0.5 -> 0 | BM44: =IF(BL44<0.6,"Demasiado Riesgo",IF(BL44<=5,"Riesgo Medio",IF(BL44<=11,"Riesgo Bajo","Cliente Blindado"))) -> Demasiado Riesgo | BP44: 0 | CL44: =COUNTIF(AT44:BH44,"*OK*") -> 0 | CN44: =COUNTIF(AT44:BH44,"*OP*") -> 0
A45: 34609 | B45: DGF920601FY6 | C45: =AD45 -> 1041.9426 | D45: =COUNTIF(AX45:BI45,"OK") -> 0 | E45: Dafne de la Rosa | F45: DHL GLOBAL FORWARDING (MEXICO) | H45: =IF(LEN(TRIM($G45&""))=0, $C45, SUMIF($G$3:$G$561, TRIM($G45), $C$3:$C$561)) -> 1041.9426 | I45: ENTERPRISE | N45: Asignar a Dafne | O45: Miguel | P45: 5543397940 | Q45: miguel.castillo2@dhl.com | T45: SI | Z45: 1035.2577 | AA45: 1051.33 | AB45: 1097.0775 | AC45: 1105.5105 | AD45: 1041.9426 | AE45: 465 | BJ45: =COUNTIF(AT45:BI45,"*OP*") -> 0 | BL45: =(COUNTIF(AT45:AV45,"*OK*")*3) + (COUNTIF(AW45:AY45,"*OK*")*2) + COUNTIF(AZ45:BB45,"*OK*")+COUNTIF(BK45:BK45,"SI")*0.5 -> 0 | BM45: =IF(BL45<0.6,"Demasiado Riesgo",IF(BL45<=5,"Riesgo Medio",IF(BL45<=11,"Riesgo Bajo","Cliente Blindado"))) -> Demasiado Riesgo | BO45: implementación dar seguimiento | BP45: 0 | BQ45: Pendiente | CL45: =COUNTIF(AT45:BH45,"*OK*") -> 0 | CN45: =COUNTIF(AT45:BH45,"*OP*") -> 0
A46: 25521 | B46: CCO990211T64 | C46: =AD46 -> 976.5927 | D46: =COUNTIF(AT46:BH46,"*OK*") -> 0 | E46: Karla Patiño | F46: CINCO CONTEMPORANEA | H46: =IF(LEN(TRIM($G46&""))=0, $C46, SUMIF($G$3:$G$561, TRIM($G46), $C$3:$C$561)) -> 976.5927 | I46: ENTERPRISE | L46: =HYPERLINK("https://crm.zoho.com/crm/org685875245/tab/Accounts/3525045000323377150","https://crm.zoho.com/crm/org685875245/tab/Accounts/3525045000323377150") -> https://crm.zoho.com/crm/org685875245/tab/Accounts/3525045000323377150 | M46: Expandir | O46: Sofia | P46: 3331373186 | Q46: nominas@constructoracinco.com | U46: - | V46: 1500.17 | W46: 1448.08 | X46: 1603.74 | Y46: 1357.91 | Z46: 1353.7167 | AA46: 1446.28 | AB46: 1297.879 | AC46: 1103.0343 | AD46: 976.5927 | AE46: 820 | AF46: 200 | AI46: CDMX | AJ46: Turismo y Gastronomía | AK46: Grupo restaurantero mexicano con concepto de cocina contemporánea, opera varios restaurantes y bares de alta cocina en la Ciudad de México. | AQ46: Buscar integración con buk | AS46: NO | BJ46: =COUNTIF(AT46:BI46,"*OP*") -> 0 | BL46: =(COUNTIF(AT46:AV46,"*OK*")*3) + (COUNTIF(AW46:AY46,"*OK*")*2) + COUNTIF(AZ46:BB46,"*OK*")+COUNTIF(BK46:BK46,"SI")*0.5 -> 0 | BM46: =IF(BL46<0.6,"Demasiado Riesgo",IF(BL46<=5,"Riesgo Medio",IF(BL46<=11,"Riesgo Bajo","Cliente Blindado"))) -> Demasiado Riesgo | BP46: 0 | CL46: =COUNTIF(AT46:BH46,"*OK*") -> 0 | CN46: =COUNTIF(AT46:BH46,"*OP*") -> 0
A47: 6341 | B47: FPF170810F72 | C47: =AD47 -> 926.9167 | D47: =COUNTIF(AT47:BH47,"*OK*") -> 0 | E47: Dafne de la Rosa | F47: FLORES Y PLANTAS LA FINCA | G47: (BODEGA DE FLORES) | H47: =IF(LEN(TRIM($G47&""))=0, $C47, SUMIF($G$3:$G$561, TRIM($G47), $C$3:$C$561)) -> 926.9167 | I47: ENTERPRISE | L47: =HYPERLINK("https://crm.zoho.com/crm/org685875245/tab/Accounts/3525045000069397259","https://crm.zoho.com/crm/org685875245/tab/Accounts/3525045000069397259") -> https://crm.zoho.com/crm/org685875245/tab/Accounts/3525045000069397259 | M47: Mantener | N47: UP 2 Tiendas y Vacaciones | O47: Angel | P47: 7221299948 | Q47: fyfcomprasvillaguerrero@hotmail.com | S47: Mapeada en junio, julio | U47: 15. Planta Productiva | V47: 854.05 | W47: 904.72 | X47: 874.45 | Y47: 868.85 | Z47: 884.8178 | AA47: 946.99 | AB47: 993.3432 | AC47: 972.5301 | AD47: 926.9167 | AE47: 218 | AF47: 200 | AH47: Nuevo Leon | AI47: Nuevo León | AJ47: Agrícola | AK47: Empresa productora y comercializadora de flores, plantas ornamentales y productos agrícolas, con producción en Nuevo León y distribución nacional. | AL47: Agrícola / Retail | AS47: SI | AT47: OP | AV47: OP (Q3) | BJ47: =COUNTIF(AT47:BI47,"*OP*") -> 2 | BK47: NO | BL47: =(COUNTIF(AT47:AV47,"*OK*")*3) + (COUNTIF(AW47:AY47,"*OK*")*2) + COUNTIF(AZ47:BB47,"*OK*")+COUNTIF(BK47:BK47,"SI")*0.5 -> 0 | BM47: =IF(BL47<0.6,"Demasiado Riesgo",IF(BL47<=5,"Riesgo Medio",IF(BL47<=11,"Riesgo Bajo","Cliente Blindado"))) -> Demasiado Riesgo | BO47: angel mismo aquí | BP47: 0 | BQ47: Llamada | CL47: =COUNTIF(AT47:BH47,"*OK*") -> 0 | CN47: =COUNTIF(AT47:BH47,"*OP*") -> 2
A48: 33849 | B48: EPM811006HH2 | C48: =AD48 -> 1051.7108 | D48: =COUNTIF(AT48:BH48,"*OK*") -> 0 | E48: Raúl Campos | F48: NEWREST CATERING MEXICO | H48: =IF(LEN(TRIM($G48&""))=0, $C48, SUMIF($G$3:$G$561, TRIM($G48), $C$3:$C$561)) -> 1051.7108 | I48: ENTERPRISE | L48: =HYPERLINK("https://crm.zoho.com/crm/org685875245/tab/Accounts/3525045000459175562","https://crm.zoho.com/crm/org685875245/tab/Accounts/3525045000459175562") -> https://crm.zoho.com/crm/org685875245/tab/Accounts/3525045000459175562 | M48: Alcanzar | O48: Brhayan | P48: 5532636024 | Q48: brhayan.frieven@newrest.eu | R48: Ver si están en CDMX | T48: SI | U48: - | X48: 834.64 | Y48: 1128 | Z48: 916.307 | AA48: 959.68 | AB48: 937.4136 | AC48: 961.6299 | AD48: 1051.7108 | AE48: 2223 | AF48: 5500 | AI48: CDMX | AJ48: Outsourcing | AK48: Filial mexicana de Newrest, empresa multinacional francesa de catering y restauración colectiva para aerolíneas, industria y colectividades. | AL48: Outsourcing General | AN48: 5. Mail | AV48: OP(Q3) | BJ48: =COUNTIF(AT48:BI48,"*OP*") -> 1 | BL48: =(COUNTIF(AT48:AV48,"*OK*")*3) + (COUNTIF(AW48:AY48,"*OK*")*2) + COUNTIF(AZ48:BB48,"*OK*")+COUNTIF(BK48:BK48,"SI")*0.5 -> 0 | BM48: =IF(BL48<0.6,"Demasiado Riesgo",IF(BL48<=5,"Riesgo Medio",IF(BL48<=11,"Riesgo Bajo","Cliente Blindado"))) -> Demasiado Riesgo | BP48: 0 | CL48: =COUNTIF(AT48:BH48,"*OK*") -> 0 | CN48: =COUNTIF(AT48:BH48,"*OP*") -> 1
A49: 26509 | B49: CGR020208GD6 | C49: =AD49 -> 893.7086 | D49: =COUNTIF(AX49:BI49,"OK") -> 0 | E49: Dafne de la Rosa | F49: IDEAL AUTOMOTIVE MEXICO | H49: =IF(LEN(TRIM($G49&""))=0, $C49, SUMIF($G$3:$G$561, TRIM($G49), $C$3:$C$561)) -> 893.7086 | I49: ENTERPRISE | O49: Raul Garcia | P49: 2211129139 | Q49: rgvraul@hotmail.com | T49: SI | AA49: 897.4 | AB49: 944.8465 | AC49: 952.5933 | AD49: 893.7086 | AE49: 384 | BJ49: =COUNTIF(AT49:BI49,"*OP*") -> 0 | BL49: =(COUNTIF(AT49:AV49,"*OK*")*3) + (COUNTIF(AW49:AY49,"*OK*")*2) + COUNTIF(AZ49:BB49,"*OK*")+COUNTIF(BK49:BK49,"SI")*0.5 -> 0 | BM49: =IF(BL49<0.6,"Demasiado Riesgo",IF(BL49<=5,"Riesgo Medio",IF(BL49<=11,"Riesgo Bajo","Cliente Blindado"))) -> Demasiado Riesgo | BO49: implementación dar seguimiento | BP49: 0 | BQ49: Pendiente | CL49: =COUNTIF(AT49:BH49,"*OK*") -> 0 | CN49: =COUNTIF(AT49:BH49,"*OP*") -> 0
A50: 30597 | B50: FME080110D68 | C50: =AD50 -> 856.3466 | D50: =COUNTIF(AT50:BH50,"*OK*") -> 0 | E50: Raúl Campos | F50: FORSAC MEXICO | H50: =IF(LEN(TRIM($G50&""))=0, $C50, SUMIF($G$3:$G$561, TRIM($G50), $C$3:$C$561)) -> 856.3466 | I50: ENTERPRISE | L50: =HYPERLINK("https://crm.zoho.com/crm/org685875245/tab/Accounts/3525045000511564020","https://crm.zoho.com/crm/org685875245/tab/Accounts/3525045000511564020") -> https://crm.zoho.com/crm/org685875245/tab/Accounts/3525045000511564020 | M50: Mantener | O50: Cristian | P50: 3332182170 | Q50: tercero.cristian.villamil@cmpc.com | R50: Ver si están en CDMX | U50: 20. Servicios | V50: 1159.33 | W50: 932.08 | X50: 914.69 | Y50: 960.03 | Z50: 932.9162 | AA50: 899.49 | AB50: 922.8934 | AC50: 929.4151 | AD50: 856.3466 | AE50: 383 | AF50: 350 | AI50: Estado de México | AJ50: Manufactura | AK50: Empresa del grupo CMPC fabricante de sacos de papel kraft y empaques industriales para la industria del cemento, alimentos y química. | AL50: Servicios | AN50: 4. Whatsapp | AS50: SI | BJ50: =COUNTIF(AT50:BI50,"*OP*") -> 0 | BK50: NO | BL50: =(COUNTIF(AT50:AV50,"*OK*")*3) + (COUNTIF(AW50:AY50,"*OK*")*2) + COUNTIF(AZ50:BB50,"*OK*")+COUNTIF(BK50:BK50,"SI")*0.5 -> 0 | BM50: =IF(BL50<0.6,"Demasiado Riesgo",IF(BL50<=5,"Riesgo Medio",IF(BL50<=11,"Riesgo Bajo","Cliente Blindado"))) -> Demasiado Riesgo | BP50: 0 | CL50: =COUNTIF(AT50:BH50,"*OK*") -> 0 | CN50: =COUNTIF(AT50:BH50,"*OP*") -> 0
A51: 38808 | B51: IPI041105GZ5 | C51: =AD51 -> 863.6865 | D51: =COUNTIF(AX51:BI51,"OK") -> 0 | E51: Dafne de la Rosa | F51: INTER PLAS INDUSTRIES (IPISA) | G51: IPISA | H51: =IF(LEN(TRIM($G51&""))=0, $C51, SUMIF($G$3:$G$561, TRIM($G51), $C$3:$C$561)) -> 863.6865 | I51: ENTERPRISE | L51: =HYPERLINK("https://crm.zoho.com/crm/org685875245/tab/Accounts/3525045000577986714","https://crm.zoho.com/crm/org685875245/tab/Accounts/3525045000577986714") -> https://crm.zoho.com/crm/org685875245/tab/Accounts/3525045000577986714 | N51: Piloto geocoffee | O51: Karem | P51: 7222431970 | Q51: gerencia.rh@ipisa.ws | U51: 15. Planta Productiva | AA51: 857.06 | AB51: 855.6514 | AC51: 927.1266 | AD51: 863.6865 | AE51: 290 | AF51: 200 | BJ51: =COUNTIF(AT51:BI51,"*OP*") -> 0 | BL51: =(COUNTIF(AT51:AV51,"*OK*")*3) + (COUNTIF(AW51:AY51,"*OK*")*2) + COUNTIF(AZ51:BB51,"*OK*")+COUNTIF(BK51:BK51,"SI")*0.5 -> 0 | BM51: =IF(BL51<0.6,"Demasiado Riesgo",IF(BL51<=5,"Riesgo Medio",IF(BL51<=11,"Riesgo Bajo","Cliente Blindado"))) -> Demasiado Riesgo | BO51: base de datos | BP51: 0 | CL51: =COUNTIF(AT51:BH51,"*OK*") -> 0 | CN51: =COUNTIF(AT51:BH51,"*OP*") -> 0
A52: 31422 | B52: TTR841228A39 | C52: =AD52 -> 850.9691 | D52: =COUNTIF(AT52:BH52,"*OK*") -> 0 | E52: Dafne de la Rosa | F52: TIENDAS TROPICALES (Cinco Soles) | H52: =IF(LEN(TRIM($G52&""))=0, $C52, SUMIF($G$3:$G$561, TRIM($G52), $C$3:$C$561)) -> 850.9691 | I52: ENTERPRISE | L52: =HYPERLINK("https://crm.zoho.com/crm/org685875245/tab/Accounts/3525045000444479020","https://crm.zoho.com/crm/org685875245/tab/Accounts/3525045000444479020") -> https://crm.zoho.com/crm/org685875245/tab/Accounts/3525045000444479020 | O52: Ivan | P52: 3333333333 | Q52: amir@loscincosoles.com | R52: Invitar | T52: SI | U52: 22. Turismo, Hotelería y Gastronomía | V52: 856.03 | W52: 868.46 | X52: 869.2 | Y52: 878.98 | Z52: 903.9822 | AA52: 918.83 | AB52: 931.8412 | AC52: 918.1875 | AD52: 850.9691 | AE52: 673 | AF52: 598 | AI52: Guerrero | AJ52: Retail | AK52: Cadena de supermercados regionales Cinco Soles con operaciones en el estado de Guerrero y zona del Pacífico sur de México. | BJ52: =COUNTIF(AT52:BI52,"*OP*") -> 0 | BL52: =(COUNTIF(AT52:AV52,"*OK*")*3) + (COUNTIF(AW52:AY52,"*OK*")*2) + COUNTIF(AZ52:BB52,"*OK*")+COUNTIF(BK52:BK52,"SI")*0.5 -> 0 | BM52: =IF(BL52<0.6,"Demasiado Riesgo",IF(BL52<=5,"Riesgo Medio",IF(BL52<=11,"Riesgo Bajo","Cliente Blindado"))) -> Demasiado Riesgo | BO52: implementación dar seguimiento | BP52: 0 | BQ52: Pendiente | CL52: =COUNTIF(AT52:BH52,"*OK*") -> 0 | CN52: =COUNTIF(AT52:BH52,"*OP*") -> 0
A53: 3455 | B53: TQM8612184N3 | C53: =AD53 -> 855.5552 | D53: =COUNTIF(AT53:BH53,"*OK*") -> 2 | E53: Raúl Campos | F53: Puratos de México SA de CV | H53: =IF(LEN(TRIM($G53&""))=0, $C53, SUMIF($G$3:$G$561, TRIM($G53), $C$3:$C$561)) -> 855.5552 | I53: ENTERPRISE | L53: =HYPERLINK("https://crm.zoho.com/crm/org685875245/tab/Accounts/3525045000025416632","https://crm.zoho.com/crm/org685875245/tab/Accounts/3525045000025416632") -> https://crm.zoho.com/crm/org685875245/tab/Accounts/3525045000025416632 | M53: Mantener | O53: MIRIAM LETICIA TORRES CHILLON | P53: 7757849823 | Q53: mtorreschillon@puratos.com | R53: Ver si están en CDMX | U53: 15. Planta Productiva | V53: 1056.67 | W53: 1055.71 | X53: 1006.07 | Y53: 883.72 | Z53: 895.6054 | AA53: 866 | AB53: 893.2574 | AC53: 909.679 | AD53: 855.5552 | AE53: 606 | AF53: 400 | AI53: Hidalgo | AJ53: Manufactura | AK53: Empresa belga con operaciones en Tizayuca, Hidalgo; produce y comercializa materias primas para la industria de panadería, pastelería y chocolatería en más de 100 países. | AN53: 4. Whatsapp | AS53: SI | AV53: OK(062025) | AX53: OK(062025) | BJ53: =COUNTIF(AT53:BI53,"*OP*") -> 0 | BK53: NO | BL53: =(COUNTIF(AT53:AV53,"*OK*")*3) + (COUNTIF(AW53:AY53,"*OK*")*2) + COUNTIF(AZ53:BB53,"*OK*")+COUNTIF(BK53:BK53,"SI")*0.5 -> 5 | BM53: =IF(BL53<0.6,"Demasiado Riesgo",IF(BL53<=5,"Riesgo Medio",IF(BL53<=11,"Riesgo Bajo","Cliente Blindado"))) -> Riesgo Medio | BP53: 0 | CL53: =COUNTIF(AT53:BH53,"*OK*") -> 2 | CN53: =COUNTIF(AT53:BH53,"*OP*") -> 0
A54: 24336 | B54: DJU890724BU0 | C54: =AD54 -> 822.7925 | D54: =COUNTIF(AT54:BH54,"*OK*") -> 0 | E54: Raúl Campos | F54: DISTRIBUIDORA JUGUETRON | H54: =IF(LEN(TRIM($G54&""))=0, $C54, SUMIF($G$3:$G$561, TRIM($G54), $C$3:$C$561)) -> 822.7925 | I54: ENTERPRISE | L54: =HYPERLINK("https://crm.zoho.com/crm/org685875245/tab/Accounts/3525045000272607068","https://crm.zoho.com/crm/org685875245/tab/Accounts/3525045000272607068") -> https://crm.zoho.com/crm/org685875245/tab/Accounts/3525045000272607068 | M54: Expandir | N54: Tiene personalizacion de reporte de nomina BUK. Conseguir documentación con Olga | O54: Irma | P54: 5564846416 | Q54: ipalencia@juguetron.mx | R54: Registrado | U54: - | V54: 1027.48 | W54: 832.46 | X54: 819.61 | Y54: 832.43 | Z54: 848.5416 | AA54: 847.98 | AB54: 871.7848 | AC54: 903.7725 | AD54: 822.7925 | AE54: 1055 | AF54: 1200 | AI54: CDMX | AJ54: Retail | AK54: Cadena mexicana de tiendas de juguetes con presencia en los principales centros comerciales del país, distribuidora oficial de marcas internacionales. | AN54: 2. Videollamada | AS54: SI | BJ54: =COUNTIF(AT54:BI54,"*OP*") -> 0 | BL54: =(COUNTIF(AT54:AV54,"*OK*")*3) + (COUNTIF(AW54:AY54,"*OK*")*2) + COUNTIF(AZ54:BB54,"*OK*")+COUNTIF(BK54:BK54,"SI")*0.5 -> 0 | BM54: =IF(BL54<0.6,"Demasiado Riesgo",IF(BL54<=5,"Riesgo Medio",IF(BL54<=11,"Riesgo Bajo","Cliente Blindado"))) -> Demasiado Riesgo | BP54: 0 | CL54: =COUNTIF(AT54:BH54,"*OK*") -> 0 | CN54: =COUNTIF(AT54:BH54,"*OP*") -> 0
A55: 24766 | B55: CSI161207HK1 | C55: =AD55 -> 878.218 | D55: =COUNTIF(AT55:BH55,"*OK*") -> 1 | E55: Dafne de la Rosa | F55: CEPADEMRH SERVICIOS INTEGRALES (LUMO FINANCIERA) | H55: =IF(LEN(TRIM($G55&""))=0, $C55, SUMIF($G$3:$G$561, TRIM($G55), $C$3:$C$561)) -> 878.218 | I55: ENTERPRISE | L55: =HYPERLINK("https://crm.zoho.com/crm/org685875245/tab/Accounts/3525045000252648254","https://crm.zoho.com/crm/org685875245/tab/Accounts/3525045000252648254") -> https://crm.zoho.com/crm/org685875245/tab/Accounts/3525045000252648254 | M55: Retener | N55: Estamos en espera de la respuesta de diferencias entre las bajas de usuarios para tener reunion con el cliente. | O55: Emmanuel Jimenez Jimenez ramirez | P55: +521112223355 | Q55: emmanueljimenez@lumofc.com | R55: Invitar | S55: Mapeada en junio | U55: - | V55: 1362.93 | W55: 1354.17 | X55: 1254.71 | Y55: 1008.74 | Z55: 1022.3089 | AA55: 1029.62 | AB55: 912.6239 | AC55: 901.4453 | AD55: 878.218 | AE55: 413 | AF55: 600 | AH55: CDMX | AI55: CDMX | AJ55: Outsourcing | AK55: Empresa de outsourcing de recursos humanos y nómina (LUMO Financiera), especializada en administración de personal y servicios de RRHH para empresas. | AL55: Outsourcing General | AR55: BUK (sin asistencia) | AS55: SI, no integrado | AU55: OP (Personalizada con Buk, permisos parciales y RAM) | AV55: NO - buk | AX55: NO - interno | AZ55: OK(092024) | BB55: OP (Costo $0) | BJ55: =COUNTIF(AT55:BI55,"*OP*") -> 2 | BL55: =(COUNTIF(AT55:AV55,"*OK*")*3) + (COUNTIF(AW55:AY55,"*OK*")*2) + COUNTIF(AZ55:BB55,"*OK*")+COUNTIF(BK55:BK55,"SI")*0.5 -> 1 | BM55: =IF(BL55<0.6,"Demasiado Riesgo",IF(BL55<=5,"Riesgo Medio",IF(BL55<=11,"Riesgo Bajo","Cliente Blindado"))) -> Riesgo Medio | BO55: ramirez mismo aquí | BP55: 0 | BQ55: Correo | CL55: =COUNTIF(AT55:BH55,"*OK*") -> 1 | CN55: =COUNTIF(AT55:BH55,"*OP*") -> 2
A56: 27983 | B56: NMM0608281R3 | C56: =AD56 -> 830.0221 | D56: =COUNTIF(AT56:BH56,"*OK*") -> 2 | E56: Raúl Campos | F56: NETAFIM MANUFACTURING MEXICO | G56: NETAFIM | H56: =IF(LEN(TRIM($G56&""))=0, $C56, SUMIF($G$3:$G$561, TRIM($G56), $C$3:$C$561)) -> 1381.8985 | I56: ENTERPRISE | L56: =HYPERLINK("https://crm.zoho.com/crm/org685875245/tab/Accounts/3525045000324636081","https://crm.zoho.com/crm/org685875245/tab/Accounts/3525045000324636081") -> https://crm.zoho.com/crm/org685875245/tab/Accounts/3525045000324636081 | M56: Mantener | O56: ALEJANDRA ESCOBEDO ESCOBEDO CRUZ | P56: +528991601534 | Q56: alejandra.escobedo@netafim.orbia.com | R56: No están en CDMX | U56: 15. Planta Productiva | V56: 637.93 | W56: 618.28 | X56: 776.1 | Y56: 811.8 | Z56: 877.0228 | AA56: 864.72 | AB56: 836.8097 | AC56: 896.3202 | AD56: 830.0221 | AE56: 312 | AF56: 500 | AI56: Estado de México | AJ56: Manufactura | AK56: Planta manufacturera de Netafim en México, fabricante israelí líder en sistemas de riego por goteo y soluciones de fertirrigación para el sector agrícola. | AN56: 2. Videollamada | AS56: SI | AV56: OK(Q3) | AZ56: OK(Q3) | BI56: OP (Q3) | BJ56: =COUNTIF(AT56:BI56,"*OP*") -> 1 | BK56: NO | BL56: =(COUNTIF(AT56:AV56,"*OK*")*3) + (COUNTIF(AW56:AY56,"*OK*")*2) + COUNTIF(AZ56:BB56,"*OK*")+COUNTIF(BK56:BK56,"SI")*0.5 -> 4 | BM56: =IF(BL56<0.6,"Demasiado Riesgo",IF(BL56<=5,"Riesgo Medio",IF(BL56<=11,"Riesgo Bajo","Cliente Blindado"))) -> Riesgo Medio | BP56: 0 | CL56: =COUNTIF(AT56:BH56,"*OK*") -> 2 | CN56: =COUNTIF(AT56:BH56,"*OP*") -> 0
A57: 38784 | B57: IME910214GD1 | C57: =AD57 -> 1087.0309 | D57: =COUNTIF(AX57:BI57,"OK") -> 0 | E57: Dafne de la Rosa | F57: ENTIA DE MEXICO | H57: =IF(LEN(TRIM($G57&""))=0, $C57, SUMIF($G$3:$G$561, TRIM($G57), $C$3:$C$561)) -> 1087.0309 | I57: ENTERPRISE | L57: =HYPERLINK("https://crm.zoho.com/crm/org685875245/tab/Accounts/3525045000630418441","https://crm.zoho.com/crm/org685875245/tab/Accounts/3525045000630418441") -> https://crm.zoho.com/crm/org685875245/tab/Accounts/3525045000630418441 | O57: ILSE LARA CADO | P57: +525542353118 | Q57: ilara@entiamx.com | T57: SI | AA57: 791.81 | AB57: 829.2039 | AC57: 890.1589 | AD57: 1087.0309 | AE57: 336 | BJ57: =COUNTIF(AT57:BI57,"*OP*") -> 0 | BL57: =(COUNTIF(AT57:AV57,"*OK*")*3) + (COUNTIF(AW57:AY57,"*OK*")*2) + COUNTIF(AZ57:BB57,"*OK*")+COUNTIF(BK57:BK57,"SI")*0.5 -> 0 | BM57: =IF(BL57<0.6,"Demasiado Riesgo",IF(BL57<=5,"Riesgo Medio",IF(BL57<=11,"Riesgo Bajo","Cliente Blindado"))) -> Demasiado Riesgo | BP57: 0 | CL57: =COUNTIF(AT57:BH57,"*OK*") -> 0 | CN57: =COUNTIF(AT57:BH57,"*OP*") -> 0
A58: 35601 | B58: GKA081001HL5 | C58: =AD58 -> 841.6115 | D58: =COUNTIF(AT58:BH58,"*OK*") -> 0 | E58: Dafne de la Rosa | F58: GRUPO KARUNA | H58: =IF(LEN(TRIM($G58&""))=0, $C58, SUMIF($G$3:$G$561, TRIM($G58), $C$3:$C$561)) -> 841.6115 | I58: ENTERPRISE | L58: =HYPERLINK("https://crm.zoho.com/crm/org685875245/tab/Accounts/3525045000533674268","https://crm.zoho.com/crm/org685875245/tab/Accounts/3525045000533674268") -> https://crm.zoho.com/crm/org685875245/tab/Accounts/3525045000533674268 | M58: Expandir | N58: Reu pendiente con Azucena | O58: Gabriela Muñoz Muñoz | P58: 5214461399288 | Q58: gmg@gka.mx | S58: Mapeada en junio, julio, agosto | U58: Otros | V58: 742.45 | W58: 785.23 | X58: 740.03 | Y58: 772.41 | Z58: 788.5752 | AA58: 782.79 | AB58: 832.6035 | AC58: 886.0514 | AD58: 841.6115 | AE58: 294 | AF58: 300 | AI58: CDMX | AJ58: Salud | AK58: Grupo empresarial con laboratorios farmacéuticos y clínicos, especializado en producción y comercialización de medicamentos y servicios de salud. | AL58: Laboratorios | BJ58: =COUNTIF(AT58:BI58,"*OP*") -> 0 | BL58: =(COUNTIF(AT58:AV58,"*OK*")*3) + (COUNTIF(AW58:AY58,"*OK*")*2) + COUNTIF(AZ58:BB58,"*OK*")+COUNTIF(BK58:BK58,"SI")*0.5 -> 0 | BM58: =IF(BL58<0.6,"Demasiado Riesgo",IF(BL58<=5,"Riesgo Medio",IF(BL58<=11,"Riesgo Bajo","Cliente Blindado"))) -> Demasiado Riesgo | BP58: 0 | CL58: =COUNTIF(AT58:BH58,"*OK*") -> 0 | CN58: =COUNTIF(AT58:BH58,"*OP*") -> 0
A59: 36200 | B59: HER800206R92 | C59: =AD59 -> 813.4658 | D59: =COUNTIF(AT59:BH59,"*OK*") -> 1 | E59: Dafne de la Rosa | F59: HERMOS | H59: =IF(LEN(TRIM($G59&""))=0, $C59, SUMIF($G$3:$G$561, TRIM($G59), $C$3:$C$561)) -> 813.4658 | I59: SMB | L59: =HYPERLINK("https://crm.zoho.com/crm/org685875245/tab/Accounts/3525045000582917522","https://crm.zoho.com/crm/org685875245/tab/Accounts/3525045000582917522") -> https://crm.zoho.com/crm/org685875245/tab/Accounts/3525045000582917522 | O59: Karen Rodriguez / Cesar Hernandez | P59: 4612807722 / +524611091119 | Q59: akrodriguez@hermos.com / cahernandez@hermos.com.mx | T59: SI | U59: 20. Servicios | X59: 24.3 | Y59: 25.08 | Z59: 896.0294 | AA59: 324.94 | AB59: 852.4823 | AC59: 868.1544 | AD59: 813.4658 | AE59: 266 | AF59: 50 | AI59: CDMX | AJ59: Servicios | AK59: Empresa de servicios con sede en México, posiblemente orientada a gestión comercial, consultoría o soluciones operativas para clientes empresariales. | AL59: Servicios | AV59: OK(032026) | BJ59: =COUNTIF(AT59:BI59,"*OP*") -> 0 | BL59: =(COUNTIF(AT59:AV59,"*OK*")*3) + (COUNTIF(AW59:AY59,"*OK*")*2) + COUNTIF(AZ59:BB59,"*OK*")+COUNTIF(BK59:BK59,"SI")*0.5 -> 3 | BM59: =IF(BL59<0.6,"Demasiado Riesgo",IF(BL59<=5,"Riesgo Medio",IF(BL59<=11,"Riesgo Bajo","Cliente Blindado"))) -> Riesgo Medio | BP59: 0 | CL59: =COUNTIF(AT59:BH59,"*OK*") -> 1 | CN59: =COUNTIF(AT59:BH59,"*OP*") -> 0
A60: 22786 | B60: CEN180307897 | C60: =AD60 -> 834.101 | D60: 1 | E60: Dafne de la Rosa | F60: COMETA ENERGIA (SAAVI) | H60: =IF(LEN(TRIM($G60&""))=0, $C60, SUMIF($G$3:$G$561, TRIM($G60), $C$3:$C$561)) -> 834.101 | I60: ENTERPRISE | L60: =HYPERLINK("https://crm.zoho.com/crm/org685875245/tab/Accounts/3525045000136022031","https://crm.zoho.com/crm/org685875245/tab/Accounts/3525045000136022031") -> https://crm.zoho.com/crm/org685875245/tab/Accounts/3525045000136022031 | M60: Mantener | N60: Solicitar baja de BI EN FACTURACION DE JULIO | O60: ARTURO POSADAS DIAZ | P60: 5544997784 | Q60: ARTURO.POSADAS@SAAVIENERGIA.COM | R60: Invitado | U60: - | V60: 864.85 | W60: 936.04 | X60: 885.35 | Y60: 923.35 | Z60: 943.3716 | AA60: 833.57 | AB60: 872.1023 | AC60: 867.2131 | AD60: 834.101 | AE60: 224 | AF60: 190 | AH60: CDMX | AI60: CDMX | AJ60: Energía | AK60: Empresa del grupo SAAVI comercializadora de energía eléctrica y gas natural, con soluciones de suministro energético para clientes industriales y comerciales. | AL60: Olantas de Energia | AS60: MANUAL | AU60: OP (SICOS) | AV60: OP | AX60: NO - tuvieron problemas con BI y ya no les gusta | BJ60: =COUNTIF(AT60:BI60,"*OP*") -> 2 | BL60: =(COUNTIF(AT60:AV60,"*OK*")*3) + (COUNTIF(AW60:AY60,"*OK*")*2) + COUNTIF(AZ60:BB60,"*OK*")+COUNTIF(BK60:BK60,"SI")*0.5 -> 0 | BM60: =IF(BL60<0.6,"Demasiado Riesgo",IF(BL60<=5,"Riesgo Medio",IF(BL60<=11,"Riesgo Bajo","Cliente Blindado"))) -> Demasiado Riesgo | BO60: base de datos | BP60: 0 | BQ60: Correo | CL60: =COUNTIF(AT60:BH60,"*OK*") -> 0 | CN60: =COUNTIF(AT60:BH60,"*OP*") -> 2
A61: 38201 | B61: PPE060105CM2 | C61: =AD61 -> 809.6026 | D61: =COUNTIF(AX61:BI61,"OK") -> 0 | E61: Dafne de la Rosa | F61: PUNTO PEN (Penhealth) | H61: =IF(LEN(TRIM($G61&""))=0, $C61, SUMIF($G$3:$G$561, TRIM($G61), $C$3:$C$561)) -> 809.6026 | I61: ENTERPRISE | L61: =HYPERLINK("https://crm.zoho.com/crm/org685875245/tab/Accounts/3525045000526296256","https://crm.zoho.com/crm/org685875245/tab/Accounts/3525045000526296256") -> https://crm.zoho.com/crm/org685875245/tab/Accounts/3525045000526296256 | O61: Sharon | P61: 8888888888 | Q61: sharon.lopez@pen.com.mx | T61: SI | U61: 19. Salud | Z61: 759.1119 | AA61: 794.5 | AB61: 847.8727 | AC61: 860.8195 | AD61: 809.6026 | AE61: 309 | BJ61: =COUNTIF(AT61:BI61,"*OP*") -> 0 | BL61: =(COUNTIF(AT61:AV61,"*OK*")*3) + (COUNTIF(AW61:AY61,"*OK*")*2) + COUNTIF(AZ61:BB61,"*OK*")+COUNTIF(BK61:BK61,"SI")*0.5 -> 0 | BM61: =IF(BL61<0.6,"Demasiado Riesgo",IF(BL61<=5,"Riesgo Medio",IF(BL61<=11,"Riesgo Bajo","Cliente Blindado"))) -> Demasiado Riesgo | BP61: 0 | CL61: =COUNTIF(AT61:BH61,"*OK*") -> 0 | CN61: =COUNTIF(AT61:BH61,"*OP*") -> 0
A62: 35510 | B62: CEM970905VB3 | C62: =AD62 -> 807.1192 | D62: =COUNTIF(AT62:BH62,"*OK*") -> 1 | E62: Raúl Campos | F62: COMBUSTIBLES ECOLOGICOS MEXICANOS (VI Group) | H62: =IF(LEN(TRIM($G62&""))=0, $C62, SUMIF($G$3:$G$561, TRIM($G62), $C$3:$C$561)) -> 807.1192 | I62: ENTERPRISE | L62: =HYPERLINK("https://crm.zoho.com/crm/org685875245/tab/Accounts/3525045000502956105","https://crm.zoho.com/crm/org685875245/tab/Accounts/3525045000502956105") -> https://crm.zoho.com/crm/org685875245/tab/Accounts/3525045000502956105 | O62: Dafne | P62: 5561050446 | Q62: dafne.orozco@encognv.com | R62: Ver si están en CDMX | T62: SI | U62: 20. Servicios | V62: 783.05 | W62: 782.34 | X62: 745.56 | Y62: 859.34 | Z62: 816.3053 | AA62: 848.49 | AB62: 847.8727 | AC62: 844.9762 | AD62: 807.1192 | AE62: 315 | AF62: 200 | AI62: CDMX | AJ62: Energía | AK62: Empresa del VI Group comercializadora de combustibles ecológicos y alternativos, con soluciones de abastecimiento de energía limpia para flotas vehiculares. | AY62: OK ($0) | BJ62: =COUNTIF(AT62:BI62,"*OP*") -> 0 | BL62: =(COUNTIF(AT62:AV62,"*OK*")*3) + (COUNTIF(AW62:AY62,"*OK*")*2) + COUNTIF(AZ62:BB62,"*OK*")+COUNTIF(BK62:BK62,"SI")*0.5 -> 2 | BM62: =IF(BL62<0.6,"Demasiado Riesgo",IF(BL62<=5,"Riesgo Medio",IF(BL62<=11,"Riesgo Bajo","Cliente Blindado"))) -> Riesgo Medio | BP62: 0 | CL62: =COUNTIF(AT62:BH62,"*OK*") -> 1 | CN62: =COUNTIF(AT62:BH62,"*OP*") -> 0
A63: 18764 | B63: FDA130819JI3 | C63: =AD63 -> 792.7152 | D63: =COUNTIF(AT63:BH63,"*OK*") -> 0 | E63: Raúl Campos | F63: FARMACOS DAROVI | G63: DAROVI | H63: =IF(LEN(TRIM($G63&""))=0, $C63, SUMIF($G$3:$G$561, TRIM($G63), $C$3:$C$561)) -> 2111.8102 | I63: ENTERPRISE | L63: =HYPERLINK("https://crm.zoho.com/crm/org685875245/tab/Accounts/3525045000152361120","https://crm.zoho.com/crm/org685875245/tab/Accounts/3525045000152361120") -> https://crm.zoho.com/crm/org685875245/tab/Accounts/3525045000152361120 | M63: Mantener | O63: Ruth Ines Loredo leon | P63: +525513333636 | Q63: ruth.loredo@farmacosdarovi.com.mx | U63: 19. Salud | V63: 467.51 | W63: 467.08 | X63: 445.12 | Y63: 459.45 | Z63: 854.2609 | AA63: 820.73 | AB63: 827.6482 | AC63: 842.8638 | AD63: 792.7152 | AE63: 630 | AF63: 200 | AI63: CDMX | AJ63: Salud | AK63: Empresa del sector salud dedicada a la distribución y comercialización de medicamentos y productos farmacéuticos para farmacias, hospitales y clínicas en México. | AL63: Salud | AN63: 4. Whatsapp | AT63: NO - ya rechazaron | AV63: OP (Q3) | AZ63: OP(Visitas ,Q2) | BJ63: =COUNTIF(AT63:BI63,"*OP*") -> 2 | BL63: =(COUNTIF(AT63:AV63,"*OK*")*3) + (COUNTIF(AW63:AY63,"*OK*")*2) + COUNTIF(AZ63:BB63,"*OK*")+COUNTIF(BK63:BK63,"SI")*0.5 -> 0 | BM63: =IF(BL63<0.6,"Demasiado Riesgo",IF(BL63<=5,"Riesgo Medio",IF(BL63<=11,"Riesgo Bajo","Cliente Blindado"))) -> Demasiado Riesgo | BP63: 0 | CL63: =COUNTIF(AT63:BH63,"*OK*") -> 0 | CN63: =COUNTIF(AT63:BH63,"*OP*") -> 2
A64: 23468 | B64: PFR110526BP4 | C64: =AD64 -> 782.064 | D64: =COUNTIF(AT64:BH64,"*OK*") -> 1 | E64: Raúl Campos | F64: COMPAÑIA MADERERA DE CHIHUAHUA SUCESORES (HAGALO) | H64: =IF(LEN(TRIM($G64&""))=0, $C64, SUMIF($G$3:$G$561, TRIM($G64), $C$3:$C$561)) -> 782.064 | I64: ENTERPRISE | L64: =HYPERLINK("https://crm.zoho.com/crm/org685875245/tab/Accounts/3525045000271013014","https://crm.zoho.com/crm/org685875245/tab/Accounts/3525045000271013014") -> https://crm.zoho.com/crm/org685875245/tab/Accounts/3525045000271013014 | M64: Mantener | O64: Janeth | P64: 6561244948 | Q64: janeth.pantoja@hagalo.com.mx | U64: - | V64: 609.77 | W64: 576.03 | X64: 729.48 | Y64: 389.14 | Z64: 791.9548 | AA64: 800.18 | AB64: 737.3006 | AC64: 826.1109 | AD64: 782.064 | AE64: 735 | AF64: 710 | AI64: Chihuahua | AJ64: Retail | AK64: Cadena de tiendas de autoservicio de materiales para construcción, ferretería y decoración 'Hágalo', con 9 sucursales principalmente en Ciudad Juárez y Chihuahua. | AN64: 4. Whatsapp | AR64: BUK | AS64: SI | AW64: OP (Q3-Q4) | AX64: OK(122025) | BJ64: =COUNTIF(AT64:BI64,"*OP*") -> 1 | BL64: =(COUNTIF(AT64:AV64,"*OK*")*3) + (COUNTIF(AW64:AY64,"*OK*")*2) + COUNTIF(AZ64:BB64,"*OK*")+COUNTIF(BK64:BK64,"SI")*0.5 -> 2 | BM64: =IF(BL64<0.6,"Demasiado Riesgo",IF(BL64<=5,"Riesgo Medio",IF(BL64<=11,"Riesgo Bajo","Cliente Blindado"))) -> Riesgo Medio | BP64: 0 | CL64: =COUNTIF(AT64:BH64,"*OK*") -> 1 | CN64: =COUNTIF(AT64:BH64,"*OP*") -> 1
A65: 26664 | B65: DCP790511D36 | C65: =AD65 -> 790.5628 | D65: =COUNTIF(AT65:BH65,"*OK*") -> 1 | E65: Raúl Campos | F65: DICIPA | G65: DICIPA | H65: =IF(LEN(TRIM($G65&""))=0, $C65, SUMIF($G$3:$G$561, TRIM($G65), $C$3:$C$561)) -> 1141.2803 | I65: ENTERPRISE | L65: =HYPERLINK("https://crm.zoho.com/crm/org685875245/tab/Accounts/3525045000118304484","https://crm.zoho.com/crm/org685875245/tab/Accounts/3525045000118304484") -> https://crm.zoho.com/crm/org685875245/tab/Accounts/3525045000118304484 | M65: Mantener | O65: Karla | P65: 5550932000 | Q65: samantha.macias@dicipa.com.mx | R65: Registrado | U65: 19. Salud | V65: 769.71 | W65: 767.85 | X65: 730.09 | Y65: 766.13 | Z65: 785.3978 | AA65: 776.79 | AB65: 797.4555 | AC65: 809.182 | AD65: 790.5628 | AE65: 1110 | AF65: 400 | AI65: CDMX | AJ65: Salud | AK65: Distribuidora de insumos, químicos y productos farmacéuticos para hospitales y clínicas, con cobertura nacional en el sector salud público y privado. | AL65: Salud | AN65: 2. Videollamada | AS65: SI | AW65: OP | AX65: OP (Q2, 600) | AZ65: OK(022025) | BJ65: =COUNTIF(AT65:BI65,"*OP*") -> 2 | BK65: NO | BL65: =(COUNTIF(AT65:AV65,"*OK*")*3) + (COUNTIF(AW65:AY65,"*OK*")*2) + COUNTIF(AZ65:BB65,"*OK*")+COUNTIF(BK65:BK65,"SI")*0.5 -> 1 | BM65: =IF(BL65<0.6,"Demasiado Riesgo",IF(BL65<=5,"Riesgo Medio",IF(BL65<=11,"Riesgo Bajo","Cliente Blindado"))) -> Riesgo Medio | BP65: 0 | CL65: =COUNTIF(AT65:BH65,"*OK*") -> 1 | CN65: =COUNTIF(AT65:BH65,"*OP*") -> 2
A66: 36858 | B66: GAQ0004123V3 | C66: =AD66 -> 776.4901 | D66: =COUNTIF(AT66:BH66,"*OK*") -> 0 | E66: Dafne de la Rosa | F66: GRUPO AVICOLA QUIÑONES | H66: =IF(LEN(TRIM($G66&""))=0, $C66, SUMIF($G$3:$G$561, TRIM($G66), $C$3:$C$561)) -> 776.4901 | I66: ENTERPRISE | L66: =HYPERLINK("https://crm.zoho.com/crm/org685875245/tab/Accounts/3525045000587145112","https://crm.zoho.com/crm/org685875245/tab/Accounts/3525045000587145112") -> https://crm.zoho.com/crm/org685875245/tab/Accounts/3525045000587145112 | M66: Expandir | N66: Solicitud JPTI? Tiene diseño de reporte, ver con Gio. Ver si se va a cobrar | O66: Leyver Rios / Irene Ventura Avila | P66: 3314797527 / 3316068292 | Q66: capital.humano@gaq.com / atraccionydesarrollo@gaq.com.mx | R66: Invitar | U66: 1. Agrícola | X66: 1573.95 | Y66: 755.87 | Z66: 757.3788 | AA66: 738.79 | AB66: 760.579 | AC66: 800.967 | AD66: 776.4901 | AE66: 412 | AF66: 400 | AI66: Sinaloa | AJ66: 6 | AK66: Empresa avícola dedicada a la producción, procesamiento y distribución de pollo y productos derivados en el noroeste de México. | AL66: Agrícola | AY66: OP (Q3) | BJ66: =COUNTIF(AT66:BI66,"*OP*") -> 1 | BL66: =(COUNTIF(AT66:AV66,"*OK*")*3) + (COUNTIF(AW66:AY66,"*OK*")*2) + COUNTIF(AZ66:BB66,"*OK*")+COUNTIF(BK66:BK66,"SI")*0.5 -> 0 | BM66: =IF(BL66<0.6,"Demasiado Riesgo",IF(BL66<=5,"Riesgo Medio",IF(BL66<=11,"Riesgo Bajo","Cliente Blindado"))) -> Demasiado Riesgo | BP66: 0 | CL66: =COUNTIF(AT66:BH66,"*OK*") -> 0 | CN66: =COUNTIF(AT66:BH66,"*OP*") -> 1
A67: 38149-24834 | B67: FSP071205RT6 | C67: =AD67 -> 708.2671 | D67: =COUNTIF(AT67:BH67,"*OK*") -> 0 | E67: Raúl Campos | F67: FIDES SEGURIDAD PRIVADA | G67: HEINEKEN | H67: =IF(LEN(TRIM($G67&""))=0, $C67, SUMIF($G$3:$G$561, TRIM($G67), $C$3:$C$561)) -> 708.2671 | I67: ENTERPRISE | M67: Expandir | O67: Joan Pedraza Joan Pedraza | P67: +528110115348 | Q67: joan.pedraza@heineken.com | U67: 12. Outsourcing Seguridad | V67: 744.41 | W67: 720.75 | X67: 700.8 | Y67: 725.41 | Z67: 760.1662 | AA67: 735.35 | AB67: 762.3277 | AC67: 791.15 | AD67: 708.2671 | AE67: 479 | AF67: 2000 | AI67: CDMX | AJ67: Seguridad Privada | AK67: Empresa de seguridad privada contratada por el grupo HEINEKEN México para la vigilancia y protección de sus instalaciones industriales. | AN67: 4. Whatsapp | AS67: SI | BJ67: =COUNTIF(AT67:BI67,"*OP*") -> 0 | BK67: NO | BL67: =(COUNTIF(AT67:AV67,"*OK*")*3) + (COUNTIF(AW67:AY67,"*OK*")*2) + COUNTIF(AZ67:BB67,"*OK*")+COUNTIF(BK67:BK67,"SI")*0.5 -> 0 | BM67: =IF(BL67<0.6,"Demasiado Riesgo",IF(BL67<=5,"Riesgo Medio",IF(BL67<=11,"Riesgo Bajo","Cliente Blindado"))) -> Demasiado Riesgo | BP67: 0 | CL67: =COUNTIF(AT67:BH67,"*OK*") -> 0 | CN67: =COUNTIF(AT67:BH67,"*OP*") -> 0
A68: 30644 | B68: EAS1303221G2 | C68: =AD68 -> 746.3577 | D68: =COUNTIF(AT68:BH68,"*OK*") -> 1 | E68: Raúl Campos | F68: EPIC ADVENTURE SPORTS | G68: JULIO | H68: =IF(LEN(TRIM($G68&""))=0, $C68, SUMIF($G$3:$G$561, TRIM($G68), $C$3:$C$561)) -> 4176.8213 | I68: ENTERPRISE | L68: =HYPERLINK("https://crm.zoho.com/crm/org685875245/tab/Accounts/3525045000480423000","https://crm.zoho.com/crm/org685875245/tab/Accounts/3525045000480423000") -> https://crm.zoho.com/crm/org685875245/tab/Accounts/3525045000480423000 | M68: Expandir | O68: - | U68: 17. Retail Enterprise | V68: 606.61 | W68: 606.05 | X68: 668.02 | Y68: 667.97 | Z68: 674.5351 | AA68: 710.34 | AB68: 728.4272 | AC68: 791.109 | AD68: 746.3577 | AE68: 1624 | AF68: 200 | AI68: CDMX | AJ68: Turismo y Gastronomía | AK68: Empresa del Grupo Julio operadora de actividades y deportes de aventura, con instalaciones recreativas y parques de entretenimiento. | AN68: 2. Videollamada | AS68: SI | AV68: OP (Q3, tienen permisos gratis, op en vacaciones pagados) | AX68: OP (Q3) | AY68: OK(102025) | BJ68: =COUNTIF(AT68:BI68,"*OP*") -> 2 | BK68: NO | BL68: =(COUNTIF(AT68:AV68,"*OK*")*3) + (COUNTIF(AW68:AY68,"*OK*")*2) + COUNTIF(AZ68:BB68,"*OK*")+COUNTIF(BK68:BK68,"SI")*0.5 -> 2 | BM68: =IF(BL68<0.6,"Demasiado Riesgo",IF(BL68<=5,"Riesgo Medio",IF(BL68<=11,"Riesgo Bajo","Cliente Blindado"))) -> Riesgo Medio | BP68: 0 | CL68: =COUNTIF(AT68:BH68,"*OK*") -> 1 | CN68: =COUNTIF(AT68:BH68,"*OP*") -> 2
A69: 27187 | B69: FTM001025RS7 | C69: =AD69 -> 724.276 | D69: =COUNTIF(AT69:BH69,"*OK*") -> 3 | E69: Karla Patiño | F69: FINOS TEXTILES DE MEXICO | H69: =IF(LEN(TRIM($G69&""))=0, $C69, SUMIF($G$3:$G$561, TRIM($G69), $C$3:$C$561)) -> 724.276 | I69: ENTERPRISE | L69: =HYPERLINK("https://crm.zoho.com/crm/org685875245/tab/Accounts/3525045000385457715","https://crm.zoho.com/crm/org685875245/tab/Accounts/3525045000385457715") -> https://crm.zoho.com/crm/org685875245/tab/Accounts/3525045000385457715 | M69: Expandir | N69: Datainvaders con la Fran | O69: Karla Alonso | Q69: dinorahalonso@finotex.com | U69: - | V69: 141.46 | W69: 141.33 | X69: 134.68 | Y69: 817.67 | Z69: 844.7946 | AA69: 828.35 | AB69: 796.5226 | AC69: 770.0949 | AD69: 724.276 | AE69: 178 | AF69: 200 | AI69: CDMX | AJ69: Manufactura | AK69: Empresa del sector textil dedicada a la producción y comercialización de telas, tejidos y materiales textiles de calidad para la industria de la moda y confección en México. | AT69: OK (Q22026) | AV69: OK (Q22026) | AX69: OK (Q22026) | BI69: OK | BJ69: =COUNTIF(AT69:BI69,"*OP*") -> 0 | BL69: =(COUNTIF(AT69:AV69,"*OK*")*3) + (COUNTIF(AW69:AY69,"*OK*")*2) + COUNTIF(AZ69:BB69,"*OK*")+COUNTIF(BK69:BK69,"SI")*0.5 -> 8 | BM69: =IF(BL69<0.6,"Demasiado Riesgo",IF(BL69<=5,"Riesgo Medio",IF(BL69<=11,"Riesgo Bajo","Cliente Blindado"))) -> Riesgo Bajo | CL69: =COUNTIF(AT69:BH69,"*OK*") -> 3 | CN69: =COUNTIF(AT69:BH69,"*OP*") -> 0
A70: 38133 | B70: SAS230111D49 | C70: =AD70 -> 705.7395 | D70: =COUNTIF(AX70:BI70,"OK") -> 0 | E70: Karla Patiño | F70: SERVICIOS DE ADMINISTRACION EN SALUD WEE | H70: =IF(LEN(TRIM($G70&""))=0, $C70, SUMIF($G$3:$G$561, TRIM($G70), $C$3:$C$561)) -> 705.7395 | I70: ENTERPRISE | M70: Expandir | N70: Hermana a WeeClaims, que ya era de Karla | O70: Eduardo | P70: 5599096846 | Q70: eduardo.perez@weemedic.com | T70: SI | AA70: 769.07 | AB70: 741.2188 | AC70: 756.019 | AD70: 705.7395 | AE70: 248 | AT70: OK(042026) | AV70: OK(042026) | AX70: OK(062026) | BI70: OP (Q2 - 137) | BJ70: =COUNTIF(AT70:BI70,"*OP*") -> 1 | BL70: =(COUNTIF(AT70:AV70,"*OK*")*3) + (COUNTIF(AW70:AY70,"*OK*")*2) + COUNTIF(AZ70:BB70,"*OK*")+COUNTIF(BK70:BK70,"SI")*0.5 -> 8 | BM70: =IF(BL70<0.6,"Demasiado Riesgo",IF(BL70<=5,"Riesgo Medio",IF(BL70<=11,"Riesgo Bajo","Cliente Blindado"))) -> Riesgo Bajo | BP70: 0 | CL70: =COUNTIF(AT70:BH70,"*OK*") -> 3 | CN70: =COUNTIF(AT70:BH70,"*OP*") -> 0
A71: 23418 | B71: SME900524FC2 | C71: =AD71 -> 593.543 | D71: =COUNTIF(AT71:BH71,"*OK*") -> 0 | E71: Dafne de la Rosa | F71: SGS DE MEXICO | H71: =IF(LEN(TRIM($G71&""))=0, $C71, SUMIF($G$3:$G$561, TRIM($G71), $C$3:$C$561)) -> 593.543 | I71: ENTERPRISE | L71: =HYPERLINK("https://crm.zoho.com/crm/org685875245/tab/Accounts/3525045000256954023","https://crm.zoho.com/crm/org685875245/tab/Accounts/3525045000256954023") -> https://crm.zoho.com/crm/org685875245/tab/Accounts/3525045000256954023 | M71: Retener | N71: Apoyo cobranza | O71: JOSE JUAN GARCIA SERRANO | P71: +525580090757 | Q71: jose.garcias@sgs.com | R71: Invitar | U71: 20. Servicios | X71: 538.86 | Y71: 580.31 | Z71: 601.4685 | AA71: 598.17 | AB71: 599.4757 | AC71: 748.1061 | AD71: 593.543 | AE71: 721 | AF71: 1000 | AH71: CDMX | AI71: CDMX | AJ71: Servicios | AK71: Filial mexicana de SGS, líder mundial en inspección, verificación, análisis y certificación de productos, procesos y sistemas para múltiples industrias. | AL71: Servicios | AR71: Averiguar | AS71: SI | AV71: NO - tuvo y canceló | BJ71: =COUNTIF(AT71:BI71,"*OP*") -> 0 | BK71: NO | BL71: =(COUNTIF(AT71:AV71,"*OK*")*3) + (COUNTIF(AW71:AY71,"*OK*")*2) + COUNTIF(AZ71:BB71,"*OK*")+COUNTIF(BK71:BK71,"SI")*0.5 -> 0 | BM71: =IF(BL71<0.6,"Demasiado Riesgo",IF(BL71<=5,"Riesgo Medio",IF(BL71<=11,"Riesgo Bajo","Cliente Blindado"))) -> Demasiado Riesgo | BP71: 0 | CL71: =COUNTIF(AT71:BH71,"*OK*") -> 0 | CN71: =COUNTIF(AT71:BH71,"*OP*") -> 0
A72: 1207 | B72: REM8810176J7 | C72: =AD72 -> 698.3046 | D72: =COUNTIF(AT72:BH72,"*OK*") -> 0 | E72: Dafne de la Rosa | F72: RADIOLOGIA Y ELECTRONICA DE MEXICO (REMSA) | H72: =IF(LEN(TRIM($G72&""))=0, $C72, SUMIF($G$3:$G$561, TRIM($G72), $C$3:$C$561)) -> 698.3046 | I72: ENTERPRISE | L72: =HYPERLINK("https://crm.zoho.com/crm/org685875245/tab/Accounts/3525045000008382277","https://crm.zoho.com/crm/org685875245/tab/Accounts/3525045000008382277") -> https://crm.zoho.com/crm/org685875245/tab/Accounts/3525045000008382277 | M72: Mantener | N72: Seguimiento, ver disposición a pago para ofrecer módulo muy barato o dar algo gratis. Sacar reu | O72: Israel López Moreno | P72: 55482514 | Q72: sistemas@remsamexico.com | R72: Invitar | S72: Mapeada en junio | U72: - | V72: 611.62 | W72: 661.98 | X72: 650.27 | Y72: 691.23 | Z72: 695.4592 | AA72: 692.85 | AB72: 729.0772 | AC72: 742.4806 | AD72: 698.3046 | AE72: 142 | AF72: 200 | AH72: CDMX | AI72: CDMX | AJ72: Retail | AK72: Empresa distribuidora de equipos de electrónica, cómputo y tecnología para el mercado empresarial y al detalle en la Ciudad de México. | AL72: Retail Enterprise | BJ72: =COUNTIF(AT72:BI72,"*OP*") -> 0 | BL72: =(COUNTIF(AT72:AV72,"*OK*")*3) + (COUNTIF(AW72:AY72,"*OK*")*2) + COUNTIF(AZ72:BB72,"*OK*")+COUNTIF(BK72:BK72,"SI")*0.5 -> 0 | BM72: =IF(BL72<0.6,"Demasiado Riesgo",IF(BL72<=5,"Riesgo Medio",IF(BL72<=11,"Riesgo Bajo","Cliente Blindado"))) -> Demasiado Riesgo | BP72: 0 | CL72: =COUNTIF(AT72:BH72,"*OK*") -> 0 | CN72: =COUNTIF(AT72:BH72,"*OP*") -> 0
A73: 26808 | B73: EMS970314UZ7 | C73: =AD73 -> 649.0066 | D73: =COUNTIF(AT73:BH73,"*OK*") -> 1 | E73: Raúl Campos | F73: EULEN MEXICO SA DE CV | G73: EULEN | H73: =IF(LEN(TRIM($G73&""))=0, $C73, SUMIF($G$3:$G$561, TRIM($G73), $C$3:$C$561)) -> 3660.4305 | I73: ENTERPRISE | L73: =HYPERLINK("https://crm.zoho.com/crm/org685875245/tab/Accounts/3525045000269312009","https://crm.zoho.com/crm/org685875245/tab/Accounts/3525045000269312009") -> https://crm.zoho.com/crm/org685875245/tab/Accounts/3525045000269312009 | M73: Expandir | R73: Invitación por parte de Tony | U73: - | V73: 820.45 | W73: 788.45 | X73: 664.32 | Y73: 669.17 | Z73: 650.6179 | AA73: 714.56 | AB73: 732.5758 | AC73: 724.0977 | AD73: 649.0066 | AE73: 3424 | AF73: 3060 | AI73: CDMX | AJ73: Outsourcing | AK73: Empresa del Grupo EULEN en México dedicada a servicios de outsourcing de personal, limpieza industrial y mantenimiento de instalaciones. | AN73: 1. Reuniones presenciales | AW73: OK(032026) | BJ73: =COUNTIF(AT73:BI73,"*OP*") -> 0 | BL73: =(COUNTIF(AT73:AV73,"*OK*")*3) + (COUNTIF(AW73:AY73,"*OK*")*2) + COUNTIF(AZ73:BB73,"*OK*")+COUNTIF(BK73:BK73,"SI")*0.5 -> 2 | BM73: =IF(BL73<0.6,"Demasiado Riesgo",IF(BL73<=5,"Riesgo Medio",IF(BL73<=11,"Riesgo Bajo","Cliente Blindado"))) -> Riesgo Medio | BP73: 0 | CL73: =COUNTIF(AT73:BH73,"*OK*") -> 1 | CN73: =COUNTIF(AT73:BH73,"*OP*") -> 0
A74: 21190 | B74: ARH071204CK8 | C74: =AD74 -> 665.4636 | D74: =COUNTIF(AT74:BH74,"*OK*") -> 0 | E74: Dafne de la Rosa | F74: COMERCIALIZADORA IMU | H74: =IF(LEN(TRIM($G74&""))=0, $C74, SUMIF($G$3:$G$561, TRIM($G74), $C$3:$C$561)) -> 665.4636 | I74: ENTERPRISE | L74: =HYPERLINK("https://crm.zoho.com/crm/org685875245/tab/Accounts/3525045000187101102","https://crm.zoho.com/crm/org685875245/tab/Accounts/3525045000187101102") -> https://crm.zoho.com/crm/org685875245/tab/Accounts/3525045000187101102 | M74: Mantener | O74: Oscar | P74: 5531519094 | Q74: ocampo@imu.com.mx | R74: Invitado | U74: 16. Logistica | V74: 659.8 | W74: 659.2 | X74: 628.21 | Y74: 648.43 | Z74: 657.1518 | AB74: 728.2544 | AC74: 707.562 | AD74: 665.4636 | AE74: 373 | AF74: 200 | AH74: CDMX | AI74: CDMX | AJ74: Manufactura | AK74: Empresa manufacturera y comercializadora de productos industriales con sede en CDMX, orientada al abastecimiento de insumos para planta productiva. | AL74: Planta Productiva | BJ74: =COUNTIF(AT74:BI74,"*OP*") -> 0 | BL74: =(COUNTIF(AT74:AV74,"*OK*")*3) + (COUNTIF(AW74:AY74,"*OK*")*2) + COUNTIF(AZ74:BB74,"*OK*")+COUNTIF(BK74:BK74,"SI")*0.5 -> 0 | BM74: =IF(BL74<0.6,"Demasiado Riesgo",IF(BL74<=5,"Riesgo Medio",IF(BL74<=11,"Riesgo Bajo","Cliente Blindado"))) -> Demasiado Riesgo | BP74: 0 | CL74: =COUNTIF(AT74:BH74,"*OK*") -> 0 | CN74: =COUNTIF(AT74:BH74,"*OP*") -> 0
A75: 20005 | B75: OCM050331BC9 | C75: =AD75 -> 897.0197 | D75: =COUNTIF(AT75:BH75,"*OK*") -> 0 | E75: Raúl Campos | F75: OPCEM | G75: ALEATICA | H75: =IF(LEN(TRIM($G75&""))=0, $C75, SUMIF($G$3:$G$561, TRIM($G75), $C$3:$C$561)) -> 4240.7286 | I75: ENTERPRISE | K75: FDP | M75: Mantener | O75: Monica | P75: 5560790550 | Q75: monica.espino@aleatica.com | R75: Registrado | U75: - | V75: 670.53 | W75: 658.32 | X75: 636.21 | Y75: 658.97 | Z75: 677.077 | AA75: 699.36 | AB75: 705.2641 | AC75: 706.4939 | AD75: 897.0197 | AE75: 1417 | AF75: 200 | AI75: Estado de México | AJ75: Transporte | AK75: Empresa del Grupo Aleatica responsable de la operación y conservación de tramos de autopistas concesionadas en el Estado de México. | AN75: 2. Videollamada | AS75: Petal / Success Factors | BJ75: =COUNTIF(AT75:BI75,"*OP*") -> 0 | BL75: =(COUNTIF(AT75:AV75,"*OK*")*3) + (COUNTIF(AW75:AY75,"*OK*")*2) + COUNTIF(AZ75:BB75,"*OK*")+COUNTIF(BK75:BK75,"SI")*0.5 -> 0 | BM75: =IF(BL75<0.6,"Demasiado Riesgo",IF(BL75<=5,"Riesgo Medio",IF(BL75<=11,"Riesgo Bajo","Cliente Blindado"))) -> Demasiado Riesgo | BP75: 0 | CL75: =COUNTIF(AT75:BH75,"*OK*") -> 0 | CN75: =COUNTIF(AT75:BH75,"*OP*") -> 0
A76: 23369 | B76: IES020111TDA | C76: =AD76 -> 658.9404 | D76: =COUNTIF(AT76:BH76,"*OK*") -> 3 | E76: Karla Patiño | F76: SOCIEDAD INDUSTRIAL EQUIPOS Y SERVICIOS (SIES) | H76: =IF(LEN(TRIM($G76&""))=0, $C76, SUMIF($G$3:$G$561, TRIM($G76), $C$3:$C$561)) -> 658.9404 | I76: SMB | L76: =HYPERLINK("https://crm.zoho.com/crm/org685875245/tab/Accounts/3525045000303849074","https://crm.zoho.com/crm/org685875245/tab/Accounts/3525045000303849074") -> https://crm.zoho.com/crm/org685875245/tab/Accounts/3525045000303849074 | M76: Expandir | N76: Datainvaders con la Fran | O76: Gema | P76: 5519481760 | Q76: iguerrero@siesmex.com.mx | R76: Registrado | U76: 20. Servicios | V76: 187.28 | W76: 200.63 | X76: 199.79 | Y76: 172.96 | Z76: 399.3715 | AA76: 422.53 | AB76: 664.9304 | AC76: 686.0737 | AD76: 658.9404 | AE76: 241 | AF76: 10 | AI76: CDMX | AJ76: Manufactura | AK76: Empresa industrial dedicada al suministro de equipos y servicios especializados para el sector manufacturero, con soluciones de mantenimiento, instalación y operación de maquinaria industrial. | AS76: SI | AV76: OK | BA76: OK | BD76: OK | BJ76: =COUNTIF(AT76:BI76,"*OP*") -> 0 | BK76: NO (compró) | BL76: =(COUNTIF(AT76:AV76,"*OK*")*3) + (COUNTIF(AW76:AY76,"*OK*")*2) + COUNTIF(AZ76:BB76,"*OK*")+COUNTIF(BK76:BK76,"SI")*0.5 -> 4 | BM76: =IF(BL76<0.6,"Demasiado Riesgo",IF(BL76<=5,"Riesgo Medio",IF(BL76<=11,"Riesgo Bajo","Cliente Blindado"))) -> Riesgo Medio | BP76: 0 | CL76: =COUNTIF(AT76:BH76,"*OK*") -> 3 | CN76: =COUNTIF(AT76:BH76,"*OP*") -> 0
A77: 26665 | B77: CIN930226HQ0 | C77: =AD77 -> 617.3659 | D77: =COUNTIF(AT77:BH77,"*OK*") -> 0 | E77: Dafne de la Rosa | F77: CINMSA | H77: =IF(LEN(TRIM($G77&""))=0, $C77, SUMIF($G$3:$G$561, TRIM($G77), $C$3:$C$561)) -> 617.3659 | I77: ENTERPRISE | L77: =HYPERLINK("https://crm.zoho.com/crm/org685875245/tab/Accounts/3525045000353562087","https://crm.zoho.com/crm/org685875245/tab/Accounts/3525045000353562087") -> https://crm.zoho.com/crm/org685875245/tab/Accounts/3525045000353562087 | M77: Mantener | O77: Itzel Benito Benito hernandez | P77: +52555555555 | Q77: itzel.benito@cinmsa.com.mx | R77: Invitar | S77: Mapeada en agosto | U77: 3. Construcción | V77: 714.35 | W77: 640.35 | X77: 615.91 | Y77: 614.28 | Z77: 683.8166 | AA77: 662.64 | AB77: 735.2453 | AC77: 676.4956 | AD77: 617.3659 | AE77: 321 | AF77: 300 | AH77: EDOMEX | AI77: Estado de México | AJ77: Construcción | AK77: Empresa constructora con sede en Estado de México especializada en obras civiles, infraestructura y proyectos de edificación industrial. | AL77: Construcción | AS77: SI | BJ77: =COUNTIF(AT77:BI77,"*OP*") -> 0 | BL77: =(COUNTIF(AT77:AV77,"*OK*")*3) + (COUNTIF(AW77:AY77,"*OK*")*2) + COUNTIF(AZ77:BB77,"*OK*")+COUNTIF(BK77:BK77,"SI")*0.5 -> 0 | BM77: =IF(BL77<0.6,"Demasiado Riesgo",IF(BL77<=5,"Riesgo Medio",IF(BL77<=11,"Riesgo Bajo","Cliente Blindado"))) -> Demasiado Riesgo | BP77: 0 | CL77: =COUNTIF(AT77:BH77,"*OK*") -> 0 | CN77: =COUNTIF(AT77:BH77,"*OP*") -> 0
A78: 26829-24649 | B78: GSI091216BL8 | C78: =AD78 -> 613.1329 | D78: =COUNTIF(AT78:BH78,"*OK*") -> 0 | E78: Raúl Campos | F78: GRUPO SABER INTEGRARSE (Saberin) | H78: =IF(LEN(TRIM($G78&""))=0, $C78, SUMIF($G$3:$G$561, TRIM($G78), $C$3:$C$561)) -> 613.1329 | I78: ENTERPRISE | L78: =HYPERLINK("https://crm.zoho.com/crm/org685875245/tab/Accounts/3525045000305241333","https://crm.zoho.com/crm/org685875245/tab/Accounts/3525045000305241333") -> https://crm.zoho.com/crm/org685875245/tab/Accounts/3525045000305241333 | M78: Expandir | O78: Paula | P78: 5523282503 | Q78: montserrat@lfcmexico.com.mx | U78: - | V78: 627.09 | W78: 584.22 | X78: 569.35 | Y78: 594.18 | Z78: 562.2298 | AA78: 578.46 | AB78: 606.5272 | AC78: 662.9331 | AD78: 613.1329 | AE78: 307 | AF78: 150 | AI78: CDMX | AJ78: Servicios | AK78: Empresa de consultoría y capacitación empresarial enfocada en integración de equipos, desarrollo organizacional y formación de capital humano. | AN78: 2. Videollamada | BI78: OP (Q2-Q3, 10926) | BJ78: =COUNTIF(AT78:BI78,"*OP*") -> 1 | BL78: =(COUNTIF(AT78:AV78,"*OK*")*3) + (COUNTIF(AW78:AY78,"*OK*")*2) + COUNTIF(AZ78:BB78,"*OK*")+COUNTIF(BK78:BK78,"SI")*0.5 -> 0 | BM78: =IF(BL78<0.6,"Demasiado Riesgo",IF(BL78<=5,"Riesgo Medio",IF(BL78<=11,"Riesgo Bajo","Cliente Blindado"))) -> Demasiado Riesgo | BP78: 0 | CL78: =COUNTIF(AT78:BH78,"*OK*") -> 0 | CN78: =COUNTIF(AT78:BH78,"*OP*") -> 0
A79: 35427 | B79: DIA1410035SA | C79: =AD79 -> 555.7394 | D79: =COUNTIF(AT79:BH79,"*OK*") -> 2 | E79: Dafne de la Rosa | F79: OAXX PROYECTOS (DESARROLLO INTEGRAL ADMINISTRATIVO LUAN / GRUPO IPS)) | H79: =IF(LEN(TRIM($G79&""))=0, $C79, SUMIF($G$3:$G$561, TRIM($G79), $C$3:$C$561)) -> 555.7394 | I79: ENTERPRISE | L79: =HYPERLINK("https://crm.zoho.com/crm/org685875245/tab/Accounts/3525045000256468003","https://crm.zoho.com/crm/org685875245/tab/Accounts/3525045000256468003") -> https://crm.zoho.com/crm/org685875245/tab/Accounts/3525045000256468003 | M79: Mantener | O79: Leslie | P79: 528126126781 | Q79: auxiliarrh2@ipsco.com.mx | U79: - | V79: 332.25 | W79: 788.02 | X79: 644.27 | Y79: 576.43 | Z79: 632.7088 | AA79: 640.17 | AB79: 725.431 | AC79: 659.9029 | AD79: 555.7394 | AE79: 172 | AF79: 500 | AI79: CDMX | AJ79: Servicios | AK79: Empresa del Grupo IPS dedicada a outsourcing administrativo y gestión integral de recursos humanos para clientes corporativos. | AL79: Servicios | AU79: OK(122025) | AV79: OK(122025) | AW79: OP | BJ79: =COUNTIF(AT79:BI79,"*OP*") -> 1 | BL79: =(COUNTIF(AT79:AV79,"*OK*")*3) + (COUNTIF(AW79:AY79,"*OK*")*2) + COUNTIF(AZ79:BB79,"*OK*")+COUNTIF(BK79:BK79,"SI")*0.5 -> 6 | BM79: =IF(BL79<0.6,"Demasiado Riesgo",IF(BL79<=5,"Riesgo Medio",IF(BL79<=11,"Riesgo Bajo","Cliente Blindado"))) -> Riesgo Bajo | BP79: 0 | CL79: =COUNTIF(AT79:BH79,"*OK*") -> 2 | CN79: =COUNTIF(AT79:BH79,"*OP*") -> 1
A80: 20416 | B80: CDO0402126Z1 | C80: =AD80 -> 628.2583 | D80: =COUNTIF(AT80:BH80,"*OK*") -> 1 | E80: Raúl Campos | F80: COMERCIALIZADORA DOMARTS | G80: CONVERSE | H80: =IF(LEN(TRIM($G80&""))=0, $C80, SUMIF($G$3:$G$561, TRIM($G80), $C$3:$C$561)) -> 986.4757 | I80: ENTERPRISE | M80: Mantener | O80: Jose | P80: 5579474263 | Q80: jose.weingers@converse.com.mx | R80: No están en CDMX | U80: - | V80: 651.63 | W80: 668.4 | X80: 628.7 | Y80: 663.17 | Z80: 700.9359 | AA80: 721.78 | AB80: 676.0827 | AC80: 656.2836 | AD80: 628.2583 | AE80: 365 | AF80: 100 | AI80: CDMX | AJ80: Retail | AK80: Empresa comercializadora y distribuidora de productos de consumo con operaciones en la Ciudad de México, orientada a canales de venta modernos y tradicionales. | AN80: 4. Whatsapp | AS80: SI | AV80: OK | BJ80: =COUNTIF(AT80:BI80,"*OP*") -> 0 | BK80: NO | BL80: =(COUNTIF(AT80:AV80,"*OK*")*3) + (COUNTIF(AW80:AY80,"*OK*")*2) + COUNTIF(AZ80:BB80,"*OK*")+COUNTIF(BK80:BK80,"SI")*0.5 -> 3 | BM80: =IF(BL80<0.6,"Demasiado Riesgo",IF(BL80<=5,"Riesgo Medio",IF(BL80<=11,"Riesgo Bajo","Cliente Blindado"))) -> Riesgo Medio | BP80: 0 | CL80: =COUNTIF(AT80:BH80,"*OK*") -> 1 | CN80: =COUNTIF(AT80:BH80,"*OP*") -> 0
A81: 33251 | B81: CAG120903M8A | C81: =AD81 -> 608.096 | D81: =COUNTIF(AT81:BH81,"*OK*") -> 0 | E81: Karla Patiño | F81: C. & G. OFTALMOLOGOS (San Angel Oftalmologica) | H81: =IF(LEN(TRIM($G81&""))=0, $C81, SUMIF($G$3:$G$561, TRIM($G81), $C$3:$C$561)) -> 608.096 | I81: ENTERPRISE | L81: =HYPERLINK("https://crm.zoho.com/crm/org685875245/tab/Accounts/3525045000506213377","https://crm.zoho.com/crm/org685875245/tab/Accounts/3525045000506213377") -> https://crm.zoho.com/crm/org685875245/tab/Accounts/3525045000506213377 | M81: Expandir | N81: Ver op de alertas, ofrecer 2 meses gratis y se factura al 3° Reunión viernes 23. Revisar herramienta de cop | O81: Noe | P81: 3333333333 | Q81: noefernandoocampo@gmail.com | R81: GDL | U81: - | V81: 539.52 | W81: 536.27 | X81: 521.59 | Y81: 538.38 | Z81: 551.1361 | AA81: 547.82 | AB81: 555.1881 | AC81: 640.9673 | AD81: 608.096 | AE81: 230 | AF81: 200 | AI81: Guadalajara | AJ81: Salud | AK81: Centro oftalmológico especializado en diagnóstico y tratamiento de enfermedades oculares, con sedes en la Ciudad de México. | AV81: OP (SIGUIENTE Q) | BJ81: =COUNTIF(AT81:BI81,"*OP*") -> 1 | BL81: =(COUNTIF(AT81:AV81,"*OK*")*3) + (COUNTIF(AW81:AY81,"*OK*")*2) + COUNTIF(AZ81:BB81,"*OK*")+COUNTIF(BK81:BK81,"SI")*0.5 -> 0 | BM81: =IF(BL81<0.6,"Demasiado Riesgo",IF(BL81<=5,"Riesgo Medio",IF(BL81<=11,"Riesgo Bajo","Cliente Blindado"))) -> Demasiado Riesgo | BP81: 0 | CL81: =COUNTIF(AT81:BH81,"*OK*") -> 0 | CN81: =COUNTIF(AT81:BH81,"*OP*") -> 1
A82: 5901 | B82: NMS940324RY6 | C82: =AD82 -> 551.8764 | D82: =COUNTIF(AT82:BH82,"*OK*") -> 1 | E82: Raúl Campos | F82: NETAFIM MEXICO SA DE CV | G82: NETAFIM | H82: =IF(LEN(TRIM($G82&""))=0, $C82, SUMIF($G$3:$G$561, TRIM($G82), $C$3:$C$561)) -> 1381.8985 | I82: ENTERPRISE | L82: =HYPERLINK("https://crm.zoho.com/crm/org685875245/tab/Accounts/3525045000010332421","https://crm.zoho.com/crm/org685875245/tab/Accounts/3525045000010332421") -> https://crm.zoho.com/crm/org685875245/tab/Accounts/3525045000010332421 | M82: Expandir | O82: ALEJANDRA ESCOBEDO ESCOBEDO CRUZ | P82: +528991601534 | Q82: alejandra.escobedo@netafim.orbia.com | U82: - | V82: 148 | W82: 166.96 | X82: 153.58 | Y82: 158.53 | Z82: 156.7907 | AA82: 918.77 | AB82: 490.2853 | AC82: 628.8618 | AD82: 551.8764 | AE82: 226 | AF82: 300 | AI82: CDMX | AJ82: Manufactura | AK82: Subsidiaria de Netafim, empresa israelí líder mundial en sistemas de riego por goteo y soluciones de irrigación para agricultura de precisión, con operaciones de manufactura y distribución en México. | AN82: 4. Whatsapp | AV82: OK | BJ82: =COUNTIF(AT82:BI82,"*OP*") -> 0 | BL82: =(COUNTIF(AT82:AV82,"*OK*")*3) + (COUNTIF(AW82:AY82,"*OK*")*2) + COUNTIF(AZ82:BB82,"*OK*")+COUNTIF(BK82:BK82,"SI")*0.5 -> 3 | BM82: =IF(BL82<0.6,"Demasiado Riesgo",IF(BL82<=5,"Riesgo Medio",IF(BL82<=11,"Riesgo Bajo","Cliente Blindado"))) -> Riesgo Medio | BP82: 0 | CL82: =COUNTIF(AT82:BH82,"*OK*") -> 1 | CN82: =COUNTIF(AT82:BH82,"*OP*") -> 0
A83: 26820 | B83: TJA170719450 | C83: =AD83 -> 583.9956 | D83: 1 | E83: Dafne de la Rosa | F83: TRIBUNAL DE JUSTICIA ADMINISTRATIVA DEL ESTADO DE MEXICO (Gobierno del estado de mexico) | H83: =IF(LEN(TRIM($G83&""))=0, $C83, SUMIF($G$3:$G$561, TRIM($G83), $C$3:$C$561)) -> 583.9956 | I83: ENTERPRISE | L83: =HYPERLINK("https://crm.zoho.com/crm/org685875245/tab/Accounts/3525045000278421021","https://crm.zoho.com/crm/org685875245/tab/Accounts/3525045000278421021") -> https://crm.zoho.com/crm/org685875245/tab/Accounts/3525045000278421021 | M83: Mantener | N83: Presupuesto anual, salir a buscarlos a inicio del Q4 | O83: Jose Alfredo Montoya | P83: 7291052817 | Q83: jose.montoya@trijaem.gob.mx | U83: - | V83: 782.19 | W83: 781.48 | X83: 774.75 | Y83: 887.72 | Z83: 808.7924 | AA83: 616.07 | AB83: 609.7308 | AC83: 624.2966 | AD83: 583.9956 | AE83: 366 | AF83: 500 | AH83: Toluca | AI83: Estado de México | AJ83: Gobierno | AK83: Órgano jurisdiccional autónomo del Estado de México encargado de resolver conflictos entre ciudadanos y la administración pública estatal y municipal. | AL83: Gobierno | AS83: SI | BJ83: =COUNTIF(AT83:BI83,"*OP*") -> 0 | BL83: =(COUNTIF(AT83:AV83,"*OK*")*3) + (COUNTIF(AW83:AY83,"*OK*")*2) + COUNTIF(AZ83:BB83,"*OK*")+COUNTIF(BK83:BK83,"SI")*0.5 -> 0 | BM83: =IF(BL83<0.6,"Demasiado Riesgo",IF(BL83<=5,"Riesgo Medio",IF(BL83<=11,"Riesgo Bajo","Cliente Blindado"))) -> Demasiado Riesgo | BP83: 0 | CL83: =COUNTIF(AT83:BH83,"*OK*") -> 0 | CN83: =COUNTIF(AT83:BH83,"*OP*") -> 0
A84: 2075 | B84: KLA140509S32 | C84: =AD84 -> 551.6893 | D84: =COUNTIF(AT84:BH84,"*OK*") -> 0 | E84: Dafne de la Rosa | F84: KLIP LAB | H84: =IF(LEN(TRIM($G84&""))=0, $C84, SUMIF($G$3:$G$561, TRIM($G84), $C$3:$C$561)) -> 551.6893 | I84: ENTERPRISE | L84: =HYPERLINK("https://crm.zoho.com/crm/org685875245/tab/Accounts/3525045000025415384","https://crm.zoho.com/crm/org685875245/tab/Accounts/3525045000025415384") -> https://crm.zoho.com/crm/org685875245/tab/Accounts/3525045000025415384 | M84: Mantener | O84: Zaira Raciel Hernandez Martinez | P84: 5651181648 | Q84: leicar_87@hotmail.com | U84: 20. Servicios | V84: 544.43 | W84: 521.82 | X84: 514.15 | Y84: 548.1 | Z84: 551.0639 | AA84: 579.9 | AB84: 611.1765 | AC84: 617.9346 | AD84: 551.6893 | AE84: 136 | AF84: 100 | AH84: CDMX | AI84: CDMX | AJ84: Tecnología | AK84: Empresa de tecnología y servicios digitales con sede en CDMX, especializada en soluciones de software y plataformas para empresas. | AL84: Servicios | BJ84: =COUNTIF(AT84:BI84,"*OP*") -> 0 | BL84: =(COUNTIF(AT84:AV84,"*OK*")*3) + (COUNTIF(AW84:AY84,"*OK*")*2) + COUNTIF(AZ84:BB84,"*OK*")+COUNTIF(BK84:BK84,"SI")*0.5 -> 0 | BM84: =IF(BL84<0.6,"Demasiado Riesgo",IF(BL84<=5,"Riesgo Medio",IF(BL84<=11,"Riesgo Bajo","Cliente Blindado"))) -> Demasiado Riesgo | BP84: 0 | CL84: =COUNTIF(AT84:BH84,"*OK*") -> 0 | CN84: =COUNTIF(AT84:BH84,"*OP*") -> 0
A85: 35128 | B85: BRC0109073D0 | C85: =AD85 -> 564.9834 | D85: =COUNTIF(AT85:BH85,"*OK*") -> 0 | E85: Raúl Campos | F85: BARRADAS REFRIGERACION COMERCIAL | H85: =IF(LEN(TRIM($G85&""))=0, $C85, SUMIF($G$3:$G$561, TRIM($G85), $C$3:$C$561)) -> 564.9834 | I85: ENTERPRISE | M85: Alcanzar | N85: Tienen modulo antiguo, quieren migrar al modulo nuevo. Lunes 15 se haría la migración | O85: Rogelio | P85: 5212282854559 | Q85: seguridadsocial@barradas.mx | U85: - | V85: 684.45 | W85: 707 | X85: 680.66 | Y85: 684.05 | Z85: 691.8086 | AA85: 679.94 | AB85: 685.6735 | AC85: 611.2875 | AD85: 564.9834 | AE85: 438 | AF85: 200 | AI85: CDMX | AJ85: Servicios | AK85: Empresa especializada en refrigeración comercial e industrial, con servicios de instalación, mantenimiento y reparación de equipos de frío. | AN85: 5. Mail | BJ85: =COUNTIF(AT85:BI85,"*OP*") -> 0 | BL85: =(COUNTIF(AT85:AV85,"*OK*")*3) + (COUNTIF(AW85:AY85,"*OK*")*2) + COUNTIF(AZ85:BB85,"*OK*")+COUNTIF(BK85:BK85,"SI")*0.5 -> 0 | BM85: =IF(BL85<0.6,"Demasiado Riesgo",IF(BL85<=5,"Riesgo Medio",IF(BL85<=11,"Riesgo Bajo","Cliente Blindado"))) -> Demasiado Riesgo | BP85: 0 | CL85: =COUNTIF(AT85:BH85,"*OK*") -> 0 | CN85: =COUNTIF(AT85:BH85,"*OP*") -> 0
A86: 25238 | B86: TME930119HR3 | C86: =AD86 -> 560.9404 | D86: =COUNTIF(AT86:BH86,"*OK*") -> 0 | E86: Dafne de la Rosa | F86: TOTALENERGIES MARKETING MEXICO | H86: =IF(LEN(TRIM($G86&""))=0, $C86, SUMIF($G$3:$G$561, TRIM($G86), $C$3:$C$561)) -> 560.9404 | I86: ENTERPRISE | L86: =HYPERLINK("https://crm.zoho.com/crm/org685875245/tab/Accounts/3525045000269171061","https://crm.zoho.com/crm/org685875245/tab/Accounts/3525045000269171061") -> https://crm.zoho.com/crm/org685875245/tab/Accounts/3525045000269171061 | M86: Alcanzar | O86: Said | P86: 3338122300 | Q86: marisol.gutierrez@totalenergies.com | U86: 17. Retail Enterprise | V86: 558.54 | W86: 568.36 | X86: 538.36 | Y86: 548.91 | Z86: 570.0295 | AA86: 597.74 | AB86: 582.2347 | AC86: 596.4265 | AD86: 560.9404 | AE86: 170 | AF86: 500 | AH86: Jalisco | AI86: Jalisco | AJ86: Energía | AK86: Filial de TotalEnergies en México dedicada a la comercialización y distribución de combustibles, lubricantes y energía para el sector industrial y automotriz. | AL86: Retail Enterprise | AS86: SI | AY86: OP ($0) | BJ86: =COUNTIF(AT86:BI86,"*OP*") -> 1 | BK86: NO | BL86: =(COUNTIF(AT86:AV86,"*OK*")*3) + (COUNTIF(AW86:AY86,"*OK*")*2) + COUNTIF(AZ86:BB86,"*OK*")+COUNTIF(BK86:BK86,"SI")*0.5 -> 0 | BM86: =IF(BL86<0.6,"Demasiado Riesgo",IF(BL86<=5,"Riesgo Medio",IF(BL86<=11,"Riesgo Bajo","Cliente Blindado"))) -> Demasiado Riesgo | BP86: 0 | CL86: =COUNTIF(AT86:BH86,"*OK*") -> 0 | CN86: =COUNTIF(AT86:BH86,"*OP*") -> 1
A87: 6588 | B87: MAR940516K16 | C87: =AD87 -> 540.7837 | D87: =COUNTIF(AT87:BH87,"*OK*") -> 0 | E87: Raúl Campos | F87: MEXICANA DE ARROZ | G87: SCHETTINO | H87: =IF(LEN(TRIM($G87&""))=0, $C87, SUMIF($G$3:$G$561, TRIM($G87), $C$3:$C$561)) -> 2091.1148 | I87: ENTERPRISE | M87: Mantener | O87: - | P87: - | Q87: - | R87: No están en CDMX | U87: - | V87: 560.61 | W87: 582.99 | X87: 546.85 | Y87: 571.18 | Z87: 597.1218 | AA87: 555.78 | AB87: 572.9695 | AC87: 555.9239 | AD87: 540.7837 | AE87: 858 | AF87: 200 | AI87: CDMX | AJ87: Manufactura | AK87: Empresa del grupo Schettino productora y comercializadora de arroz y productos arroceros bajo diversas marcas para el mercado nacional. | AN87: 4. Whatsapp | BJ87: =COUNTIF(AT87:BI87,"*OP*") -> 0 | BL87: =(COUNTIF(AT87:AV87,"*OK*")*3) + (COUNTIF(AW87:AY87,"*OK*")*2) + COUNTIF(AZ87:BB87,"*OK*")+COUNTIF(BK87:BK87,"SI")*0.5 -> 0 | BM87: =IF(BL87<0.6,"Demasiado Riesgo",IF(BL87<=5,"Riesgo Medio",IF(BL87<=11,"Riesgo Bajo","Cliente Blindado"))) -> Demasiado Riesgo | BP87: 0 | CL87: =COUNTIF(AT87:BH87,"*OK*") -> 0 | CN87: =COUNTIF(AT87:BH87,"*OP*") -> 0
A88: 27573 | B88: ULA751222J13 | C88: =AD88 -> 544.8256 | D88: =COUNTIF(AT88:BH88,"*OK*") -> 0 | E88: Dafne de la Rosa | F88: UNIVERSIDAD LATINOAMERICANA | H88: =IF(LEN(TRIM($G88&""))=0, $C88, SUMIF($G$3:$G$561, TRIM($G88), $C$3:$C$561)) -> 544.8256 | I88: ENTERPRISE | L88: =HYPERLINK("https://crm.zoho.com/crm/org685875245/tab/Accounts/3525045000374297001","https://crm.zoho.com/crm/org685875245/tab/Accounts/3525045000374297001") -> https://crm.zoho.com/crm/org685875245/tab/Accounts/3525045000374297001 | M88: Expandir | O88: Ignacio Valenzuela | P88: 5585516857 | Q88: iganacio.valenzuela@utc.mx | U88: 7. Educación | V88: 553.38 | W88: 545.66 | X88: 503.97 | Y88: 522.56 | Z88: 529.5921 | AA88: 516.68 | AB88: 528.2037 | AC88: 550.0842 | AD88: 544.8256 | AE88: 210 | AF88: 500 | AH88: Nuevo Leon | AI88: CDMX | AJ88: Educación | AK88: Universidad privada mexicana con campus en CDMX, Nuevo León y otras ciudades, con oferta educativa de licenciaturas, posgrados y educación continua. | AL88: Educación | BJ88: =COUNTIF(AT88:BI88,"*OP*") -> 0 | BL88: =(COUNTIF(AT88:AV88,"*OK*")*3) + (COUNTIF(AW88:AY88,"*OK*")*2) + COUNTIF(AZ88:BB88,"*OK*")+COUNTIF(BK88:BK88,"SI")*0.5 -> 0 | BM88: =IF(BL88<0.6,"Demasiado Riesgo",IF(BL88<=5,"Riesgo Medio",IF(BL88<=11,"Riesgo Bajo","Cliente Blindado"))) -> Demasiado Riesgo | BP88: 0 | CL88: =COUNTIF(AT88:BH88,"*OK*") -> 0 | CN88: =COUNTIF(AT88:BH88,"*OP*") -> 0
A89: 23652 | B89: PJU190215RN2 | C89: =AD89 -> 555.144 | D89: =COUNTIF(AT89:BH89,"*OK*") -> 1 | E89: Raúl Campos | F89: PODER JUSTO | H89: =IF(LEN(TRIM($G89&""))=0, $C89, SUMIF($G$3:$G$561, TRIM($G89), $C$3:$C$561)) -> 555.144 | I89: ENTERPRISE | L89: =HYPERLINK("https://crm.zoho.com/crm/org685875245/tab/Accounts/3525045000318641064","https://crm.zoho.com/crm/org685875245/tab/Accounts/3525045000318641064") -> https://crm.zoho.com/crm/org685875245/tab/Accounts/3525045000318641064 | M89: Mantener | O89: Karina | P89: 5513728694 | Q89: karina.ordaz@justo.mx | U89: - | V89: 1791.87 | W89: 501.19 | X89: 517.15 | Y89: 432.99 | Z89: 517.879 | AA89: 544.78 | AB89: 515.207 | AC89: 543.4171 | AD89: 555.144 | AE89: 1507 | AF89: 300 | AI89: CDMX | AJ89: Outsourcing | AK89: Empresa de outsourcing de nómina y gestión de personal, especializada en administración de empleados para empresas medianas y grandes. | AN89: 4. Whatsapp | AW89: OK(052026) | BJ89: =COUNTIF(AT89:BI89,"*OP*") -> 0 | BL89: =(COUNTIF(AT89:AV89,"*OK*")*3) + (COUNTIF(AW89:AY89,"*OK*")*2) + COUNTIF(AZ89:BB89,"*OK*")+COUNTIF(BK89:BK89,"SI")*0.5 -> 2 | BM89: =IF(BL89<0.6,"Demasiado Riesgo",IF(BL89<=5,"Riesgo Medio",IF(BL89<=11,"Riesgo Bajo","Cliente Blindado"))) -> Riesgo Medio | BP89: 0 | CL89: =COUNTIF(AT89:BH89,"*OK*") -> 1 | CN89: =COUNTIF(AT89:BH89,"*OP*") -> 0
A90: 6975 | B90: TLM1402276K0 | C90: =AD90 -> 429.9106 | D90: =COUNTIF(AT90:BH90,"*OK*") -> 1 | E90: Dafne de la Rosa | F90: TRANSPORTACION Y LOGISTICA MALDONADO (TRANSMAL) | H90: =IF(LEN(TRIM($G90&""))=0, $C90, SUMIF($G$3:$G$561, TRIM($G90), $C$3:$C$561)) -> 429.9106 | I90: ENTERPRISE | L90: =HYPERLINK("https://crm.zoho.com/crm/org685875245/tab/Accounts/3525045000094546145","https://crm.zoho.com/crm/org685875245/tab/Accounts/3525045000094546145") -> https://crm.zoho.com/crm/org685875245/tab/Accounts/3525045000094546145 | M90: Mantener | O90: Lucia | P90: 5534961937 | Q90: lucia.labrada86@gmail.com | R90: Invitado | U90: - | V90: 540.14 | W90: 550.03 | X90: 539 | Y90: 495.1 | Z90: 450.0355 | AA90: 434.87 | AB90: 448.8557 | AC90: 541.1733 | AD90: 429.9106 | AE90: 108 | AF90: 250 | AH90: EDOMEX | AI90: Estado de México | AJ90: Logística | AK90: Empresa de transporte y logística con flota propia para distribución de carga en la zona metropolitana del Valle de México y nacional. | AL90: Logistica | AS90: SI | AV90: OK(052025) | BJ90: =COUNTIF(AT90:BI90,"*OP*") -> 0 | BK90: NO | BL90: =(COUNTIF(AT90:AV90,"*OK*")*3) + (COUNTIF(AW90:AY90,"*OK*")*2) + COUNTIF(AZ90:BB90,"*OK*")+COUNTIF(BK90:BK90,"SI")*0.5 -> 3 | BM90: =IF(BL90<0.6,"Demasiado Riesgo",IF(BL90<=5,"Riesgo Medio",IF(BL90<=11,"Riesgo Bajo","Cliente Blindado"))) -> Riesgo Medio | BP90: 0 | CL90: =COUNTIF(AT90:BH90,"*OK*") -> 1 | CN90: =COUNTIF(AT90:BH90,"*OP*") -> 0
A91: 32676 | B91: HAL161209L83 | C91: =AD91 -> 539.6104 | D91: =COUNTIF(AT91:BH91,"*OK*") -> 0 | E91: Dafne de la Rosa | F91: HORIZON AUTO LOGISTICS | G91: HORIZON | H91: =IF(LEN(TRIM($G91&""))=0, $C91, SUMIF($G$3:$G$561, TRIM($G91), $C$3:$C$561)) -> 709.99 | I91: ENTERPRISE | L91: =HYPERLINK("https://crm.zoho.com/crm/org685875245/tab/Accounts/3525045000439364137","https://crm.zoho.com/crm/org685875245/tab/Accounts/3525045000439364137") -> https://crm.zoho.com/crm/org685875245/tab/Accounts/3525045000439364137 | M91: Mantener | O91: Jose | P91: 522291105230 | Q91: jose.navarro@horizonautologistics.com | T91: SI | U91: 16. Logistica | V91: 565.12 | W91: 517.21 | X91: 553.52 | Y91: 553.38 | Z91: 568.9146 | AA91: 548.68 | AB91: 531.1227 | AC91: 540.8869 | AD91: 539.6104 | AE91: 289 | AF91: 300 | AH91: CDMX | AI91: CDMX | AJ91: Logística | AK91: Empresa del grupo Horizon especializada en logística automotriz y transporte de vehículos para distribuidores y armadoras en México. | AL91: Logistica | BJ91: =COUNTIF(AT91:BI91,"*OP*") -> 0 | BL91: =(COUNTIF(AT91:AV91,"*OK*")*3) + (COUNTIF(AW91:AY91,"*OK*")*2) + COUNTIF(AZ91:BB91,"*OK*")+COUNTIF(BK91:BK91,"SI")*0.5 -> 0 | BM91: =IF(BL91<0.6,"Demasiado Riesgo",IF(BL91<=5,"Riesgo Medio",IF(BL91<=11,"Riesgo Bajo","Cliente Blindado"))) -> Demasiado Riesgo | BP91: 0 | CL91: =COUNTIF(AT91:BH91,"*OK*") -> 0 | CN91: =COUNTIF(AT91:BH91,"*OP*") -> 0
A92: 38736 | B92: AAS9610021I4 | C92: =AD92 -> 475.9933 | D92: =COUNTIF(AX92:BI92,"OK") -> 0 | E92: Karla Patiño | F92: ANCORA AGENTE DE SEGUROS Y DE FIANZAS | H92: =IF(LEN(TRIM($G92&""))=0, $C92, SUMIF($G$3:$G$561, TRIM($G92), $C$3:$C$561)) -> 475.9933 | I92: SMB | L92: =HYPERLINK("https://crm.zoho.com/crm/org685875245/tab/Accounts/3525045000350643029","https://crm.zoho.com/crm/org685875245/tab/Accounts/3525045000350643029") -> https://crm.zoho.com/crm/org685875245/tab/Accounts/3525045000350643029 | O92: Estephany Martinez | Q92: efarrera@ancora.com.mx | T92: SI | AA92: 482.81 | AB92: 525.2028 | AC92: 537.2054 | AD92: 475.9933 | AE92: 139 | AW92: OP (Q3) | BJ92: =COUNTIF(AT92:BI92,"*OP*") -> 1 | BL92: =(COUNTIF(AT92:AV92,"*OK*")*3) + (COUNTIF(AW92:AY92,"*OK*")*2) + COUNTIF(AZ92:BB92,"*OK*")+COUNTIF(BK92:BK92,"SI")*0.5 -> 0 | BM92: =IF(BL92<0.6,"Demasiado Riesgo",IF(BL92<=5,"Riesgo Medio",IF(BL92<=11,"Riesgo Bajo","Cliente Blindado"))) -> Demasiado Riesgo | BP92: 0 | CL92: =COUNTIF(AT92:BH92,"*OK*") -> 0 | CN92: =COUNTIF(AT92:BH92,"*OP*") -> 1
B93: TBU210421JV6 | C93: =AD93 -> 500.1004 | D93: =COUNTIF(AT93:BH93,"*OK*") -> 0 | E93: No Asignado | F93: TECH BUKERS (BUK) | H93: =IF(LEN(TRIM($G93&""))=0, $C93, SUMIF($G$3:$G$561, TRIM($G93), $C$3:$C$561)) -> 500.1004 | I93: ENTERPRISE | L93: =HYPERLINK("https://crm.zoho.com/crm/org685875245/tab/Accounts/3525045000194616020","https://crm.zoho.com/crm/org685875245/tab/Accounts/3525045000194616020") -> https://crm.zoho.com/crm/org685875245/tab/Accounts/3525045000194616020 | U93: - | V93: 525.62 | W93: 525.14 | X93: 500.45 | Y93: 516.56 | Z93: 523.5111 | AA93: 517.77 | AB93: 522.1386 | AC93: 531.7377 | AD93: 500.1004 | AF93: 300 | AI93: CDMX | AJ93: Tecnología | AK93: Plataforma SaaS chilena con operaciones en México (Tech Bukers) para gestión integral de recursos humanos, nómina, desempeño y clima laboral. | BJ93: =COUNTIF(AT93:BI93,"*OP*") -> 0 | BL93: =(COUNTIF(AT93:AV93,"*OK*")*3) + (COUNTIF(AW93:AY93,"*OK*")*2) + COUNTIF(AZ93:BB93,"*OK*")+COUNTIF(BK93:BK93,"SI")*0.5 -> 0 | BM93: =IF(BL93<0.6,"Demasiado Riesgo",IF(BL93<=5,"Riesgo Medio",IF(BL93<=11,"Riesgo Bajo","Cliente Blindado"))) -> Demasiado Riesgo | BP93: 0 | CL93: =COUNTIF(AT93:BH93,"*OK*") -> 0 | CN93: =COUNTIF(AT93:BH93,"*OP*") -> 0
A94: 24591 | B94: TBO181023J20 | C94: =AD94 -> 321.5828 | D94: =COUNTIF(AT94:BH94,"*OK*") -> 0 | E94: Karla Patiño | F94: TEAM BACK 11 | H94: =IF(LEN(TRIM($G94&""))=0, $C94, SUMIF($G$3:$G$561, TRIM($G94), $C$3:$C$561)) -> 321.5828 | I94: ENTERPRISE | M94: Recuperar | N94: Op mapeada, seguimiento porque no hay respuesta Desactivado por mora | O94: María | P94: 5635991773 | Q94: magdalena.lujano@teamback.com.mx | R94: No pueden ir | U94: - | V94: 587.47 | W94: 546.73 | X94: 555.5 | Y94: 569.43 | Z94: 585.1066 | AA94: 574.73 | AB94: 543.6019 | AC94: 521.0311 | AD94: 321.5828 | AE94: 139 | AF94: 200 | AI94: Estado de México | AJ94: Outsourcing | AK94: Empresa de outsourcing especializada en transporte de material peligroso y servicios de recursos humanos: reclutamiento, selección, capacitación y administración de personal. Sede en Tultitlán, Edo. Mex. | AT94: OP | AW94: OP (Q3) | BJ94: =COUNTIF(AT94:BI94,"*OP*") -> 2 | BL94: =(COUNTIF(AT94:AV94,"*OK*")*3) + (COUNTIF(AW94:AY94,"*OK*")*2) + COUNTIF(AZ94:BB94,"*OK*")+COUNTIF(BK94:BK94,"SI")*0.5 -> 0 | BM94: =IF(BL94<0.6,"Demasiado Riesgo",IF(BL94<=5,"Riesgo Medio",IF(BL94<=11,"Riesgo Bajo","Cliente Blindado"))) -> Demasiado Riesgo | BP94: 0 | CL94: =COUNTIF(AT94:BH94,"*OK*") -> 0 | CN94: =COUNTIF(AT94:BH94,"*OP*") -> 2
A95: 21582 | B95: CEC081223FJ2 | C95: =AD95 -> 497.1043 | D95: =COUNTIF(AT95:BH95,"*OK*") -> 0 | E95: Dafne de la Rosa | F95: CAFES DE ESPECIALIDAD DE CHIAPAS S.A.P.I. DE C.V. (CAFESCA)* | H95: =IF(LEN(TRIM($G95&""))=0, $C95, SUMIF($G$3:$G$561, TRIM($G95), $C$3:$C$561)) -> 497.1043 | I95: ENTERPRISE | L95: =HYPERLINK("https://crm.zoho.com/crm/org685875245/tab/Accounts/3525045000223883010","https://crm.zoho.com/crm/org685875245/tab/Accounts/3525045000223883010") -> https://crm.zoho.com/crm/org685875245/tab/Accounts/3525045000223883010 | M95: Mantener | O95: PAULO LOPEZ LOPEZ ALVAREZ | P95: +529622203955 | Q95: paulo.lopez@cafesca.com | U95: - | V95: 412.5 | W95: 521.24 | X95: 490.69 | Y95: 505.34 | Z95: 511.9673 | AA95: 505.39 | AB95: 508.4931 | AC95: 515.7289 | AD95: 497.1043 | AE95: 198 | AF95: 3000 | AH95: Chiapas | AI95: Chiapas | AJ95: Manufactura | AK95: Empresa productora y exportadora de café de especialidad en Chiapas, dedicada al cultivo, procesamiento y comercialización de café premium. | AL95: Planta Productiva | AR95: Human Eland | AU95: OP | AV95: NO - lo tienen en human | AY95: OP | AZ95: OP | BJ95: =COUNTIF(AT95:BI95,"*OP*") -> 3 | BL95: =(COUNTIF(AT95:AV95,"*OK*")*3) + (COUNTIF(AW95:AY95,"*OK*")*2) + COUNTIF(AZ95:BB95,"*OK*")+COUNTIF(BK95:BK95,"SI")*0.5 -> 0 | BM95: =IF(BL95<0.6,"Demasiado Riesgo",IF(BL95<=5,"Riesgo Medio",IF(BL95<=11,"Riesgo Bajo","Cliente Blindado"))) -> Demasiado Riesgo | BP95: 0 | CL95: =COUNTIF(AT95:BH95,"*OK*") -> 0 | CN95: =COUNTIF(AT95:BH95,"*OP*") -> 3
A96: 27824 | B96: DUE9506226QA | C96: =AD96 -> 478.9603 | D96: =COUNTIF(AT96:BH96,"*OK*") -> 0 | E96: Karla Patiño | F96: DOMUS URBANIZADORA Y EDIFICADORA | G96: DOMUS | H96: =IF(LEN(TRIM($G96&""))=0, $C96, SUMIF($G$3:$G$561, TRIM($G96), $C$3:$C$561)) -> 808.5674 | I96: SMB | M96: Mantener | O96: Brenda | P96: 3338140325 | Q96: psic.brendalizrosasrey@gmail.com | R96: GDL | U96: - | V96: 235.46 | W96: 227.13 | X96: 185.53 | Y96: 268.66 | Z96: 269.5598 | AA96: 213.28 | AB96: 207.0169 | AC96: 511.9981 | AD96: 478.9603 | AE96: 309 | AF96: 200 | AI96: CDMX | AJ96: Construcción | AK96: Empresa de desarrollo inmobiliario y edificación con sede en CDMX, especializada en proyectos residenciales, urbanizaciones y construcción de vivienda para el mercado local. | AS96: SI | AV96: OP | BJ96: =COUNTIF(AT96:BI96,"*OP*") -> 1 | BK96: NO | BL96: =(COUNTIF(AT96:AV96,"*OK*")*3) + (COUNTIF(AW96:AY96,"*OK*")*2) + COUNTIF(AZ96:BB96,"*OK*")+COUNTIF(BK96:BK96,"SI")*0.5 -> 0 | BM96: =IF(BL96<0.6,"Demasiado Riesgo",IF(BL96<=5,"Riesgo Medio",IF(BL96<=11,"Riesgo Bajo","Cliente Blindado"))) -> Demasiado Riesgo | BP96: 0 | CL96: =COUNTIF(AT96:BH96,"*OK*") -> 0 | CN96: =COUNTIF(AT96:BH96,"*OP*") -> 1
A97: 27596 | B97: FSN9905126S3 | C97: =AD97 -> 494.4636 | D97: =COUNTIF(AT97:BH97,"*OK*") -> 0 | E97: Dafne de la Rosa | F97: FARMACIAS SIMI DEL NORTE | H97: =IF(LEN(TRIM($G97&""))=0, $C97, SUMIF($G$3:$G$561, TRIM($G97), $C$3:$C$561)) -> 494.4636 | I97: ENTERPRISE | L97: =HYPERLINK("https://crm.zoho.com/crm/org685875245/tab/Accounts/3525045000401412566","https://crm.zoho.com/crm/org685875245/tab/Accounts/3525045000401412566") -> https://crm.zoho.com/crm/org685875245/tab/Accounts/3525045000401412566 | M97: Expandir | O97: Blanca | P97: 5218711891457 | Q97: blanca@simidelnorte.com | U97: - | V97: 516.09 | W97: 499.39 | X97: 496.53 | Y97: 510.74 | Z97: 494.246 | AA97: 504.82 | AB97: 518.0459 | AC97: 511.1402 | AD97: 494.4636 | AE97: 268 | AF97: 260 | AH97: Tamaulipas | AI97: Tamaulipas | AJ97: Retail | AK97: Franquicia regional de Farmacias Similares (Dr. Simi) con operaciones en el norte del país, distribuidora de medicamentos genéricos a bajo costo. | AL97: Retail Enterprise | AS97: SI | BJ97: =COUNTIF(AT97:BI97,"*OP*") -> 0 | BL97: =(COUNTIF(AT97:AV97,"*OK*")*3) + (COUNTIF(AW97:AY97,"*OK*")*2) + COUNTIF(AZ97:BB97,"*OK*")+COUNTIF(BK97:BK97,"SI")*0.5 -> 0 | BM97: =IF(BL97<0.6,"Demasiado Riesgo",IF(BL97<=5,"Riesgo Medio",IF(BL97<=11,"Riesgo Bajo","Cliente Blindado"))) -> Demasiado Riesgo | BP97: 0 | CL97: =COUNTIF(AT97:BH97,"*OK*") -> 0 | CN97: =COUNTIF(AT97:BH97,"*OP*") -> 0
A98: 29844 | B98: ESI180502TU8 | C98: =AD98 -> 413.9073 | D98: =COUNTIF(AT98:BH98,"*OK*") -> 0 | E98: Karla Patiño | F98: EB SIETE | H98: =IF(LEN(TRIM($G98&""))=0, $C98, SUMIF($G$3:$G$561, TRIM($G98), $C$3:$C$561)) -> 413.9073 | I98: SMB | N98: Asignar a Karla | O98: Mario | P98: 5214776320655 | Q98: controloperativo@ebsiete.com | R98: Guanajuato | U98: - | V98: 324.78 | W98: 324.52 | X98: 315.89 | Y98: 365.11 | Z98: 374.0677 | AA98: 371.97 | AB98: 492.0715 | AC98: 507.2791 | AD98: 413.9073 | AE98: 302 | AF98: 150 | AI98: CDMX | AJ98: Construcción | AK98: Empresa constructora e inmobiliaria con operaciones en CDMX, especializada en desarrollo de proyectos habitacionales y comerciales. | BJ98: =COUNTIF(AT98:BI98,"*OP*") -> 0 | BL98: =(COUNTIF(AT98:AV98,"*OK*")*3) + (COUNTIF(AW98:AY98,"*OK*")*2) + COUNTIF(AZ98:BB98,"*OK*")+COUNTIF(BK98:BK98,"SI")*0.5 -> 0 | BM98: =IF(BL98<0.6,"Demasiado Riesgo",IF(BL98<=5,"Riesgo Medio",IF(BL98<=11,"Riesgo Bajo","Cliente Blindado"))) -> Demasiado Riesgo | BP98: 0 | CL98: =COUNTIF(AT98:BH98,"*OK*") -> 0 | CN98: =COUNTIF(AT98:BH98,"*OP*") -> 0
A99: 17919 | B99: SCA210528AWA | C99: =AD99 -> 512.6175 | D99: =COUNTIF(AT99:BH99,"*OK*") -> 0 | E99: Dafne de la Rosa | F99: SINFOROSA CAFE | H99: =IF(LEN(TRIM($G99&""))=0, $C99, SUMIF($G$3:$G$561, TRIM($G99), $C$3:$C$561)) -> 512.6175 | I99: ENTERPRISE | L99: =HYPERLINK("https://crm.zoho.com/crm/org685875245/tab/Accounts/3525045000141005503","https://crm.zoho.com/crm/org685875245/tab/Accounts/3525045000141005503") -> https://crm.zoho.com/crm/org685875245/tab/Accounts/3525045000141005503 | M99: Mantener | N99: Se brinda seguimiento a la nueva admisnistradora. Apertura de 3 cafeterias. | O99: María | P99: 5209600674 | Q99: mariazavala.sinforosacafe@gmail.com | S99: Mapeada en agosto | U99: 22. Turismo, Hotelería y Gastronomía | V99: 838.1 | W99: 724.75 | X99: 720.85 | Y99: 809.81 | Z99: 638.3253 | AA99: 620.92 | AB99: 717.1078 | AC99: 502.2979 | AD99: 512.6175 | AE99: 133 | AF99: 150 | AH99: Queretaro | AI99: Querétaro | AJ99: Turismo y Gastronomía | AK99: Cadena de cafeterías y restaurantes con sede en Querétaro, especializada en café de especialidad y gastronomía artesanal mexicana. | AL99: Turismo, Hotelería y Gastronomía | AT99: OP | AV99: NO - lo tienen interno | AW99: OP | BJ99: =COUNTIF(AT99:BI99,"*OP*") -> 2 | BL99: =(COUNTIF(AT99:AV99,"*OK*")*3) + (COUNTIF(AW99:AY99,"*OK*")*2) + COUNTIF(AZ99:BB99,"*OK*")+COUNTIF(BK99:BK99,"SI")*0.5 -> 0 | BM99: =IF(BL99<0.6,"Demasiado Riesgo",IF(BL99<=5,"Riesgo Medio",IF(BL99<=11,"Riesgo Bajo","Cliente Blindado"))) -> Demasiado Riesgo | BP99: 0 | CL99: =COUNTIF(AT99:BH99,"*OK*") -> 0 | CN99: =COUNTIF(AT99:BH99,"*OP*") -> 2
A100: 21116 | B100: VOT030512SA3 | C100: =AD100 -> 472.75 | D100: =COUNTIF(AT100:BH100,"*OK*") -> 0 | E100: Dafne de la Rosa | F100: V O TECNOLOGIA LASER APLICADA A LA VISION | H100: =IF(LEN(TRIM($G100&""))=0, $C100, SUMIF($G$3:$G$561, TRIM($G100), $C$3:$C$561)) -> 472.75 | I100: SMB | L100: =HYPERLINK("https://crm.zoho.com/crm/org685875245/tab/Accounts/3525045000217274383","https://crm.zoho.com/crm/org685875245/tab/Accounts/3525045000217274383") -> https://crm.zoho.com/crm/org685875245/tab/Accounts/3525045000217274383 | M100: Mantener | O100: Alan | P100: 5555555555 | Q100: rhcalidad.grupovo@gmail.com | U100: - | V100: 434.35 | W100: 443.82 | X100: 407.29 | Y100: 404.23 | Z100: 439.1653 | AA100: 408.42 | AB100: 444.5515 | AC100: 499.3281 | AD100: 472.75 | AE100: 151 | AF100: 150 | AH100: Guanajuato | AI100: Guanajuato | AJ100: Salud | AK100: Empresa de tecnología médica especializada en cirugía y tratamientos con láser oftalmológico, con clínicas en Guanajuato. | AL100: Salud | BJ100: =COUNTIF(AT100:BI100,"*OP*") -> 0 | BL100: =(COUNTIF(AT100:AV100,"*OK*")*3) + (COUNTIF(AW100:AY100,"*OK*")*2) + COUNTIF(AZ100:BB100,"*OK*")+COUNTIF(BK100:BK100,"SI")*0.5 -> 0 | BM100: =IF(BL100<0.6,"Demasiado Riesgo",IF(BL100<=5,"Riesgo Medio",IF(BL100<=11,"Riesgo Bajo","Cliente Blindado"))) -> Demasiado Riesgo | BP100: 0 | CL100: =COUNTIF(AT100:BH100,"*OK*") -> 0 | CN100: =COUNTIF(AT100:BH100,"*OP*") -> 0
...

Sheet Hoja1
G2: CAFES DE ESPECIALIDAD DE CHIAPAS
G3: FORSAC MEXICO
G4: AGROFORESTAL DEL VALLE DE NEJAPA
G5: GRUPO CONVERSE DE MEXICO
G6: SISTEMAS INTEGRALES PARA EL TRANSPORTE
G7: CESEHSA PRODUCTS
G8: SOCIEDAD INDUSTRIAL EQUIPOS Y SERVICIOS
G9: AJEMEX
G10: IDEAL AUTOMOTIVE MEXICO
G11: QUIMICA BLANTEX
G12: TECNOLOGIA SINTEL
G13: NOMINATIVA TECHNOLOGIES
... G16: FRUEHAUF DE MEXICO

Sheet Semáforo
A1: CROSS-SELLING POR SEGMENTO (USD)
A2: Mes | B2: ENTERPRISE | C2: SMB | D2: Sin dato | E2: Total | G2: Q | H2: Total Q | K2: Q1 | L2: Cross | M2: Meta | N2: Churn promedio | O2: Semáforo
A3: Enero | B3: =SUMIFS('Ventas 2026'!$M:$M,'Ventas 2026'!$E:$E,"Cross selling",'Ventas 2026'!$P:$P,"ENTERPRISE",'Ventas 2026'!$C:$C,"Enero") -> 0 | C3: =SUMIFS('Ventas 2026'!$M:$M,'Ventas 2026'!$E:$E,"Cross selling",'Ventas 2026'!$P:$P,"SMB",'Ventas 2026'!$C:$C,"Enero") -> 0 | D3: =SUMIFS('Ventas 2026'!$M:$M,'Ventas 2026'!$E:$E,"Cross selling",'Ventas 2026'!$P:$P,"Sin dato",'Ventas 2026'!$C:$C,"Enero") -> 0 | E3: =B3+C3+D3 -> 0 | G3: Q1 | H3: =SUM(E3:E5) -> 0 | K3: Dafne | L3: =B37+B38+B39 -> 0 | M3: M1 | N3: =AVERAGE(G88:G90) -> 0.0099004552 | O3: Verde
A4: Febrero | B4: =SUMIFS('Ventas 2026'!$M:$M,'Ventas 2026'!$E:$E,"Cross selling",'Ventas 2026'!$P:$P,"ENTERPRISE",'Ventas 2026'!$C:$C,"Febrero") -> 0 | C4: =SUMIFS('Ventas 2026'!$M:$M,'Ventas 2026'!$E:$E,"Cross selling",'Ventas 2026'!$P:$P,"SMB",'Ventas 2026'!$C:$C,"Febrero") -> 0 | D4: =SUMIFS('Ventas 2026'!$M:$M,'Ventas 2026'!$E:$E,"Cross selling",'Ventas 2026'!$P:$P,"Sin dato",'Ventas 2026'!$C:$C,"Febrero") -> 0 | E4: =B4+C4+D4 -> 0 | G4: Q2 | H4: =SUM(E6:E8) -> 0 | K4: Raúl | L4: =D37+D38+D39 -> 0 | M4: M2 | N4: =AVERAGE(K88:K90) -> 0.0050548042 | O4: Verde
A5: Marzo | B5: =SUMIFS('Ventas 2026'!$M:$M,'Ventas 2026'!$E:$E,"Cross selling",'Ventas 2026'!$P:$P,"ENTERPRISE",'Ventas 2026'!$C:$C,"Marzo") -> 0 | C5: =SUMIFS('Ventas 2026'!$M:$M,'Ventas 2026'!$E:$E,"Cross selling",'Ventas 2026'!$P:$P,"SMB",'Ventas 2026'!$C:$C,"Marzo") -> 0 | D5: =SUMIFS('Ventas 2026'!$M:$M,'Ventas 2026'!$E:$E,"Cross selling",'Ventas 2026'!$P:$P,"Sin dato",'Ventas 2026'!$C:$C,"Marzo") -> 0 | E5: =B5+C5+D5 -> 0 | G5: Q3 | H5: =SUM(E9:E11) -> 0 | K5: Karla | L5: =SUM(C37:C39) -> 0 | M5: No llega | N5: =AVERAGE(I88:I90) -> 0.010611344 | O5: Café
A6: Abril | B6: =SUMIFS('Ventas 2026'!$M:$M,'Ventas 2026'!$E:$E,"Cross selling",'Ventas 2026'!$P:$P,"ENTERPRISE",'Ventas 2026'!$C:$C,"Abril") -> 0 | C6: =SUMIFS('Ventas 2026'!$M:$M,'Ventas 2026'!$E:$E,"Cross selling",'Ventas 2026'!$P:$P,"SMB",'Ventas 2026'!$C:$C,"Abril") -> 0 | D6: =SUMIFS('Ventas 2026'!$M:$M,'Ventas 2026'!$E:$E,"Cross selling",'Ventas 2026'!$P:$P,"Sin dato",'Ventas 2026'!$C:$C,"Abril") -> 0 | E6: =B6+C6+D6 -> 0 | G6: Q4 | H6: =SUM(E12:E14) -> 0
A7: Mayo | B7: =SUMIFS('Ventas 2026'!$M:$M,'Ventas 2026'!$E:$E,"Cross selling",'Ventas 2026'!$P:$P,"ENTERPRISE",'Ventas 2026'!$C:$C,"Mayo") -> 0 | C7: =SUMIFS('Ventas 2026'!$M:$M,'Ventas 2026'!$E:$E,"Cross selling",'Ventas 2026'!$P:$P,"SMB",'Ventas 2026'!$C:$C,"Mayo") -> 0 | D7: =SUMIFS('Ventas 2026'!$M:$M,'Ventas 2026'!$E:$E,"Cross selling",'Ventas 2026'!$P:$P,"Sin dato",'Ventas 2026'!$C:$C,"Mayo") -> 0 | E7: =B7+C7+D7 -> 0
A8: Junio | B8: =SUMIFS('Ventas 2026'!$M:$M,'Ventas 2026'!$E:$E,"Cross selling",'Ventas 2026'!$P:$P,"ENTERPRISE",'Ventas 2026'!$C:$C,"Junio") -> 0 | C8: =SUMIFS('Ventas 2026'!$M:$M,'Ventas 2026'!$E:$E,"Cross selling",'Ventas 2026'!$P:$P,"SMB",'Ventas 2026'!$C:$C,"Junio") -> 0 | D8: =SUMIFS('Ventas 2026'!$M:$M,'Ventas 2026'!$E:$E,"Cross selling",'Ventas 2026'!$P:$P,"Sin dato",'Ventas 2026'!$C:$C,"Junio") -> 0 | E8: =B8+C8+D8 -> 0 | L8: (Junio aun no se cierra)
A9: Julio | B9: =SUMIFS('Ventas 2026'!$M:$M,'Ventas 2026'!$E:$E,"Cross selling",'Ventas 2026'!$P:$P,"ENTERPRISE",'Ventas 2026'!$C:$C,"Julio") -> 0 | C9: =SUMIFS('Ventas 2026'!$M:$M,'Ventas 2026'!$E:$E,"Cross selling",'Ventas 2026'!$P:$P,"SMB",'Ventas 2026'!$C:$C,"Julio") -> 0 | D9: =SUMIFS('Ventas 2026'!$M:$M,'Ventas 2026'!$E:$E,"Cross selling",'Ventas 2026'!$P:$P,"Sin dato",'Ventas 2026'!$C:$C,"Julio") -> 0 | E9: =B9+C9+D9 -> 0 | K9: Q2 | L9: Cross | M9: Meta | N9: Churn promedio | O9: Semáforo
A10: Agosto | B10: =SUMIFS('Ventas 2026'!$M:$M,'Ventas 2026'!$E:$E,"Cross selling",'Ventas 2026'!$P:$P,"ENTERPRISE",'Ventas 2026'!$C:$C,"Agosto") -> 0 | C10: =SUMIFS('Ventas 2026'!$M:$M,'Ventas 2026'!$E:$E,"Cross selling",'Ventas 2026'!$P:$P,"SMB",'Ventas 2026'!$C:$C,"Agosto") -> 0 | D10: =SUMIFS('Ventas 2026'!$M:$M,'Ventas 2026'!$E:$E,"Cross selling",'Ventas 2026'!$P:$P,"Sin dato",'Ventas 2026'!$C:$C,"Agosto") -> 0 | E10: =B10+C10+D10 -> 0 | K10: Dafne | L10: =SUM(B40:B42) -> 0 | N10: =AVERAGE(G91:G93) -> 0.022912854
A11: Septiembre | B11: =SUMIFS('Ventas 2026'!$M:$M,'Ventas 2026'!$E:$E,"Cross selling",'Ventas 2026'!$P:$P,"ENTERPRISE",'Ventas 2026'!$C:$C,"Septiembre") -> 0 | C11: =SUMIFS('Ventas 2026'!$M:$M,'Ventas 2026'!$E:$E,"Cross selling",'Ventas 2026'!$P:$P,"SMB",'Ventas 2026'!$C:$C,"Septiembre") -> 0 | D11: =SUMIFS('Ventas 2026'!$M:$M,'Ventas 2026'!$E:$E,"Cross selling",'Ventas 2026'!$P:$P,"Sin dato",'Ventas 2026'!$C:$C,"Septiembre") -> 0 | E11: =B11+C11+D11 -> 0 | K11: Raúl | L11: =SUM(D40:D42) -> 0 | N11: =AVERAGE(I91:I93) -> 0.0079379989
A12: Octubre | B12: =SUMIFS('Ventas 2026'!$M:$M,'Ventas 2026'!$E:$E,"Cross selling",'Ventas 2026'!$P:$P,"ENTERPRISE",'Ventas 2026'!$C:$C,"Octubre") -> 0 | C12: =SUMIFS('Ventas 2026'!$M:$M,'Ventas 2026'!$E:$E,"Cross selling",'Ventas 2026'!$P:$P,"SMB",'Ventas 2026'!$C:$C,"Octubre") -> 0 | D12: =SUMIFS('Ventas 2026'!$M:$M,'Ventas 2026'!$E:$E,"Cross selling",'Ventas 2026'!$P:$P,"Sin dato",'Ventas 2026'!$C:$C,"Octubre") -> 0 | E12: =B12+C12+D12 -> 0 | K12: Karla | L12: =SUM(C40:C42) -> 0 | N12: =AVERAGE(H91:H93) -> 30767.68
A13: Noviembre | B13: =SUMIFS('Ventas 2026'!$M:$M,'Ventas 2026'!$E:$E,"Cross selling",'Ventas 2026'!$P:$P,"ENTERPRISE",'Ventas 2026'!$C:$C,"Noviembre") -> 0 | C13: =SUMIFS('Ventas 2026'!$M:$M,'Ventas 2026'!$E:$E,"Cross selling",'Ventas 2026'!$P:$P,"SMB",'Ventas 2026'!$C:$C,"Noviembre") -> 0 | D13: =SUMIFS('Ventas 2026'!$M:$M,'Ventas 2026'!$E:$E,"Cross selling",'Ventas 2026'!$P:$P,"Sin dato",'Ventas 2026'!$C:$C,"Noviembre") -> 0 | E13: =B13+C13+D13 -> 0
A14: Diciembre | B14: =SUMIFS('Ventas 2026'!$M:$M,'Ventas 2026'!$E:$E,"Cross selling",'Ventas 2026'!$P:$P,"ENTERPRISE",'Ventas 2026'!$C:$C,"Diciembre") -> 0 | C14: =SUMIFS('Ventas 2026'!$M:$M,'Ventas 2026'!$E:$E,"Cross selling",'Ventas 2026'!$P:$P,"SMB",'Ventas 2026'!$C:$C,"Diciembre") -> 0 | D14: =SUMIFS('Ventas 2026'!$M:$M,'Ventas 2026'!$E:$E,"Cross selling",'Ventas 2026'!$P:$P,"Sin dato",'Ventas 2026'!$C:$C,"Diciembre") -> 0 | E14: =B14+C14+D14 -> 0
A15: TOTAL | B15: =SUM(B3:B14) -> 0 | C15: =SUM(C3:C14) -> 0 | D15: =SUM(D3:D14) -> 0 | E15: =SUM(E3:E14) -> 0
A18: UP-SELLING POR SEGMENTO (USD)
A19: Mes | B19: ENTERPRISE | C19: SMB | D19: Sin dato | E19: Total | G19: Q | H19: Total Q
A20: Enero | B20: =SUMIFS('Ventas 2026'!$M:$M,'Ventas 2026'!$E:$E,"Up Selling",'Ventas 2026'!$P:$P,"ENTERPRISE",'Ventas 2026'!$C:$C,"Enero") -> 0 | C20: =SUMIFS('Ventas 2026'!$M:$M,'Ventas 2026'!$E:$E,"Up Selling",'Ventas 2026'!$P:$P,"SMB",'Ventas 2026'!$C:$C,"Enero") -> 0 | D20: =SUMIFS('Ventas 2026'!$M:$M,'Ventas 2026'!$E:$E,"Up Selling",'Ventas 2026'!$P:$P,"Sin dato",'Ventas 2026'!$C:$C,"Enero") -> 0 | E20: =B20+C20+D20 -> 0 | G20: Q1 | H20: =SUM(E20:E22) -> 0
A21: Febrero | B21: =SUMIFS('Ventas 2026'!$M:$M,'Ventas 2026'!$E:$E,"Up Selling",'Ventas 2026'!$P:$P,"ENTERPRISE",'Ventas 2026'!$C:$C,"Febrero") -> 0 | C21: =SUMIFS('Ventas 2026'!$M:$M,'Ventas 2026'!$E:$E,"Up Selling",'Ventas 2026'!$P:$P,"SMB",'Ventas 2026'!$C:$C,"Febrero") -> 0 | D21: =SUMIFS('Ventas 2026'!$M:$M,'Ventas 2026'!$E:$E,"Up Selling",'Ventas 2026'!$P:$P,"Sin dato",'Ventas 2026'!$C:$C,"Febrero") -> 0 | E21: =B21+C21+D21 -> 0 | G21: Q2 | H21: =SUM(E23:E25) -> 0
A22: Marzo | B22: =SUMIFS('Ventas 2026'!$M:$M,'Ventas 2026'!$E:$E,"Up Selling",'Ventas 2026'!$P:$P,"ENTERPRISE",'Ventas 2026'!$C:$C,"Marzo") -> 0 | C22: =SUMIFS('Ventas 2026'!$M:$M,'Ventas 2026'!$E:$E,"Up Selling",'Ventas 2026'!$P:$P,"SMB",'Ventas 2026'!$C:$C,"Marzo") -> 0 | D22: =SUMIFS('Ventas 2026'!$M:$M,'Ventas 2026'!$E:$E,"Up Selling",'Ventas 2026'!$P:$P,"Sin dato",'Ventas 2026'!$C:$C,"Marzo") -> 0 | E22: =B22+C22+D22 -> 0 | G22: Q3 | H22: =SUM(E26:E28) -> 0
A23: Abril | B23: =SUMIFS('Ventas 2026'!$M:$M,'Ventas 2026'!$E:$E,"Up Selling",'Ventas 2026'!$P:$P,"ENTERPRISE",'Ventas 2026'!$C:$C,"Abril") -> 0 | C23: =SUMIFS('Ventas 2026'!$M:$M,'Ventas 2026'!$E:$E,"Up Selling",'Ventas 2026'!$P:$P,"SMB",'Ventas 2026'!$C:$C,"Abril") -> 0 | D23: =SUMIFS('Ventas 2026'!$M:$M,'Ventas 2026'!$E:$E,"Up Selling",'Ventas 2026'!$P:$P,"Sin dato",'Ventas 2026'!$C:$C,"Abril") -> 0 | E23: =B23+C23+D23 -> 0 | G23: Q4 | H23: =SUM(E29:E31) -> 0
A24: Mayo | B24: =SUMIFS('Ventas 2026'!$M:$M,'Ventas 2026'!$E:$E,"Up Selling",'Ventas 2026'!$P:$P,"ENTERPRISE",'Ventas 2026'!$C:$C,"Mayo") -> 0 | C24: =SUMIFS('Ventas 2026'!$M:$M,'Ventas 2026'!$E:$E,"Up Selling",'Ventas 2026'!$P:$P,"SMB",'Ventas 2026'!$C:$C,"Mayo") -> 0 | D24: =SUMIFS('Ventas 2026'!$M:$M,'Ventas 2026'!$E:$E,"Up Selling",'Ventas 2026'!$P:$P,"Sin dato",'Ventas 2026'!$C:$C,"Mayo") -> 0 | E24: =B24+C24+D24 -> 0
A25: Junio | B25: =SUMIFS('Ventas 2026'!$M:$M,'Ventas 2026'!$E:$E,"Up Selling",'Ventas 2026'!$P:$P,"ENTERPRISE",'Ventas 2026'!$C:$C,"Junio") -> 0 | C25: =SUMIFS('Ventas 2026'!$M:$M,'Ventas 2026'!$E:$E,"Up Selling",'Ventas 2026'!$P:$P,"SMB",'Ventas 2026'!$C:$C,"Junio") -> 0 | D25: =SUMIFS('Ventas 2026'!$M:$M,'Ventas 2026'!$E:$E,"Up Selling",'Ventas 2026'!$P:$P,"Sin dato",'Ventas 2026'!$C:$C,"Junio") -> 0 | E25: =B25+C25+D25 -> 0
A26: Julio | B26: =SUMIFS('Ventas 2026'!$M:$M,'Ventas 2026'!$E:$E,"Up Selling",'Ventas 2026'!$P:$P,"ENTERPRISE",'Ventas 2026'!$C:$C,"Julio") -> 0 | C26: =SUMIFS('Ventas 2026'!$M:$M,'Ventas 2026'!$E:$E,"Up Selling",'Ventas 2026'!$P:$P,"SMB",'Ventas 2026'!$C:$C,"Julio") -> 0 | D26: =SUMIFS('Ventas 2026'!$M:$M,'Ventas 2026'!$E:$E,"Up Selling",'Ventas 2026'!$P:$P,"Sin dato",'Ventas 2026'!$C:$C,"Julio") -> 0 | E26: =B26+C26+D26 -> 0
A27: Agosto | B27: =SUMIFS('Ventas 2026'!$M:$M,'Ventas 2026'!$E:$E,"Up Selling",'Ventas 2026'!$P:$P,"ENTERPRISE",'Ventas 2026'!$C:$C,"Agosto") -> 0 | C27: =SUMIFS('Ventas 2026'!$M:$M,'Ventas 2026'!$E:$E,"Up Selling",'Ventas 2026'!$P:$P,"SMB",'Ventas 2026'!$C:$C,"Agosto") -> 0 | D27: =SUMIFS('Ventas 2026'!$M:$M,'Ventas 2026'!$E:$E,"Up Selling",'Ventas 2026'!$P:$P,"Sin dato",'Ventas 2026'!$C:$C,"Agosto") -> 0 | E27: =B27+C27+D27 -> 0
A28: Septiembre | B28: =SUMIFS('Ventas 2026'!$M:$M,'Ventas 2026'!$E:$E,"Up Selling",'Ventas 2026'!$P:$P,"ENTERPRISE",'Ventas 2026'!$C:$C,"Septiembre") -> 0 | C28: =SUMIFS('Ventas 2026'!$M:$M,'Ventas 2026'!$E:$E,"Up Selling",'Ventas 2026'!$P:$P,"SMB",'Ventas 2026'!$C:$C,"Septiembre") -> 0 | D28: =SUMIFS('Ventas 2026'!$M:$M,'Ventas 2026'!$E:$E,"Up Selling",'Ventas 2026'!$P:$P,"Sin dato",'Ventas 2026'!$C:$C,"Septiembre") -> 0 | E28: =B28+C28+D28 -> 0
A29: Octubre | B29: =SUMIFS('Ventas 2026'!$M:$M,'Ventas 2026'!$E:$E,"Up Selling",'Ventas 2026'!$P:$P,"ENTERPRISE",'Ventas 2026'!$C:$C,"Octubre") -> 0 | C29: =SUMIFS('Ventas 2026'!$M:$M,'Ventas 2026'!$E:$E,"Up Selling",'Ventas 2026'!$P:$P,"SMB",'Ventas 2026'!$C:$C,"Octubre") -> 0 | D29: =SUMIFS('Ventas 2026'!$M:$M,'Ventas 2026'!$E:$E,"Up Selling",'Ventas 2026'!$P:$P,"Sin dato",'Ventas 2026'!$C:$C,"Octubre") -> 0 | E29: =B29+C29+D29 -> 0
A30: Noviembre | B30: =SUMIFS('Ventas 2026'!$M:$M,'Ventas 2026'!$E:$E,"Up Selling",'Ventas 2026'!$P:$P,"ENTERPRISE",'Ventas 2026'!$C:$C,"Noviembre") -> 0 | C30: =SUMIFS('Ventas 2026'!$M:$M,'Ventas 2026'!$E:$E,"Up Selling",'Ventas 2026'!$P:$P,"SMB",'Ventas 2026'!$C:$C,"Noviembre") -> 0 | D30: =SUMIFS('Ventas 2026'!$M:$M,'Ventas 2026'!$E:$E,"Up Selling",'Ventas 2026'!$P:$P,"Sin dato",'Ventas 2026'!$C:$C,"Noviembre") -> 0 | E30: =B30+C30+D30 -> 0
A31: Diciembre | B31: =SUMIFS('Ventas 2026'!$M:$M,'Ventas 2026'!$E:$E,"Up Selling",'Ventas 2026'!$P:$P,"ENTERPRISE",'Ventas 2026'!$C:$C,"Diciembre") -> 0 | C31: =SUMIFS('Ventas 2026'!$M:$M,'Ventas 2026'!$E:$E,"Up Selling",'Ventas 2026'!$P:$P,"SMB",'Ventas 2026'!$C:$C,"Diciembre") -> 0 | D31: =SUMIFS('Ventas 2026'!$M:$M,'Ventas 2026'!$E:$E,"Up Selling",'Ventas 2026'!$P:$P,"Sin dato",'Ventas 2026'!$C:$C,"Diciembre") -> 0 | E31: =B31+C31+D31 -> 0
A32: TOTAL | B32: =SUM(B20:B31) -> 0 | C32: =SUM(C20:C31) -> 0 | D32: =SUM(D20:D31) -> 0 | E32: =SUM(E20:E31) -> 0
G36: Q | H36: Total Q
G37: Q1 | H37: =SUM(E37:E39) -> 0
G38: Q2 | H38: =SUM(E40:E42) -> 0
G39: Q3 | H39: =SUM(E43:E45) -> 0
G40: Q4 | H40: =SUM(E46:E48) -> 0
G53: Q | H53: Total Q
G54: Q1 | H54: =SUM(E54:E56) -> 0
G55: Q2 | H55: =SUM(E57:E59) -> 0
G56: Q3 | H56: =SUM(E60:E62) -> 0
G57: Q4 | H57: =SUM(E63:E65) -> 0
A69: FUGA POR SEGMENTO (USD)
A70: Mes | B70: ENTERPRISE | C70: SMB | D70: Sin dato | E70: Total | F70: Total MRR
A71: Enero | B71: =SUMIFS('Detalle Fuga 2026'!$I:$I,'Detalle Fuga 2026'!$D:$D,"ENTERPRISE",'Detalle Fuga 2026'!$K:$K,"Enero") -> 5450.65 | C71: =SUMIFS('Detalle Fuga 2026'!$I:$I,'Detalle Fuga 2026'!$D:$D,"SMB",'Detalle Fuga 2026'!$K:$K,"Enero") -> 1202.93 | E71: =B71+C71+D71 -> 6653.58 | F71: 153375 | G71: Q1 | H71: =SUM(E71:E73) -> 9859.2281
A72: Febrero | B72: =SUMIFS('Detalle Fuga 2026'!$I:$I,'Detalle Fuga 2026'!$D:$D,"ENTERPRISE",'Detalle Fuga 2026'!$K:$K,"Febrero") -> 675 | C72: =SUMIFS('Detalle Fuga 2026'!$I:$I,'Detalle Fuga 2026'!$D:$D,"SMB",'Detalle Fuga 2026'!$K:$K,"Febrero") -> 1175 | E72: =B72+C72+D72 -> 1850 | F72: 154455 | G72: Q2 | H72: =SUM(E74:E76) -> 3568
A73: Marzo | B73: =SUMIFS('Detalle Fuga 2026'!$I:$I,'Detalle Fuga 2026'!$D:$D,"ENTERPRISE",'Detalle Fuga 2026'!$K:$K,"Marzo") -> 0 | C73: =SUMIFS('Detalle Fuga 2026'!$I:$I,'Detalle Fuga 2026'!$D:$D,"SMB",'Detalle Fuga 2026'!$K:$K,"Marzo") -> 1355.6481 | E73: =B73+C73+D73 -> 1355.6481 | F73: 162290 | G73: Q3 | H73: =SUM(E77:E79) -> 0
A74: Abril | B74: =SUMIFS('Detalle Fuga 2026'!$I:$I,'Detalle Fuga 2026'!$D:$D,"ENTERPRISE",'Detalle Fuga 2026'!$K:$K,"Abril") -> 511 | C74: =SUMIFS('Detalle Fuga 2026'!$I:$I,'Detalle Fuga 2026'!$D:$D,"SMB",'Detalle Fuga 2026'!$K:$K,"Abril") -> 1473 | E74: =B74+C74+D74 -> 1984 | F74: 162968 | G74: Q4 | H74: =SUM(E80:E82) -> 0
A75: Mayo | B75: =SUMIFS('Detalle Fuga 2026'!$I:$I,'Detalle Fuga 2026'!$D:$D,"ENTERPRISE",'Detalle Fuga 2026'!$K:$K,"Mayo") -> 1282 | C75: =SUMIFS('Detalle Fuga 2026'!$I:$I,'Detalle Fuga 2026'!$D:$D,"SMB",'Detalle Fuga 2026'!$K:$K,"Mayo") -> 302 | E75: =B75+C75+D75 -> 1584 | F75: 170313
A76: Junio | B76: =SUMIFS('Detalle Fuga 2026'!$I:$I,'Detalle Fuga 2026'!$D:$D,"ENTERPRISE",'Detalle Fuga 2026'!$K:$K,"Junio") -> 0 | C76: =SUMIFS('Detalle Fuga 2026'!$I:$I,'Detalle Fuga 2026'!$D:$D,"SMB",'Detalle Fuga 2026'!$K:$K,"Junio") -> 0 | E76: =B76+C76+D76 -> 0
A77: Julio | B77: =SUMIFS('Detalle Fuga 2026'!$I:$I,'Detalle Fuga 2026'!$D:$D,"ENTERPRISE",'Detalle Fuga 2026'!$K:$K,"Julio") -> 0 | C77: =SUMIFS('Detalle Fuga 2026'!$I:$I,'Detalle Fuga 2026'!$D:$D,"SMB",'Detalle Fuga 2026'!$K:$K,"Julio") -> 0 | E77: =B77+C77+D77 -> 0
A78: Agosto | B78: =SUMIFS('Detalle Fuga 2026'!$I:$I,'Detalle Fuga 2026'!$D:$D,"ENTERPRISE",'Detalle Fuga 2026'!$K:$K,"Agosto") -> 0 | C78: =SUMIFS('Detalle Fuga 2026'!$I:$I,'Detalle Fuga 2026'!$D:$D,"SMB",'Detalle Fuga 2026'!$K:$K,"Agosto") -> 0 | E78: =B78+C78+D78 -> 0
A79: Septiembre | B79: =SUMIFS('Detalle Fuga 2026'!$I:$I,'Detalle Fuga 2026'!$D:$D,"ENTERPRISE",'Detalle Fuga 2026'!$K:$K,"Septiembre") -> 0 | C79: =SUMIFS('Detalle Fuga 2026'!$I:$I,'Detalle Fuga 2026'!$D:$D,"SMB",'Detalle Fuga 2026'!$K:$K,"Septiembre") -> 0 | E79: =B79+C79+D79 -> 0
A80: Octubre | B80: =SUMIFS('Detalle Fuga 2026'!$I:$I,'Detalle Fuga 2026'!$D:$D,"ENTERPRISE",'Detalle Fuga 2026'!$K:$K,"Octubre") -> 0 | C80: =SUMIFS('Detalle Fuga 2026'!$I:$I,'Detalle Fuga 2026'!$D:$D,"SMB",'Detalle Fuga 2026'!$K:$K,"Octubre") -> 0 | E80: =B80+C80+D80 -> 0
A81: Noviembre | B81: =SUMIFS('Detalle Fuga 2026'!$I:$I,'Detalle Fuga 2026'!$D:$D,"ENTERPRISE",'Detalle Fuga 2026'!$K:$K,"Noviembre") -> 0 | C81: =SUMIFS('Detalle Fuga 2026'!$I:$I,'Detalle Fuga 2026'!$D:$D,"SMB",'Detalle Fuga 2026'!$K:$K,"Noviembre") -> 0 | E81: =B81+C81+D81 -> 0
A82: Diciembre | B82: =SUMIFS('Detalle Fuga 2026'!$I:$I,'Detalle Fuga 2026'!$D:$D,"ENTERPRISE",'Detalle Fuga 2026'!$K:$K,"Diciembre") -> 0 | C82: =SUMIFS('Detalle Fuga 2026'!$I:$I,'Detalle Fuga 2026'!$D:$D,"SMB",'Detalle Fuga 2026'!$K:$K,"Diciembre") -> 0 | E82: =B82+C82+D82 -> 0
A83: Total | B83: =SUM(B71:B82) -> 7918.65 | C83: =SUM(C71:C82) -> 5508.5781 | D83: =SUM(D71:D82) -> 0 | E83: =SUM(E71:E82) -> 13427.228
A86: FUGA POR KAM (USD)
A87: Mes | B87: Dafne de la Rosa | C87: Karla Patiño | D87: Raúl Campos | E87: Total | F87: Total MRR | G87: Dafne de la Rosa | H87: Total MRR Karla | I87: Karla Patiño | J87: Total MRR Raúl | K87: Raúl Campos
A88: Enero | B88: 788.66 | C88: =SUMIFS('Detalle Fuga 2026'!$I:$I,'Detalle Fuga 2026'!$C:$C,"Karla Patiño",'Detalle Fuga 2026'!$K:$K,"Enero") -> 274.07 | D88: 0 | E88: =B88+C88+D88 -> 1062.73 | F88: =SUMIFS('MARE MX'!$V$2:$V$560,'MARE MX'!$E$2:$E$560, "Dafne de la Rosa") -> 42610.28 | G88: =B88/$F$88 -> 0.018508679 | H88: =SUMIFS('MARE MX'!$V$2:$V$560,'MARE MX'!$E$2:$E$560, "Karla Patiño") -> 24670.39 | I88: =C88/$F$88 -> 0.0064320159 | J88: =SUMIFS('MARE MX'!$V$2:$V$560,'MARE MX'!$E$2:$E$560, "Raúl Campos") -> 74210.71 | K88: =D88/$F$88 -> 0 | N88: Q1 | O88: =SUM(E88:E90) -> 3411.6618
A89: Febrero | B89: =SUMIFS('Detalle Fuga 2026'!$I:$I,'Detalle Fuga 2026'!$C:$C,"Dafne de la Rosa",'Detalle Fuga 2026'!$K:$K,"Febrero") -> 342 | C89: =SUMIFS('Detalle Fuga 2026'!$I:$I,'Detalle Fuga 2026'!$C:$C,"Karla Patiño",'Detalle Fuga 2026'!$K:$K,"Febrero") -> 737 | D89: =SUMIFS('Detalle Fuga 2026'!$I:$I,'Detalle Fuga 2026'!$C:$C,"Raúl Campos",'Detalle Fuga 2026'!$K:$K,"Febrero") -> 675 | E89: =B89+C89+D89 -> 1754 | F89: =SUMIFS('MARE MX'!$W$2:$W$560,'MARE MX'!$E$2:$E$560, "Dafne de la Rosa") -> 44512.11 | G89: =B89/$F89 -> 0.0076833024 | H89: =SUMIFS('MARE MX'!$W$2:$W$560,'MARE MX'!$E$2:$E$560, "Karla Patiño") -> 25859.69 | I89: =C89/$F89 -> 0.016557292 | J89: =SUMIFS('MARE MX'!$W$2:$W$560,'MARE MX'!$E$2:$E$560, "Raúl Campos") -> 73236.99 | K89: =D89/$F89 -> 0.015164413 | N89: Q2 | O89: =SUM(E91:E93) -> 3101
A90: Marzo | B90: =SUMIFS('Detalle Fuga 2026'!$I:$I,'Detalle Fuga 2026'!$C:$C,"Dafne de la Rosa",'Detalle Fuga 2026'!$K:$K,"Marzo") -> 169 | C90: =SUMIFS('Detalle Fuga 2026'!$I:$I,'Detalle Fuga 2026'!$C:$C,"Karla Patiño",'Detalle Fuga 2026'!$K:$K,"Marzo") -> 425.9318 | D90: =SUMIFS('Detalle Fuga 2026'!$I:$I,'Detalle Fuga 2026'!$C:$C,"Raúl Campos",'Detalle Fuga 2026'!$K:$K,"Marzo") -> 0 | E90: =B90+C90+D90 -> 594.9318 | F90: =SUMIFS('MARE MX'!$X$2:$X$560,'MARE MX'!$E$2:$E$560, "Dafne de la Rosa") -> 48156.6 | G90: =B90/$F90 -> 0.003509384 | H90: =SUMIFS('MARE MX'!$X$2:$X$560,'MARE MX'!$E$2:$E$560, "Karla Patiño") -> 27652.58 | I90: =C90/$F90 -> 0.0088447233 | J90: =SUMIFS('MARE MX'!$X$2:$X$560,'MARE MX'!$E$2:$E$560, "Raúl Campos") -> 75768.56 | K90: =D90/$F90 -> 0 | N90: Q3 | O90: =SUM(E94:E96) -> 3208.953
A91: Abril | B91: =SUMIFS('Detalle Fuga 2026'!$I:$I,'Detalle Fuga 2026'!$C:$C,"Dafne de la Rosa",'Detalle Fuga 2026'!$K:$K,"Abril") -> 1517 | C91: =SUMIFS('Detalle Fuga 2026'!$I:$I,'Detalle Fuga 2026'!$C:$C,"Karla Patiño",'Detalle Fuga 2026'!$K:$K,"Abril") -> 0 | D91: =SUMIFS('Detalle Fuga 2026'!$I:$I,'Detalle Fuga 2026'!$C:$C,"Raúl Campos",'Detalle Fuga 2026'!$K:$K,"Abril") -> 0 | E91: =B91+C91+D91 -> 1517 | F91: =SUMIFS('MARE MX'!$Y$2:$Y$560,'MARE MX'!$E$2:$E$560, "Dafne de la Rosa") -> 48881.99 | G91: =B91/$F91 -> 0.031033925 | H91: =SUMIFS('MARE MX'!$Y$2:$Y$560,'MARE MX'!$E$2:$E$560, "Karla Patiño") -> 29413.369 | I91: =C91/$F91 -> 0 | J91: =SUMIFS('MARE MX'!$Y$2:$Y$560,'MARE MX'!$E$2:$E$560, "Raúl Campos") -> 78845.52 | K91: =D91/$F91 -> 0 | N91: Q4 | O91: =SUM(E97:E99) -> 214.6715
A92: Mayo | B92: =SUMIFS('Detalle Fuga 2026'!$I:$I,'Detalle Fuga 2026'!$C:$C,"Dafne de la Rosa",'Detalle Fuga 2026'!$K:$K,"Mayo") -> 764 | C92: =SUMIFS('Detalle Fuga 2026'!$I:$I,'Detalle Fuga 2026'!$C:$C,"Karla Patiño",'Detalle Fuga 2026'!$K:$K,"Mayo") -> 820 | D92: =SUMIFS('Detalle Fuga 2026'!$I:$I,'Detalle Fuga 2026'!$C:$C,"Raúl Campos",'Detalle Fuga 2026'!$K:$K,"Mayo") -> 0 | E92: =B92+C92+D92 -> 1584 | F92: =SUMIFS('MARE MX'!$Z$2:$Z$560,'MARE MX'!$E$2:$E$560, "Dafne de la Rosa") -> 51650.297 | G92: =B92/$F92 -> 0.014791783 | H92: =SUMIFS('MARE MX'!$Z$2:$Z$560,'MARE MX'!$E$2:$E$560, "Karla Patiño") -> 32121.99 | I92: =C92/$F92 -> 0.015875998 | J92: =SUMIFS('MARE MX'!$Z$2:$Z$560,'MARE MX'!$E$2:$E$560, "Raúl Campos") -> 77200.104 | K92: =D92/$F92 -> 0
A93: Junio | B93: =SUMIFS('Detalle Fuga 2026'!$I:$I,'Detalle Fuga 2026'!$C:$C,"Dafne de la Rosa",'Detalle Fuga 2026'!$K:$K,"Junio") -> 0 | C93: =SUMIFS('Detalle Fuga 2026'!$I:$I,'Detalle Fuga 2026'!$C:$C,"Karla Patiño",'Detalle Fuga 2026'!$K:$K,"Junio") -> 0 | D93: =SUMIFS('Detalle Fuga 2026'!$I:$I,'Detalle Fuga 2026'!$C:$C,"Raúl Campos",'Detalle Fuga 2026'!$K:$K,"Junio") -> 0 | E93: =B93+C93+D93 -> 0
A94: Julio | B94: =SUMIFS('Detalle Fuga 2026'!$I:$I,'Detalle Fuga 2026'!$C:$C,"Dafne de la Rosa",'Detalle Fuga 2026'!$K:$K,"Julio") -> 0 | C94: =SUMIFS('Detalle Fuga 2026'!$I:$I,'Detalle Fuga 2026'!$C:$C,"Karla Patiño",'Detalle Fuga 2026'!$K:$K,"Julio") -> 182 | D94: =SUMIFS('Detalle Fuga 2026'!$I:$I,'Detalle Fuga 2026'!$C:$C,"Raúl Campos",'Detalle Fuga 2026'!$K:$K,"Julio") -> 0 | E94: =B94+C94+D94 -> 182
A95: Agosto | B95: =SUMIFS('Detalle Fuga 2026'!$I:$I,'Detalle Fuga 2026'!$C:$C,"Dafne de la Rosa",'Detalle Fuga 2026'!$K:$K,"Agosto") -> 2.3901 | C95: =SUMIFS('Detalle Fuga 2026'!$I:$I,'Detalle Fuga 2026'!$C:$C,"Karla Patiño",'Detalle Fuga 2026'!$K:$K,"Agosto") -> 786.4687 | D95: =SUMIFS('Detalle Fuga 2026'!$I:$I,'Detalle Fuga 2026'!$C:$C,"Raúl Campos",'Detalle Fuga 2026'!$K:$K,"Agosto") -> 797.9741 | E95: =B95+C95+D95 -> 1586.8329
A96: Septiembre | B96: =SUMIFS('Detalle Fuga 2026'!$I:$I,'Detalle Fuga 2026'!$C:$C,"Dafne de la Rosa",'Detalle Fuga 2026'!$K:$K,"Septiembre") -> 1273.1348 | C96: =SUMIFS('Detalle Fuga 2026'!$I:$I,'Detalle Fuga 2026'!$C:$C,"Karla Patiño",'Detalle Fuga 2026'!$K:$K,"Septiembre") -> 166.9853 | D96: =SUMIFS('Detalle Fuga 2026'!$I:$I,'Detalle Fuga 2026'!$C:$C,"Raúl Campos",'Detalle Fuga 2026'!$K:$K,"Septiembre") -> 0 | E96: =B96+C96+D96 -> 1440.1201
A97: Octubre | B97: =SUMIFS('Detalle Fuga 2026'!$I:$I,'Detalle Fuga 2026'!$C:$C,"Dafne de la Rosa",'Detalle Fuga 2026'!$K:$K,"Octubre") -> 0 | C97: =SUMIFS('Detalle Fuga 2026'!$I:$I,'Detalle Fuga 2026'!$C:$C,"Karla Patiño",'Detalle Fuga 2026'!$K:$K,"Octubre") -> 0 | D97: =SUMIFS('Detalle Fuga 2026'!$I:$I,'Detalle Fuga 2026'!$C:$C,"Raúl Campos",'Detalle Fuga 2026'!$K:$K,"Octubre") -> 0 | E97: =B97+C97+D97 -> 0
A98: Noviembre | B98: =SUMIFS('Detalle Fuga 2026'!$I:$I,'Detalle Fuga 2026'!$C:$C,"Dafne de la Rosa",'Detalle Fuga 2026'!$K:$K,"Noviembre") -> 0 | C98: =SUMIFS('Detalle Fuga 2026'!$I:$I,'Detalle Fuga 2026'!$C:$C,"Karla Patiño",'Detalle Fuga 2026'!$K:$K,"Noviembre") -> 214.6715 | D98: =SUMIFS('Detalle Fuga 2026'!$I:$I,'Detalle Fuga 2026'!$C:$C,"Raúl Campos",'Detalle Fuga 2026'!$K:$K,"Noviembre") -> 0 | E98: =B98+C98+D98 -> 214.6715
A99: Diciembre | B99: =SUMIFS('Detalle Fuga 2026'!$I:$I,'Detalle Fuga 2026'!$C:$C,"Dafne de la Rosa",'Detalle Fuga 2026'!$K:$K,"Diciembre") -> 0 | C99: =SUMIFS('Detalle Fuga 2026'!$I:$I,'Detalle Fuga 2026'!$C:$C,"Karla Patiño",'Detalle Fuga 2026'!$K:$K,"Diciembre") -> 0 | D99: =SUMIFS('Detalle Fuga 2026'!$I:$I,'Detalle Fuga 2026'!$C:$C,"Raúl Campos",'Detalle Fuga 2026'!$K:$K,"Diciembre") -> 0 | E99: =B99+C99+D99 -> 0
A100: Total | B100: =SUM(B88:B99) -> 4856.1849 | C100: =SUM(C88:C99) -> 3607.1273 | D100: =SUM(D88:D99) -> 1472.9741 | E100: =SUM(E88:E99) -> 9936.2863

Sheet Resumen MARE
A2: VENTA | B2: TOTAL | C2: Enero | D2: Febrero | E2: Marzo | F2: Q1 | G2: Abril | H2: Mayo | I2: Junio | J2: Q2 | K2: Julio | L2: Agosto | M2: Septiembre | N2: Q3 | O2: Octubre | P2: Noviembre | Q2: Diciembre | R2: Q4
A3: Up Selling | B3: =SUM(F3,J3,N3,R3) -> 0 | C3: =SUMIFS('Ventas 2026'!$M:$M,'Ventas 2026'!$C:$C,C2,'Ventas 2026'!$E:$E,$A$3) -> 0 | D3: =SUMIFS('Ventas 2026'!$M:$M,'Ventas 2026'!$C:$C,D2,'Ventas 2026'!$E:$E,$A$3) -> 0 | E3: =SUMIFS('Ventas 2026'!$M:$M,'Ventas 2026'!$C:$C,E2,'Ventas 2026'!$E:$E,$A$3) -> 0 | F3: =SUM(C3:E3) -> 0 | G3: =SUMIFS('Ventas 2026'!$M:$M,'Ventas 2026'!$C:$C,G2,'Ventas 2026'!$E:$E,$A$3) -> 0 | H3: =SUMIFS('Ventas 2026'!$M:$M,'Ventas 2026'!$C:$C,H2,'Ventas 2026'!$E:$E,$A$3) -> 0 | I3: =SUMIFS('Ventas 2026'!$M:$M,'Ventas 2026'!$C:$C,I2,'Ventas 2026'!$E:$E,$A$3) -> 0 | J3: =SUM(G3:I3) -> 0 | K3: =SUMIFS('Ventas 2026'!$M:$M,'Ventas 2026'!$C:$C,K2,'Ventas 2026'!$E:$E,$A$3) -> 0 | L3: =SUMIFS('Ventas 2026'!$M:$M,'Ventas 2026'!$C:$C,L2,'Ventas 2026'!$E:$E,$A$3) -> 0 | M3: =SUMIFS('Ventas 2026'!$M:$M,'Ventas 2026'!$C:$C,M2,'Ventas 2026'!$E:$E,$A$3) -> 0 | N3: =SUM(K3:M3) -> 0 | O3: =SUMIFS('Ventas 2026'!$M:$M,'Ventas 2026'!$C:$C,O2,'Ventas 2026'!$E:$E,$A$3) -> 0 | P3: =SUMIFS('Ventas 2026'!$M:$M,'Ventas 2026'!$C:$C,P2,'Ventas 2026'!$E:$E,$A$3) -> 0 | Q3: =SUMIFS('Ventas 2026'!$M:$M,'Ventas 2026'!$C:$C,Q2,'Ventas 2026'!$E:$E,$A$3) -> 0 | R3: =SUM(O3:Q3) -> 0
A4: Cross selling | B4: =SUM(F4,J4,N4,R4) -> 0 | C4: =SUMIFS('Ventas 2026'!$M:$M,'Ventas 2026'!$C:$C,C2,'Ventas 2026'!$E:$E,$A$4) -> 0 | D4: =SUMIFS('Ventas 2026'!$M:$M,'Ventas 2026'!$C:$C,D2,'Ventas 2026'!$E:$E,$A$4) -> 0 | E4: =SUMIFS('Ventas 2026'!$M:$M,'Ventas 2026'!$C:$C,E2,'Ventas 2026'!$E:$E,$A$4) -> 0 | F4: =SUM(C4:E4) -> 0 | G4: =SUMIFS('Ventas 2026'!$M:$M,'Ventas 2026'!$C:$C,G2,'Ventas 2026'!$E:$E,$A$4) -> 0 | H4: =SUMIFS('Ventas 2026'!$M:$M,'Ventas 2026'!$C:$C,H2,'Ventas 2026'!$E:$E,$A$4) -> 0 | I4: =SUMIFS('Ventas 2026'!$M:$M,'Ventas 2026'!$C:$C,I2,'Ventas 2026'!$E:$E,$A$4) -> 0 | J4: =SUM(G4:I4) -> 0 | K4: =SUMIFS('Ventas 2026'!$M:$M,'Ventas 2026'!$C:$C,K2,'Ventas 2026'!$E:$E,$A$4) -> 0 | L4: =SUMIFS('Ventas 2026'!$M:$M,'Ventas 2026'!$C:$C,L2,'Ventas 2026'!$E:$E,$A$4) -> 0 | M4: =SUMIFS('Ventas 2026'!$M:$M,'Ventas 2026'!$C:$C,M2,'Ventas 2026'!$E:$E,$A$4) -> 0 | N4: =SUM(K4:M4) -> 0 | O4: =SUMIFS('Ventas 2026'!$M:$M,'Ventas 2026'!$C:$C,O2,'Ventas 2026'!$E:$E,$A$4) -> 0 | P4: =SUMIFS('Ventas 2026'!$M:$M,'Ventas 2026'!$C:$C,P2,'Ventas 2026'!$E:$E,$A$4) -> 0 | Q4: =SUMIFS('Ventas 2026'!$M:$M,'Ventas 2026'!$C:$C,Q2,'Ventas 2026'!$E:$E,$A$4) -> 0 | R4: =SUM(O4:Q4) -> 0
A5: Total general | B5: =SUM(B3:B4) -> 0 | C5: =SUM(C3:C4) -> 0 | D5: =SUM(D3:D4) -> 0 | E5: =SUM(E3:E4) -> 0 | F5: =SUM(F3:F4) -> 0 | G5: =SUM(G3:G4) -> 0 | H5: =SUM(H3:H4) -> 0 | I5: =SUM(I3:I4) -> 0 | ... R5: =SUM(R3:R4) -> 0
A8: FUGA | B8: TOTAL | C8: Enero | D8: Febrero | E8: Marzo | F8: Q1 | G8: Abril | H8: Mayo | I8: Junio | J8: Q2 | K8: Julio | L8: Agosto | M8: Septiembre | N8: Q3 | O8: Octubre | P8: Noviembre | Q8: Diciembre | R8: Q4
A9: Facturación | C9: 153375 | D9: 154455 | E9: 162290 | F9: =SUM(C9:E9) -> 470120 | G9: 162968 | H9: 170313 | I9: 193090 | J9: =SUM(G9:I9) -> 526371 | K9: 188749 | L9: 193859 | M9: 196292 | N9: =SUM(K9:M9) -> 578900
A10: Baja | B10: =SUM(F10,J10,N10,R10) -> 18266.349 | C10: =SUMIFS('Detalle Fuga 2026'!$I:$I,'Detalle Fuga 2026'!$A:$A,"Baja",'Detalle Fuga 2026'!$K:$K,C8) -> 1451.92 | D10: =SUMIFS('Detalle Fuga 2026'!$I:$I,'Detalle Fuga 2026'!$A:$A,"Baja",'Detalle Fuga 2026'!$K:$K,D8) -> 1850 | E10: =SUMIFS('Detalle Fuga 2026'!$I:$I,'Detalle Fuga 2026'!$A:$A,"Baja",'Detalle Fuga 2026'!$K:$K,E8) -> 1355.6481 | F10: =SUM(C10:E10) -> 4657.5681 | G10: =SUMIFS('Detalle Fuga 2026'!$I:$I,'Detalle Fuga 2026'!$A:$A,"Baja",'Detalle Fuga 2026'!$K:$K,G8) -> 761 | H10: =SUMIFS('Detalle Fuga 2026'!$I:$I,'Detalle Fuga 2026'!$A:$A,"Baja",'Detalle Fuga 2026'!$K:$K,H8) -> 782 | I10: =SUMIFS('Detalle Fuga 2026'!$I:$I,'Detalle Fuga 2026'!$A:$A,"Baja",'Detalle Fuga 2026'!$K:$K,I8) -> 953 | J10: =SUM(G10:I10) -> 2496 | K10: =SUMIFS('Detalle Fuga 2026'!$I:$I,'Detalle Fuga 2026'!$A:$A,"Baja",'Detalle Fuga 2026'!$K:$K,K8) -> 5105.88 | L10: =SUMIFS('Detalle Fuga 2026'!$I:$I,'Detalle Fuga 2026'!$A:$A,"Baja",'Detalle Fuga 2026'!$K:$K,L8) -> 4216.3886 | M10: =SUMIFS('Detalle Fuga 2026'!$I:$I,'Detalle Fuga 2026'!$A:$A,"Baja",'Detalle Fuga 2026'!$K:$K,M8) -> 1375.7598 | N10: =SUM(K10:M10) -> 10698.028 | O10: =SUMIFS('Detalle Fuga 2026'!$I:$I,'Detalle Fuga 2026'!$A:$A,"Baja",'Detalle Fuga 2026'!$K:$K,O8) -> 200.0813 | P10: =SUMIFS('Detalle Fuga 2026'!$I:$I,'Detalle Fuga 2026'!$A:$A,"Baja",'Detalle Fuga 2026'!$K:$K,P8) -> 214.6715 | Q10: =SUMIFS('Detalle Fuga 2026'!$I:$I,'Detalle Fuga 2026'!$A:$A,"Baja",'Detalle Fuga 2026'!$K:$K,Q8) -> 0 | R10: =SUM(O10:Q10) -> 414.7528
A11: Disminución | B11: =SUM(F11,J11,N11,R11) -> 9045.0924 | C11: =SUMIFS('Detalle Fuga 2026'!$I:$I,'Detalle Fuga 2026'!$A:$A,"Disminución",'Detalle Fuga 2026'!$K:$K,C8) -> 5201.66 | D11: =SUMIFS('Detalle Fuga 2026'!$I:$I,'Detalle Fuga 2026'!$A:$A,"Disminución",'Detalle Fuga 2026'!$K:$K,D8) -> 0 | E11: =SUMIFS('Detalle Fuga 2026'!$I:$I,'Detalle Fuga 2026'!$A:$A,"Disminución",'Detalle Fuga 2026'!$K:$K,E8) -> 0 | F11: =SUM(C11:E11) -> 5201.66 | G11: =SUMIFS('Detalle Fuga 2026'!$I:$I,'Detalle Fuga 2026'!$A:$A,"Disminución",'Detalle Fuga 2026'!$K:$K,G8) -> 1156 | H11: =SUMIFS('Detalle Fuga 2026'!$I:$I,'Detalle Fuga 2026'!$A:$A,"Disminución",'Detalle Fuga 2026'!$K:$K,H8) -> 587 | I11: =SUMIFS('Detalle Fuga 2026'!$I:$I,'Detalle Fuga 2026'!$A:$A,"Disminución",'Detalle Fuga 2026'!$K:$K,I8) -> 366 | J11: =SUM(G11:I11) -> 2109 | K11: =SUMIFS('Detalle Fuga 2026'!$I:$I,'Detalle Fuga 2026'!$A:$A,"Disminución",'Detalle Fuga 2026'!$K:$K,K8) -> 725 | L11: =SUMIFS('Detalle Fuga 2026'!$I:$I,'Detalle Fuga 2026'!$A:$A,"Disminución",'Detalle Fuga 2026'!$K:$K,L8) -> 797.9741 | M11: =SUMIFS('Detalle Fuga 2026'!$I:$I,'Detalle Fuga 2026'!$A:$A,"Disminución",'Detalle Fuga 2026'!$K:$K,M8) -> 211.4583 | N11: =SUM(K11:M11) -> 1734.4324 | O11: =SUMIFS('Detalle Fuga 2026'!$I:$I,'Detalle Fuga 2026'!$A:$A,"Disminución",'Detalle Fuga 2026'!$K:$K,O8) -> 0 | P11: =SUMIFS('Detalle Fuga 2026'!$I:$I,'Detalle Fuga 2026'!$A:$A,"Disminución",'Detalle Fuga 2026'!$K:$K,P8) -> 0 | Q11: =SUMIFS('Detalle Fuga 2026'!$I:$I,'Detalle Fuga 2026'!$A:$A,"Disminución",'Detalle Fuga 2026'!$K:$K,Q8) -> 0 | R11: =SUM(O11:Q11) -> 0
A12: % Churn | C12: =C10/C9 -> 0.0094664711 | D12: =D10/D9 -> 0.011977599 | E12: =E10/E9 -> 0.0083532448 | F12: =F10/F9 -> 0.0099071899 | G12: =G10/G9 -> 0.0046696284 | H12: =H10/H9 -> 0.0045915462 | I12: =I10/I9 -> 0.0049355223 | J12: =J10/J9 -> 0.0047419026 | ... R12: =R10/R9 -> #DIV/0!
C13: 4K Newrest, 1K SGS | G13: Empresas desactivadas por cobranza que se reactivaron en mayo | K13: *Baja sin contar implementación habría sido $182 = 0,096% | L13: 1500 de Urimar
K14: Casi 4K de OVG
E15: =AVERAGE(C12,D12,E12,G12) -> 0.0086167357
A17: Cartera | B17: ENTERPRISE | AJ17: Empresas por Cantidad de Productos Cross (OK) | AP17: Empresas por # Productos Cross - ENTERPRISE por KAM | AX17: Empresas por # Productos Cross - SMB por KAM
D18: MRR real | L18: Recuento de OK por Producto y Cartera | P18: ENTERPRISE por Rubro Claude - Recuento OK | AJ18: # Productos | AK18: ENTERPRISE | AL18: % Enterprise | AM18: SMB | AN18: % SMB | AP18: # Productos | AQ18: Dafne de la Rosa | AR18: Karla Patiño | AS18: Raúl Campos | AT18: No Asignado | AU18: Implementando | AV18: TOTAL | AX18: # Productos | AY18: Dafne de la Rosa | AZ18: Karla Patiño | BA18: Raúl Campos | BB18: No Asignado | BC18: TOTAL
A19: Cuadrante (MARE + Retener) | B19: Cuenta de CLIENTE | C19: Cuenta de Acción especifica | D19: Suma de Facturación actual USD | F19: KAM | G19: Cuadrante (MARE + Retener) | H19: Cuenta de CLIENTE | I19: Cuenta de Acción especifica | J19: Suma de Facturación actual USD | L19: Producto | M19: ENTERPRISE | N19: SMB | P19: Producto | Q19: Agrícola | R19: Automotriz | S19: Banca y Finanzas | T19: Construcción | U19: Educación | V19: Energía | W19: Gobierno | X19: Logística | Y19: Manufactura | Z19: Outsourcing | AA19: Retail | AB19: Salud | AC19: Seguridad Privada | AD19: Servicios | AE19: Tecnología | AF19: Transporte | AG19: Turismo y Gastronomía | AJ19: 0 | AK19: =COUNTIFS('MARE MX'!$I:$I,"ENTERPRISE",'MARE MX'!$CL:$CL,0) -> 103 | AL19: =AK19/$AK$24 -> 0.75182482 | AM19: =COUNTIFS('MARE MX'!$I:$I,"SMB",'MARE MX'!$CL:$CL,0) -> 335 | AN19: =AM19/$AM$24 -> 0.94366197 | AP19: 0 | AQ19: =COUNTIFS('MARE MX'!I:I,"ENTERPRISE",'MARE MX'!E:E,"Dafne de la Rosa",'MARE MX'!D:D,0) -> 42 | AR19: =COUNTIFS('MARE MX'!I:I,"ENTERPRISE",'MARE MX'!E:E,"Karla Patiño",'MARE MX'!D:D,0) -> 5 | AS19: =COUNTIFS('MARE MX'!I:I,"ENTERPRISE",'MARE MX'!E:E,"Raúl Campos",'MARE MX'!CL:CL,0) -> 50 | AT19: =COUNTIFS('MARE MX'!I:I,"ENTERPRISE",'MARE MX'!E:E,"No Asignado",'MARE MX'!CL:CL,0) -> 2 | AU19: =COUNTIFS('MARE MX'!I:I,"ENTERPRISE",'MARE MX'!E:E,"Implementando",'MARE MX'!CL:CL,0) -> 1 | AV19: =SUM(AQ19:AU19) -> 100 | AX19: 0 | AY19: =COUNTIFS('MARE MX'!$I:$I,"SMB",'MARE MX'!$E:$E,"Dafne de la Rosa",'MARE MX'!$CL:$CL,0) -> 47 | AZ19: =COUNTIFS('MARE MX'!$I:$I,"SMB",'MARE MX'!$E:$E,"Karla Patiño",'MARE MX'!$CL:$CL,0) -> 144 | BA19: =COUNTIFS('MARE MX'!$I:$I,"SMB",'MARE MX'!$E:$E,"Raúl Campos",'MARE MX'!$CL:$CL,0) -> 8 | BB19: =COUNTIFS('MARE MX'!$I:$I,"SMB",'MARE MX'!$E:$E,"No Asignado",'MARE MX'!$CL:$CL,0) -> 136 | BC19: =SUM(AY19:BB19) -> 335
A20: Alcanzar | B20: 8 | D20: 8275.7982 | F20: Dafne de la Rosa | G20: Alcanzar | H20: 10 | J20: 3216.7567 | L20: Alertas | M20: =COUNTIFS('MARE MX'!$I:$I,"ENTERPRISE",'MARE MX'!$AT:$AT,"*OK*") -> 3 | N20: =COUNTIFS('MARE MX'!$I:$I,"SMB",'MARE MX'!$AT:$AT,"*OK*") -> 2 | P20: Alertas | Q20: =COUNTIFS('MARE MX'!$I:$I,"ENTERPRISE",'MARE MX'!$AJ:$AJ,"Agrícola",'MARE MX'!$AT:$AT,"*OK*") -> 0 | R20: =COUNTIFS('MARE MX'!$I:$I,"ENTERPRISE",'MARE MX'!$AJ:$AJ,"Automotriz",'MARE MX'!$AT:$AT,"*OK*") -> 0 | S20: =COUNTIFS('MARE MX'!$I:$I,"ENTERPRISE",'MARE MX'!$AJ:$AJ,"Banca y Finanzas",'MARE MX'!$AT:$AT,"*OK*") -> 0 | T20: =COUNTIFS('MARE MX'!$I:$I,"ENTERPRISE",'MARE MX'!$AJ:$AJ,"Construcción",'MARE MX'!$AT:$AT,"*OK*") -> 0 | U20: =COUNTIFS('MARE MX'!$I:$I,"ENTERPRISE",'MARE MX'!$AJ:$AJ,"Educación",'MARE MX'!$AT:$AT,"*OK*") -> 0 | V20: =COUNTIFS('MARE MX'!$I:$I,"ENTERPRISE",'MARE MX'!$AJ:$AJ,"Energía",'MARE MX'!$AT:$AT,"*OK*") -> 0 | W20: =COUNTIFS('MARE MX'!$I:$I,"ENTERPRISE",'MARE MX'!$AJ:$AJ,"Gobierno",'MARE MX'!$AT:$AT,"*OK*") -> 0 | X20: =COUNTIFS('MARE MX'!$I:$I,"ENTERPRISE",'MARE MX'!$AJ:$AJ,"Logística",'MARE MX'!$AT:$AT,"*OK*") -> 0 | Y20: =COUNTIFS('MARE MX'!$I:$I,"ENTERPRISE",'MARE MX'!$AJ:$AJ,"Manufactura",'MARE MX'!$AT:$AT,"*OK*") -> 1 | Z20: =COUNTIFS('MARE MX'!$I:$I,"ENTERPRISE",'MARE MX'!$AJ:$AJ,"Outsourcing",'MARE MX'!$AT:$AT,"*OK*") -> 0 | AA20: =COUNTIFS('MARE MX'!$I:$I,"ENTERPRISE",'MARE MX'!$AJ:$AJ,"Retail",'MARE MX'!$AT:$AT,"*OK*") -> 0 | AB20: =COUNTIFS('MARE MX'!$I:$I,"ENTERPRISE",'MARE MX'!$AJ:$AJ,"Salud",'MARE MX'!$AT:$AT,"*OK*") -> 0 | AC20: =COUNTIFS('MARE MX'!$I:$I,"ENTERPRISE",'MARE MX'!$AJ:$AJ,"Seguridad Privada",'MARE MX'!$AT:$AT,"*OK*") -> 0 | AD20: =COUNTIFS('MARE MX'!$I:$I,"ENTERPRISE",'MARE MX'!$AJ:$AJ,"Servicios",'MARE MX'!$AT:$AT,"*OK*") -> 0 | AE20: =COUNTIFS('MARE MX'!$I:$I,"ENTERPRISE",'MARE MX'!$AJ:$AJ,"Tecnología",'MARE MX'!$AT:$AT,"*OK*") -> 0 | AF20: =COUNTIFS('MARE MX'!$I:$I,"ENTERPRISE",'MARE MX'!$AJ:$AJ,"Transporte",'MARE MX'!$AT:$AT,"*OK*") -> 0 | AG20: =COUNTIFS('MARE MX'!$I:$I,"ENTERPRISE",'MARE MX'!$AJ:$AJ,"Turismo y Gastronomía",'MARE MX'!$AT:$AT,"*OK*") -> 1 | AJ20: 1 | AK20: =COUNTIFS('MARE MX'!$I:$I,"ENTERPRISE",'MARE MX'!$CL:$CL,1) -> 24 | AL20: =AK20/$AK$24 -> 0.17518248 | AM20: =COUNTIFS('MARE MX'!$I:$I,"SMB",'MARE MX'!$CL:$CL,1) -> 13 | AN20: =AM20/$AM$24 -> 0.036619718 | AP20: 1 | AQ20: =COUNTIFS('MARE MX'!I:I,"ENTERPRISE",'MARE MX'!E:E,"Dafne de la Rosa",'MARE MX'!D:D,1) -> 11 | AR20: =COUNTIFS('MARE MX'!I:I,"ENTERPRISE",'MARE MX'!E:E,"Karla Patiño",'MARE MX'!CL:CL,1) -> 0 | AS20: =COUNTIFS('MARE MX'!I:I,"ENTERPRISE",'MARE MX'!E:E,"Raúl Campos",'MARE MX'!CL:CL,1) -> 16 | AT20: =COUNTIFS('MARE MX'!I:I,"ENTERPRISE",'MARE MX'!E:E,"No Asignado",'MARE MX'!CL:CL,1) -> 0 | AU20: =COUNTIFS('MARE MX'!I:I,"ENTERPRISE",'MARE MX'!E:E,"Implementando",'MARE MX'!CL:CL,1) -> 0 | AV20: =SUM(AQ20:AU20) -> 27 | AX20: 1 | AY20: =COUNTIFS('MARE MX'!$I:$I,"SMB",'MARE MX'!$E:$E,"Dafne de la Rosa",'MARE MX'!$CL:$CL,1) -> 2 | AZ20: =COUNTIFS('MARE MX'!$I:$I,"SMB",'MARE MX'!$E:$E,"Karla Patiño",'MARE MX'!$CL:$CL,1) -> 5 | BA20: =COUNTIFS('MARE MX'!$I:$I,"SMB",'MARE MX'!$E:$E,"Raúl Campos",'MARE MX'!$CL:$CL,1) -> 1 | BB20: =COUNTIFS('MARE MX'!$I:$I,"SMB",'MARE MX'!$E:$E,"No Asignado",'MARE MX'!$CL:$CL,1) -> 5 | BC20: =SUM(AY20:BB20) -> 13
A21: Expandir | B21: 30 | D21: 39290.746 | G21: Expandir | H21: 16 | J21: 16538.444 | L21: Integración (VC) | M21: =COUNTIFS('MARE MX'!$I:$I,"ENTERPRISE",'MARE MX'!$AU:$AU,"*OK*") -> 1 | N21: =COUNTIFS('MARE MX'!$I:$I,"SMB",'MARE MX'!$AU:$AU,"*OK*") -> 0 | P21: Integración (VC) | Q21: =COUNTIFS('MARE MX'!$I:$I,"ENTERPRISE",'MARE MX'!$AJ:$AJ,"Agrícola",'MARE MX'!$AU:$AU,"*OK*") -> 0 | R21: =COUNTIFS('MARE MX'!$I:$I,"ENTERPRISE",'MARE MX'!$AJ:$AJ,"Automotriz",'MARE MX'!$AU:$AU,"*OK*") -> 0 | S21: =COUNTIFS('MARE MX'!$I:$I,"ENTERPRISE",'MARE MX'!$AJ:$AJ,"Banca y Finanzas",'MARE MX'!$AU:$AU,"*OK*") -> 0 | T21: =COUNTIFS('MARE MX'!$I:$I,"ENTERPRISE",'MARE MX'!$AJ:$AJ,"Construcción",'MARE MX'!$AU:$AU,"*OK*") -> 0 | U21: =COUNTIFS('MARE MX'!$I:$I,"ENTERPRISE",'MARE MX'!$AJ:$AJ,"Educación",'MARE MX'!$AU:$AU,"*OK*") -> 0 | V21: =COUNTIFS('MARE MX'!$I:$I,"ENTERPRISE",'MARE MX'!$AJ:$AJ,"Energía",'MARE MX'!$AU:$AU,"*OK*") -> 0 | W21: =COUNTIFS('MARE MX'!$I:$I,"ENTERPRISE",'MARE MX'!$AJ:$AJ,"Gobierno",'MARE MX'!$AU:$AU,"*OK*") -> 0 | X21: =COUNTIFS('MARE MX'!$I:$I,"ENTERPRISE",'MARE MX'!$AJ:$AJ,"Logística",'MARE MX'!$AU:$AU,"*OK*") -> 0 | Y21: =COUNTIFS('MARE MX'!$I:$I,"ENTERPRISE",'MARE MX'!$AJ:$AJ,"Manufactura",'MARE MX'!$AU:$AU,"*OK*") -> 0 | Z21: =COUNTIFS('MARE MX'!$I:$I,"ENTERPRISE",'MARE MX'!$AJ:$AJ,"Outsourcing",'MARE MX'!$AU:$AU,"*OK*") -> 0 | AA21: =COUNTIFS('MARE MX'!$I:$I,"ENTERPRISE",'MARE MX'!$AJ:$AJ,"Retail",'MARE MX'!$AU:$AU,"*OK*") -> 0 | AB21: =COUNTIFS('MARE MX'!$I:$I,"ENTERPRISE",'MARE MX'!$AJ:$AJ,"Salud",'MARE MX'!$AU:$AU,"*OK*") -> 0 | AC21: =COUNTIFS('MARE MX'!$I:$I,"ENTERPRISE",'MARE MX'!$AJ:$AJ,"Seguridad Privada",'MARE MX'!$AU:$AU,"*OK*") -> 0 | AD21: =COUNTIFS('MARE MX'!$I:$I,"ENTERPRISE",'MARE MX'!$AJ:$AJ,"Servicios",'MARE MX'!$AU:$AU,"*OK*") -> 1 | AE21: =COUNTIFS('MARE MX'!$I:$I,"ENTERPRISE",'MARE MX'!$AJ:$AJ,"Tecnología",'MARE MX'!$AU:$AU,"*OK*") -> 0 | AF21: =COUNTIFS('MARE MX'!$I:$I,"ENTERPRISE",'MARE MX'!$AJ:$AJ,"Transporte",'MARE MX'!$AU:$AU,"*OK*") -> 0 | AG21: =COUNTIFS('MARE MX'!$I:$I,"ENTERPRISE",'MARE MX'!$AJ:$AJ,"Turismo y Gastronomía",'MARE MX'!$AU:$AU,"*OK*") -> 0 | AJ21: 2 | AK21: =COUNTIFS('MARE MX'!$I:$I,"ENTERPRISE",'MARE MX'!$CL:$CL,2) -> 6 | AL21: =AK21/$AK$24 -> 0.04379562 | AM21: =COUNTIFS('MARE MX'!$I:$I,"SMB",'MARE MX'!$CL:$CL,2) -> 5 | AN21: =AM21/$AM$24 -> 0.014084507 | AP21: 2 | AQ21: =COUNTIFS('MARE MX'!I:I,"ENTERPRISE",'MARE MX'!E:E,"Dafne de la Rosa",'MARE MX'!D:D,2) -> 3 | AR21: =COUNTIFS('MARE MX'!I:I,"ENTERPRISE",'MARE MX'!E:E,"Karla Patiño",'MARE MX'!CL:CL,2) -> 0 | AS21: =COUNTIFS('MARE MX'!I:I,"ENTERPRISE",'MARE MX'!E:E,"Raúl Campos",'MARE MX'!CL:CL,2) -> 3 | AT21: =COUNTIFS('MARE MX'!I:I,"ENTERPRISE",'MARE MX'!E:E,"No Asignado",'MARE MX'!CL:CL,2) -> 0 | AU21: =COUNTIFS('MARE MX'!I:I,"ENTERPRISE",'MARE MX'!E:E,"Implementando",'MARE MX'!CL:CL,2) -> 0 | AV21: =SUM(AQ21:AU21) -> 6 | AX21: 2 | AY21: =COUNTIFS('MARE MX'!$I:$I,"SMB",'MARE MX'!$E:$E,"Dafne de la Rosa",'MARE MX'!$CL:$CL,2) -> 1 | AZ21: =COUNTIFS('MARE MX'!$I:$I,"SMB",'MARE MX'!$E:$E,"Karla Patiño",'MARE MX'!$CL:$CL,2) -> 3 | BA21: =COUNTIFS('MARE MX'!$I:$I,"SMB",'MARE MX'!$E:$E,"Raúl Campos",'MARE MX'!$CL:$CL,2) -> 1 | BB21: =COUNTIFS('MARE MX'!$I:$I,"SMB",'MARE MX'!$E:$E,"No Asignado",'MARE MX'!$CL:$CL,2) -> 0 | BC21: =SUM(AY21:BB21) -> 5
A22: Mantener | B22: 65 | D22: 52098.482 | G22: Mantener | H22: 45 | J22: 20471.957 | L22: Permisos y vacaciones | M22: =COUNTIFS('MARE MX'!$I:$I,"ENTERPRISE",'MARE MX'!$AV:$AV,"*OK*") -> 14 | N22: =COUNTIFS('MARE MX'!$I:$I,"SMB",'MARE MX'!$AV:$AV,"*OK*") -> 14 | P22: Permisos y vacaciones | Q22: =COUNTIFS('MARE MX'!$I:$I,"ENTERPRISE",'MARE MX'!$AJ:$AJ,"Agrícola",'MARE MX'!$AV:$AV,"*OK*") -> 0 | R22: =COUNTIFS('MARE MX'!$I:$I,"ENTERPRISE",'MARE MX'!$AJ:$AJ,"Automotriz",'MARE MX'!$AV:$AV,"*OK*") -> 0 | S22: =COUNTIFS('MARE MX'!$I:$I,"ENTERPRISE",'MARE MX'!$AJ:$AJ,"Banca y Finanzas",'MARE MX'!$AV:$AV,"*OK*") -> 0 | T22: =COUNTIFS('MARE MX'!$I:$I,"ENTERPRISE",'MARE MX'!$AJ:$AJ,"Construcción",'MARE MX'!$AV:$AV,"*OK*") -> 0 | U22: =COUNTIFS('MARE MX'!$I:$I,"ENTERPRISE",'MARE MX'!$AJ:$AJ,"Educación",'MARE MX'!$AV:$AV,"*OK*") -> 0 | V22: =COUNTIFS('MARE MX'!$I:$I,"ENTERPRISE",'MARE MX'!$AJ:$AJ,"Energía",'MARE MX'!$AV:$AV,"*OK*") -> 0 | W22: =COUNTIFS('MARE MX'!$I:$I,"ENTERPRISE",'MARE MX'!$AJ:$AJ,"Gobierno",'MARE MX'!$AV:$AV,"*OK*") -> 0 | X22: =COUNTIFS('MARE MX'!$I:$I,"ENTERPRISE",'MARE MX'!$AJ:$AJ,"Logística",'MARE MX'!$AV:$AV,"*OK*") -> 1 | Y22: =COUNTIFS('MARE MX'!$I:$I,"ENTERPRISE",'MARE MX'!$AJ:$AJ,"Manufactura",'MARE MX'!$AV:$AV,"*OK*") -> 6 | Z22: =COUNTIFS('MARE MX'!$I:$I,"ENTERPRISE",'MARE MX'!$AJ:$AJ,"Outsourcing",'MARE MX'!$AV:$AV,"*OK*") -> 0 | AA22: =COUNTIFS('MARE MX'!$I:$I,"ENTERPRISE",'MARE MX'!$AJ:$AJ,"Retail",'MARE MX'!$AV:$AV,"*OK*") -> 2 | AB22: =COUNTIFS('MARE MX'!$I:$I,"ENTERPRISE",'MARE MX'!$AJ:$AJ,"Salud",'MARE MX'!$AV:$AV,"*OK*") -> 0 | AC22: =COUNTIFS('MARE MX'!$I:$I,"ENTERPRISE",'MARE MX'!$AJ:$AJ,"Seguridad Privada",'MARE MX'!$AV:$AV,"*OK*") -> 0 | AD22: =COUNTIFS('MARE MX'!$I:$I,"ENTERPRISE",'MARE MX'!$AJ:$AJ,"Servicios",'MARE MX'!$AV:$AV,"*OK*") -> 2 | AE22: =COUNTIFS('MARE MX'!$I:$I,"ENTERPRISE",'MARE MX'!$AJ:$AJ,"Tecnología",'MARE MX'!$AV:$AV,"*OK*") -> 0 | AF22: =COUNTIFS('MARE MX'!$I:$I,"ENTERPRISE",'MARE MX'!$AJ:$AJ,"Transporte",'MARE MX'!$AV:$AV,"*OK*") -> 0 | AG22: =COUNTIFS('MARE MX'!$I:$I,"ENTERPRISE",'MARE MX'!$AJ:$AJ,"Turismo y Gastronomía",'MARE MX'!$AV:$AV,"*OK*") -> 1 | AJ22: 3 | AK22: =COUNTIFS('MARE MX'!$I:$I,"ENTERPRISE",'MARE MX'!$CL:$CL,3) -> 3 | AL22: =AK22/$AK$24 -> 0.02189781 | AM22: =COUNTIFS('MARE MX'!$I:$I,"SMB",'MARE MX'!$CL:$CL,3) -> 2 | AN22: =AM22/$AM$24 -> 0.0056338028 | AP22: 3 | AQ22: =COUNTIFS('MARE MX'!I:I,"ENTERPRISE",'MARE MX'!E:E,"Dafne de la Rosa",'MARE MX'!D:D,3) -> 0 | AR22: =COUNTIFS('MARE MX'!I:I,"ENTERPRISE",'MARE MX'!E:E,"Karla Patiño",'MARE MX'!CL:CL,3) -> 2 | AS22: =COUNTIFS('MARE MX'!I:I,"ENTERPRISE",'MARE MX'!E:E,"Raúl Campos",'MARE MX'!CL:CL,3) -> 1 | AT22: =COUNTIFS('MARE MX'!I:I,"ENTERPRISE",'MARE MX'!E:E,"No Asignado",'MARE MX'!CL:CL,3) -> 0 | AU22: =COUNTIFS('MARE MX'!I:I,"ENTERPRISE",'MARE MX'!E:E,"Implementando",'MARE MX'!CL:CL,3) -> 0 | AV22: =SUM(AQ22:AU22) -> 3 | AX22: 3 | AY22: =COUNTIFS('MARE MX'!$I:$I,"SMB",'MARE MX'!$E:$E,"Dafne de la Rosa",'MARE MX'!$CL:$CL,3) -> 1 | AZ22: =COUNTIFS('MARE MX'!$I:$I,"SMB",'MARE MX'!$E:$E,"Karla Patiño",'MARE MX'!$CL:$CL,3) -> 1 | BA22: =COUNTIFS('MARE MX'!$I:$I,"SMB",'MARE MX'!$E:$E,"Raúl Campos",'MARE MX'!$CL:$CL,3) -> 0 | BB22: =COUNTIFS('MARE MX'!$I:$I,"SMB",'MARE MX'!$E:$E,"No Asignado",'MARE MX'!$CL:$CL,3) -> 0 | BC22: =SUM(AY22:BB22) -> 2
A23: Recuperar | B23: 1 | D23: 652.5313 | G23: Recuperar | H23: 6 | J23: 1189.6943 | L23: Planif. Inteligente | M23: =COUNTIFS('MARE MX'!$I:$I,"ENTERPRISE",'MARE MX'!$AW:$AW,"*OK*") -> 4 | N23: =COUNTIFS('MARE MX'!$I:$I,"SMB",'MARE MX'!$AW:$AW,"*OK*") -> 1 | P23: Planif. Inteligente | Q23: =COUNTIFS('MARE MX'!$I:$I,"ENTERPRISE",'MARE MX'!$AJ:$AJ,"Agrícola",'MARE MX'!$AW:$AW,"*OK*") -> 0 | R23: =COUNTIFS('MARE MX'!$I:$I,"ENTERPRISE",'MARE MX'!$AJ:$AJ,"Automotriz",'MARE MX'!$AW:$AW,"*OK*") -> 0 | S23: =COUNTIFS('MARE MX'!$I:$I,"ENTERPRISE",'MARE MX'!$AJ:$AJ,"Banca y Finanzas",'MARE MX'!$AW:$AW,"*OK*") -> 0 | T23: =COUNTIFS('MARE MX'!$I:$I,"ENTERPRISE",'MARE MX'!$AJ:$AJ,"Construcción",'MARE MX'!$AW:$AW,"*OK*") -> 0 | U23: =COUNTIFS('MARE MX'!$I:$I,"ENTERPRISE",'MARE MX'!$AJ:$AJ,"Educación",'MARE MX'!$AW:$AW,"*OK*") -> 0 | V23: =COUNTIFS('MARE MX'!$I:$I,"ENTERPRISE",'MARE MX'!$AJ:$AJ,"Energía",'MARE MX'!$AW:$AW,"*OK*") -> 0 | W23: =COUNTIFS('MARE MX'!$I:$I,"ENTERPRISE",'MARE MX'!$AJ:$AJ,"Gobierno",'MARE MX'!$AW:$AW,"*OK*") -> 0 | X23: =COUNTIFS('MARE MX'!$I:$I,"ENTERPRISE",'MARE MX'!$AJ:$AJ,"Logística",'MARE MX'!$AW:$AW,"*OK*") -> 0 | Y23: =COUNTIFS('MARE MX'!$I:$I,"ENTERPRISE",'MARE MX'!$AJ:$AJ,"Manufactura",'MARE MX'!$AW:$AW,"*OK*") -> 1 | Z23: =COUNTIFS('MARE MX'!$I:$I,"ENTERPRISE",'MARE MX'!$AJ:$AJ,"Outsourcing",'MARE MX'!$AW:$AW,"*OK*") -> 2 | AA23: =COUNTIFS('MARE MX'!$I:$I,"ENTERPRISE",'MARE MX'!$AJ:$AJ,"Retail",'MARE MX'!$AW:$AW,"*OK*") -> 0 | AB23: =COUNTIFS('MARE MX'!$I:$I,"ENTERPRISE",'MARE MX'!$AJ:$AJ,"Salud",'MARE MX'!$AW:$AW,"*OK*") -> 0 | AC23: =COUNTIFS('MARE MX'!$I:$I,"ENTERPRISE",'MARE MX'!$AJ:$AJ,"Seguridad Privada",'MARE MX'!$AW:$AW,"*OK*") -> 0 | AD23: =COUNTIFS('MARE MX'!$I:$I,"ENTERPRISE",'MARE MX'!$AJ:$AJ,"Servicios",'MARE MX'!$AW:$AW,"*OK*") -> 0 | AE23: =COUNTIFS('MARE MX'!$I:$I,"ENTERPRISE",'MARE MX'!$AJ:$AJ,"Tecnología",'MARE MX'!$AW:$AW,"*OK*") -> 0 | AF23: =COUNTIFS('MARE MX'!$I:$I,"ENTERPRISE",'MARE MX'!$AJ:$AJ,"Transporte",'MARE MX'!$AW:$AW,"*OK*") -> 0 | AG23: =COUNTIFS('MARE MX'!$I:$I,"ENTERPRISE",'MARE MX'!$AJ:$AJ,"Turismo y Gastronomía",'MARE MX'!$AW:$AW,"*OK*") -> 1 | AJ23: 4 | AK23: =COUNTIFS('MARE MX'!$I:$I,"ENTERPRISE",'MARE MX'!$CL:$CL,4) -> 1 | AL23: =AK23/$AK$24 -> 0.0072992701 | AM23: =COUNTIFS('MARE MX'!$I:$I,"SMB",'MARE MX'!$CL:$CL,4) -> 0 | AN23: =AM23/$AM$24 -> 0 | AP23: 4 | AQ23: =COUNTIFS('MARE MX'!I:I,"ENTERPRISE",'MARE MX'!E:E,"Dafne de la Rosa",'MARE MX'!D:D,4) -> 0 | AR23: =COUNTIFS('MARE MX'!I:I,"ENTERPRISE",'MARE MX'!E:E,"Karla Patiño",'MARE MX'!CL:CL,4) -> 0 | AS23: =COUNTIFS('MARE MX'!I:I,"ENTERPRISE",'MARE MX'!E:E,"Raúl Campos",'MARE MX'!CL:CL,4) -> 1 | AT23: =COUNTIFS('MARE MX'!I:I,"ENTERPRISE",'MARE MX'!E:E,"No Asignado",'MARE MX'!CL:CL,4) -> 0 | AU23: =COUNTIFS('MARE MX'!I:I,"ENTERPRISE",'MARE MX'!E:E,"Implementando",'MARE MX'!CL:CL,4) -> 0 | AV23: =SUM(AQ23:AU23) -> 1 | AX23: 4 | AY23: =COUNTIFS('MARE MX'!$I:$I,"SMB",'MARE MX'!$E:$E,"Dafne de la Rosa",'MARE MX'!$CL:$CL,4) -> 0 | AZ23: =COUNTIFS('MARE MX'!$I:$I,"SMB",'MARE MX'!$E:$E,"Karla Patiño",'MARE MX'!$CL:$CL,4) -> 0 | BA23: =COUNTIFS('MARE MX'!$I:$I,"SMB",'MARE MX'!$E:$E,"Raúl Campos",'MARE MX'!$CL:$CL,4) -> 0 | BB23: =COUNTIFS('MARE MX'!$I:$I,"SMB",'MARE MX'!$E:$E,"No Asignado",'MARE MX'!$CL:$CL,4) -> 0 | BC23: =SUM(AY23:BB23) -> 0
A24: (en blanco) | B24: 13 | D24: 13647.375 | G24: (en blanco) | H24: 11 | J24: 2187.7211 | L24: BI | M24: =COUNTIFS('MARE MX'!$I:$I,"ENTERPRISE",'MARE MX'!$AX:$AX,"*OK*") -> 10 | N24: =COUNTIFS('MARE MX'!$I:$I,"SMB",'MARE MX'!$AX:$AX,"*OK*") -> 3 | P24: BI | Q24: =COUNTIFS('MARE MX'!$I:$I,"ENTERPRISE",'MARE MX'!$AJ:$AJ,"Agrícola",'MARE MX'!$AX:$AX,"*OK*") -> 0 | R24: =COUNTIFS('MARE MX'!$I:$I,"ENTERPRISE",'MARE MX'!$AJ:$AJ,"Automotriz",'MARE MX'!$AX:$AX,"*OK*") -> 0 | S24: =COUNTIFS('MARE MX'!$I:$I,"ENTERPRISE",'MARE MX'!$AJ:$AJ,"Banca y Finanzas",'MARE MX'!$AX:$AX,"*OK*") -> 0 | T24: =COUNTIFS('MARE MX'!$I:$I,"ENTERPRISE",'MARE MX'!$AJ:$AJ,"Construcción",'MARE MX'!$AX:$AX,"*OK*") -> 2 | U24: =COUNTIFS('MARE MX'!$I:$I,"ENTERPRISE",'MARE MX'!$AJ:$AJ,"Educación",'MARE MX'!$AX:$AX,"*OK*") -> 0 | V24: =COUNTIFS('MARE MX'!$I:$I,"ENTERPRISE",'MARE MX'!$AJ:$AJ,"Energía",'MARE MX'!$AX:$AX,"*OK*") -> 0 | W24: =COUNTIFS('MARE MX'!$I:$I,"ENTERPRISE",'MARE MX'!$AJ:$AJ,"Gobierno",'MARE MX'!$AX:$AX,"*OK*") -> 0 | X24: =COUNTIFS('MARE MX'!$I:$I,"ENTERPRISE",'MARE MX'!$AJ:$AJ,"Logística",'MARE MX'!$AX:$AX,"*OK*") -> 0 | Y24: =COUNTIFS('MARE MX'!$I:$I,"ENTERPRISE",'MARE MX'!$AJ:$AJ,"Manufactura",'MARE MX'!$AX:$AX,"*OK*") -> 4 | Z24: =COUNTIFS('MARE MX'!$I:$I,"ENTERPRISE",'MARE MX'!$AJ:$AJ,"Outsourcing",'MARE MX'!$AX:$AX,"*OK*") -> 0 | AA24: =COUNTIFS('MARE MX'!$I:$I,"ENTERPRISE",'MARE MX'!$AJ:$AJ,"Retail",'MARE MX'!$AX:$AX,"*OK*") -> 1 | AB24: =COUNTIFS('MARE MX'!$I:$I,"ENTERPRISE",'MARE MX'!$AJ:$AJ,"Salud",'MARE MX'!$AX:$AX,"*OK*") -> 0 | AC24: =COUNTIFS('MARE MX'!$I:$I,"ENTERPRISE",'MARE MX'!$AJ:$AJ,"Seguridad Privada",'MARE MX'!$AX:$AX,"*OK*") -> 0 | AD24: =COUNTIFS('MARE MX'!$I:$I,"ENTERPRISE",'MARE MX'!$AJ:$AJ,"Servicios",'MARE MX'!$AX:$AX,"*OK*") -> 0 | AE24: =COUNTIFS('MARE MX'!$I:$I,"ENTERPRISE",'MARE MX'!$AJ:$AJ,"Tecnología",'MARE MX'!$AX:$AX,"*OK*") -> 1 | AF24: =COUNTIFS('MARE MX'!$I:$I,"ENTERPRISE",'MARE MX'!$AJ:$AJ,"Transporte",'MARE MX'!$AX:$AX,"*OK*") -> 0 | AG24: =COUNTIFS('MARE MX'!$I:$I,"ENTERPRISE",'MARE MX'!$AJ:$AJ,"Turismo y Gastronomía",'MARE MX'!$AX:$AX,"*OK*") -> 1 | AJ24: TOTAL | AK24: =SUM(AK19:AK23) -> 137 | AM24: =SUM(AM19:AM23) -> 355 | AP24: TOTAL | AQ24: =SUM(AQ19:AQ23) -> 56 | AR24: =SUM(AR19:AR23) -> 7 | AS24: =SUM(AS19:AS23) -> 71 | AT24: =SUM(AT19:AT23) -> 2 | AU24: =SUM(AU19:AU23) -> 1 | AV24: =SUM(AV19:AV23) -> 137 | AX24: TOTAL | AY24: =SUM(AY19:AY23) -> 51 | AZ24: =SUM(AZ19:AZ23) -> 153 | BA24: =SUM(BA19:BA23) -> 10 | BB24: =SUM(BB19:BB23) -> 141 | BC24: =SUM(BC19:BC23) -> 355
A25: Retener | B25: 2 | D25: 1793.5662 | G25: Retener | H25: 8 | J25: 3065.2405 | L25: RAM | M25: =COUNTIFS('MARE MX'!$I:$I,"ENTERPRISE",'MARE MX'!$AY:$AY,"*OK*") -> 5 | N25: =COUNTIFS('MARE MX'!$I:$I,"SMB",'MARE MX'!$AY:$AY,"*OK*") -> 2 | P25: RAM | Q25: =COUNTIFS('MARE MX'!$I:$I,"ENTERPRISE",'MARE MX'!$AJ:$AJ,"Agrícola",'MARE MX'!$AY:$AY,"*OK*") -> 0 | R25: =COUNTIFS('MARE MX'!$I:$I,"ENTERPRISE",'MARE MX'!$AJ:$AJ,"Automotriz",'MARE MX'!$AY:$AY,"*OK*") -> 0 | S25: =COUNTIFS('MARE MX'!$I:$I,"ENTERPRISE",'MARE MX'!$AJ:$AJ,"Banca y Finanzas",'MARE MX'!$AY:$AY,"*OK*") -> 0 | T25: =COUNTIFS('MARE MX'!$I:$I,"ENTERPRISE",'MARE MX'!$AJ:$AJ,"Construcción",'MARE MX'!$AY:$AY,"*OK*") -> 0 | U25: =COUNTIFS('MARE MX'!$I:$I,"ENTERPRISE",'MARE MX'!$AJ:$AJ,"Educación",'MARE MX'!$AY:$AY,"*OK*") -> 0 | V25: =COUNTIFS('MARE MX'!$I:$I,"ENTERPRISE",'MARE MX'!$AJ:$AJ,"Energía",'MARE MX'!$AY:$AY,"*OK*") -> 1 | W25: =COUNTIFS('MARE MX'!$I:$I,"ENTERPRISE",'MARE MX'!$AJ:$AJ,"Gobierno",'MARE MX'!$AY:$AY,"*OK*") -> 0 | X25: =COUNTIFS('MARE MX'!$I:$I,"ENTERPRISE",'MARE MX'!$AJ:$AJ,"Logística",'MARE MX'!$AY:$AY,"*OK*") -> 0 | Y25: =COUNTIFS('MARE MX'!$I:$I,"ENTERPRISE",'MARE MX'!$AJ:$AJ,"Manufactura",'MARE MX'!$AY:$AY,"*OK*") -> 1 | Z25: =COUNTIFS('MARE MX'!$I:$I,"ENTERPRISE",'MARE MX'!$AJ:$AJ,"Outsourcing",'MARE MX'!$AY:$AY,"*OK*") -> 1 | AA25: =COUNTIFS('MARE MX'!$I:$I,"ENTERPRISE",'MARE MX'!$AJ:$AJ,"Retail",'MARE MX'!$AY:$AY,"*OK*") -> 0 | AB25: =COUNTIFS('MARE MX'!$I:$I,"ENTERPRISE",'MARE MX'!$AJ:$AJ,"Salud",'MARE MX'!$AY:$AY,"*OK*") -> 0 | AC25: =COUNTIFS('MARE MX'!$I:$I,"ENTERPRISE",'MARE MX'!$AJ:$AJ,"Seguridad Privada",'MARE MX'!$AY:$AY,"*OK*") -> 0 | AD25: =COUNTIFS('MARE MX'!$I:$I,"ENTERPRISE",'MARE MX'!$AJ:$AJ,"Servicios",'MARE MX'!$AY:$AY,"*OK*") -> 0 | AE25: =COUNTIFS('MARE MX'!$I:$I,"ENTERPRISE",'MARE MX'!$AJ:$AJ,"Tecnología",'MARE MX'!$AY:$AY,"*OK*") -> 0 | AF25: =COUNTIFS('MARE MX'!$I:$I,"ENTERPRISE",'MARE MX'!$AJ:$AJ,"Transporte",'MARE MX'!$AY:$AY,"*OK*") -> 1 | AG25: =COUNTIFS('MARE MX'!$I:$I,"ENTERPRISE",'MARE MX'!$AJ:$AJ,"Turismo y Gastronomía",'MARE MX'!$AY:$AY,"*OK*") -> 1
A26: Total general | B26: 119 | D26: 115758.5 | F26: Total Dafne de la Rosa | H26: 96 | J26: 46669.814 | L26: Acceso | M26: =COUNTIFS('MARE MX'!$I:$I,"ENTERPRISE",'MARE MX'!$AZ:$AZ,"*OK*") -> 10 | N26: =COUNTIFS('MARE MX'!$I:$I,"SMB",'MARE MX'!$AZ:$AZ,"*OK*") -> 1 | P26: Acceso | Q26: =COUNTIFS('MARE MX'!$I:$I,"ENTERPRISE",'MARE MX'!$AJ:$AJ,"Agrícola",'MARE MX'!$AZ:$AZ,"*OK*") -> 1 | R26: =COUNTIFS('MARE MX'!$I:$I,"ENTERPRISE",'MARE MX'!$AJ:$AJ,"Automotriz",'MARE MX'!$AZ:$AZ,"*OK*") -> 0 | S26: =COUNTIFS('MARE MX'!$I:$I,"ENTERPRISE",'MARE MX'!$AJ:$AJ,"Banca y Finanzas",'MARE MX'!$AZ:$AZ,"*OK*") -> 0 | T26: =COUNTIFS('MARE MX'!$I:$I,"ENTERPRISE",'MARE MX'!$AJ:$AJ,"Construcción",'MARE MX'!$AZ:$AZ,"*OK*") -> 0 | U26: =COUNTIFS('MARE MX'!$I:$I,"ENTERPRISE",'MARE MX'!$AJ:$AJ,"Educación",'MARE MX'!$AZ:$AZ,"*OK*") -> 0 | V26: =COUNTIFS('MARE MX'!$I:$I,"ENTERPRISE",'MARE MX'!$AJ:$AJ,"Energía",'MARE MX'!$AZ:$AZ,"*OK*") -> 0 | W26: =COUNTIFS('MARE MX'!$I:$I,"ENTERPRISE",'MARE MX'!$AJ:$AJ,"Gobierno",'MARE MX'!$AZ:$AZ,"*OK*") -> 0 | X26: =COUNTIFS('MARE MX'!$I:$I,"ENTERPRISE",'MARE MX'!$AJ:$AJ,"Logística",'MARE MX'!$AZ:$AZ,"*OK*") -> 0 | Y26: =COUNTIFS('MARE MX'!$I:$I,"ENTERPRISE",'MARE MX'!$AJ:$AJ,"Manufactura",'MARE MX'!$AZ:$AZ,"*OK*") -> 3 | Z26: =COUNTIFS('MARE MX'!$I:$I,"ENTERPRISE",'MARE MX'!$AJ:$AJ,"Outsourcing",'MARE MX'!$AZ:$AZ,"*OK*") -> 2 | AA26: =COUNTIFS('MARE MX'!$I:$I,"ENTERPRISE",'MARE MX'!$AJ:$AJ,"Retail",'MARE MX'!$AZ:$AZ,"*OK*") -> 1 | AB26: =COUNTIFS('MARE MX'!$I:$I,"ENTERPRISE",'MARE MX'!$AJ:$AJ,"Salud",'MARE MX'!$AZ:$AZ,"*OK*") -> 2 | AC26: =COUNTIFS('MARE MX'!$I:$I,"ENTERPRISE",'MARE MX'!$AJ:$AJ,"Seguridad Privada",'MARE MX'!$AZ:$AZ,"*OK*") -> 0 | AD26: =COUNTIFS('MARE MX'!$I:$I,"ENTERPRISE",'MARE MX'!$AJ:$AJ,"Servicios",'MARE MX'!$AZ:$AZ,"*OK*") -> 1 | AE26: =COUNTIFS('MARE MX'!$I:$I,"ENTERPRISE",'MARE MX'!$AJ:$AJ,"Tecnología",'MARE MX'!$AZ:$AZ,"*OK*") -> 0 | AF26: =COUNTIFS('MARE MX'!$I:$I,"ENTERPRISE",'MARE MX'!$AJ:$AJ,"Transporte",'MARE MX'!$AZ:$AZ,"*OK*") -> 0 | AG26: =COUNTIFS('MARE MX'!$I:$I,"ENTERPRISE",'MARE MX'!$AJ:$AJ,"Turismo y Gastronomía",'MARE MX'!$AZ:$AZ,"*OK*") -> 0 | AP26: +1 prod | AQ26: =SUM(AQ20:AQ23)/AQ24 -> 0.25 | AR26: =SUM(AR20:AR23)/AR24 -> 0.28571429 | AS26: =SUM(AS20:AS23)/AS24 -> 0.29577465 | AT26: =SUM(AT20:AT23)/AT24 -> 0 | AU26: =SUM(AU20:AU23)/AU24 -> 0 | AX26: +1 prod | AY26: =SUM(AY20:AY23)/AY24 -> 0.078431373 | AZ26: =SUM(AZ20:AZ23)/AZ24 -> 0.058823529 | BA26: =SUM(BA20:BA23)/BA24 -> 0.2 | BB26: =SUM(BB20:BB23)/BB24 -> 0.035460993 | BC26: =SUM(BC20:BC23)/BC24 -> 0.056338028
F27: Karla Patiño | G27: Alcanzar | H27: 12 | J27: 2652.2347 | L27: Comedor | M27: =COUNTIFS('MARE MX'!$I:$I,"ENTERPRISE",'MARE MX'!$BA:$BA,"*OK*") -> 1 | N27: =COUNTIFS('MARE MX'!$I:$I,"SMB",'MARE MX'!$BA:$BA,"*OK*") -> 1 | P27: Comedor | Q27: =COUNTIFS('MARE MX'!$I:$I,"ENTERPRISE",'MARE MX'!$AJ:$AJ,"Agrícola",'MARE MX'!$BA:$BA,"*OK*") -> 0 | R27: =COUNTIFS('MARE MX'!$I:$I,"ENTERPRISE",'MARE MX'!$AJ:$AJ,"Automotriz",'MARE MX'!$BA:$BA,"*OK*") -> 0 | S27: =COUNTIFS('MARE MX'!$I:$I,"ENTERPRISE",'MARE MX'!$AJ:$AJ,"Banca y Finanzas",'MARE MX'!$BA:$BA,"*OK*") -> 0 | T27: =COUNTIFS('MARE MX'!$I:$I,"ENTERPRISE",'MARE MX'!$AJ:$AJ,"Construcción",'MARE MX'!$BA:$BA,"*OK*") -> 0 | U27: =COUNTIFS('MARE MX'!$I:$I,"ENTERPRISE",'MARE MX'!$AJ:$AJ,"Educación",'MARE MX'!$BA:$BA,"*OK*") -> 0 | V27: =COUNTIFS('MARE MX'!$I:$I,"ENTERPRISE",'MARE MX'!$AJ:$AJ,"Energía",'MARE MX'!$BA:$BA,"*OK*") -> 0 | W27: =COUNTIFS('MARE MX'!$I:$I,"ENTERPRISE",'MARE MX'!$AJ:$AJ,"Gobierno",'MARE MX'!$BA:$BA,"*OK*") -> 0 | X27: =COUNTIFS('MARE MX'!$I:$I,"ENTERPRISE",'MARE MX'!$AJ:$AJ,"Logística",'MARE MX'!$BA:$BA,"*OK*") -> 0 | Y27: =COUNTIFS('MARE MX'!$I:$I,"ENTERPRISE",'MARE MX'!$AJ:$AJ,"Manufactura",'MARE MX'!$BA:$BA,"*OK*") -> 0 | Z27: =COUNTIFS('MARE MX'!$I:$I,"ENTERPRISE",'MARE MX'!$AJ:$AJ,"Outsourcing",'MARE MX'!$BA:$BA,"*OK*") -> 0 | AA27: =COUNTIFS('MARE MX'!$I:$I,"ENTERPRISE",'MARE MX'!$AJ:$AJ,"Retail",'MARE MX'!$BA:$BA,"*OK*") -> 0 | AB27: =COUNTIFS('MARE MX'!$I:$I,"ENTERPRISE",'MARE MX'!$AJ:$AJ,"Salud",'MARE MX'!$BA:$BA,"*OK*") -> 0 | AC27: =COUNTIFS('MARE MX'!$I:$I,"ENTERPRISE",'MARE MX'!$AJ:$AJ,"Seguridad Privada",'MARE MX'!$BA:$BA,"*OK*") -> 0 | AD27: =COUNTIFS('MARE MX'!$I:$I,"ENTERPRISE",'MARE MX'!$AJ:$AJ,"Servicios",'MARE MX'!$BA:$BA,"*OK*") -> 1 | AE27: =COUNTIFS('MARE MX'!$I:$I,"ENTERPRISE",'MARE MX'!$AJ:$AJ,"Tecnología",'MARE MX'!$BA:$BA,"*OK*") -> 0 | AF27: =COUNTIFS('MARE MX'!$I:$I,"ENTERPRISE",'MARE MX'!$AJ:$AJ,"Transporte",'MARE MX'!$BA:$BA,"*OK*") -> 0 | AG27: =COUNTIFS('MARE MX'!$I:$I,"ENTERPRISE",'MARE MX'!$AJ:$AJ,"Turismo y Gastronomía",'MARE MX'!$BA:$BA,"*OK*") -> 0
G28: Alcanzar | H28: 1 | J28: 142.0289 | L28: VictorIA | M28: =COUNTIFS('MARE MX'!$I:$I,"ENTERPRISE",'MARE MX'!$BB:$BB,"*OK*") -> 0 | N28: =COUNTIFS('MARE MX'!$I:$I,"SMB",'MARE MX'!$BB:$BB,"*OK*") -> 0 | P28: VictorIA | Q28: =COUNTIFS('MARE MX'!$I:$I,"ENTERPRISE",'MARE MX'!$AJ:$AJ,"Agrícola",'MARE MX'!$BB:$BB,"*OK*") -> 0 | R28: =COUNTIFS('MARE MX'!$I:$I,"ENTERPRISE",'MARE MX'!$AJ:$AJ,"Automotriz",'MARE MX'!$BB:$BB,"*OK*") -> 0 | S28: =COUNTIFS('MARE MX'!$I:$I,"ENTERPRISE",'MARE MX'!$AJ:$AJ,"Banca y Finanzas",'MARE MX'!$BB:$BB,"*OK*") -> 0 | T28: =COUNTIFS('MARE MX'!$I:$I,"ENTERPRISE",'MARE MX'!$AJ:$AJ,"Construcción",'MARE MX'!$BB:$BB,"*OK*") -> 0 | U28: =COUNTIFS('MARE MX'!$I:$I,"ENTERPRISE",'MARE MX'!$AJ:$AJ,"Educación",'MARE MX'!$BB:$BB,"*OK*") -> 0 | V28: =COUNTIFS('MARE MX'!$I:$I,"ENTERPRISE",'MARE MX'!$AJ:$AJ,"Energía",'MARE MX'!$BB:$BB,"*OK*") -> 0 | W28: =COUNTIFS('MARE MX'!$I:$I,"ENTERPRISE",'MARE MX'!$AJ:$AJ,"Gobierno",'MARE MX'!$BB:$BB,"*OK*") -> 0 | X28: =COUNTIFS('MARE MX'!$I:$I,"ENTERPRISE",'MARE MX'!$AJ:$AJ,"Logística",'MARE MX'!$BB:$BB,"*OK*") -> 0 | Y28: =COUNTIFS('MARE MX'!$I:$I,"ENTERPRISE",'MARE MX'!$AJ:$AJ,"Manufactura",'MARE MX'!$BB:$BB,"*OK*") -> 0 | Z28: =COUNTIFS('MARE MX'!$I:$I,"ENTERPRISE",'MARE MX'!$AJ:$AJ,"Outsourcing",'MARE MX'!$BB:$BB,"*OK*") -> 0 | AA28: =COUNTIFS('MARE MX'!$I:$I,"ENTERPRISE",'MARE MX'!$AJ:$AJ,"Retail",'MARE MX'!$BB:$BB,"*OK*") -> 0 | AB28: =COUNTIFS('MARE MX'!$I:$I,"ENTERPRISE",'MARE MX'!$AJ:$AJ,"Salud",'MARE MX'!$BB:$BB,"*OK*") -> 0 | AC28: =COUNTIFS('MARE MX'!$I:$I,"ENTERPRISE",'MARE MX'!$AJ:$AJ,"Seguridad Privada",'MARE MX'!$BB:$BB,"*OK*") -> 0 | AD28: =COUNTIFS('MARE MX'!$I:$I,"ENTERPRISE",'MARE MX'!$AJ:$AJ,"Servicios",'MARE MX'!$BB:$BB,"*OK*") -> 0 | AE28: =COUNTIFS('MARE MX'!$I:$I,"ENTERPRISE",'MARE MX'!$AJ:$AJ,"Tecnología",'MARE MX'!$BB:$BB,"*OK*") -> 0 | AF28: =COUNTIFS('MARE MX'!$I:$I,"ENTERPRISE",'MARE MX'!$AJ:$AJ,"Transporte",'MARE MX'!$BB:$BB,"*OK*") -> 0 | AG28: =COUNTIFS('MARE MX'!$I:$I,"ENTERPRISE",'MARE MX'!$AJ:$AJ,"Turismo y Gastronomía",'MARE MX'!$BB:$BB,"*OK*") -> 0
G29: Expandir | H29: 26 | J29: 6669.9068 | L29: Optimizador Turnos | M29: =COUNTIFS('MARE MX'!$I:$I,"ENTERPRISE",'MARE MX'!$BC:$BC,"*OK*") -> 0 | N29: =COUNTIFS('MARE MX'!$I:$I,"SMB",'MARE MX'!$BC:$BC,"*OK*") -> 0 | P29: Optimizador Turnos | Q29: =COUNTIFS('MARE MX'!$I:$I,"ENTERPRISE",'MARE MX'!$AJ:$AJ,"Agrícola",'MARE MX'!$BC:$BC,"*OK*") -> 0 | R29: =COUNTIFS('MARE MX'!$I:$I,"ENTERPRISE",'MARE MX'!$AJ:$AJ,"Automotriz",'MARE MX'!$BC:$BC,"*OK*") -> 0 | S29: =COUNTIFS('MARE MX'!$I:$I,"ENTERPRISE",'MARE MX'!$AJ:$AJ,"Banca y Finanzas",'MARE MX'!$BC:$BC,"*OK*") -> 0 | T29: =COUNTIFS('MARE MX'!$I:$I,"ENTERPRISE",'MARE MX'!$AJ:$AJ,"Construcción",'MARE MX'!$BC:$BC,"*OK*") -> 0 | U29: =COUNTIFS('MARE MX'!$I:$I,"ENTERPRISE",'MARE MX'!$AJ:$AJ,"Educación",'MARE MX'!$BC:$BC,"*OK*") -> 0 | V29: =COUNTIFS('MARE MX'!$I:$I,"ENTERPRISE",'MARE MX'!$AJ:$AJ,"Energía",'MARE MX'!$BC:$BC,"*OK*") -> 0 | W29: =COUNTIFS('MARE MX'!$I:$I,"ENTERPRISE",'MARE MX'!$AJ:$AJ,"Gobierno",'MARE MX'!$BC:$BC,"*OK*") -> 0 | X29: =COUNTIFS('MARE MX'!$I:$I,"ENTERPRISE",'MARE MX'!$AJ:$AJ,"Logística",'MARE MX'!$BC:$BC,"*OK*") -> 0 | Y29: =COUNTIFS('MARE MX'!$I:$I,"ENTERPRISE",'MARE MX'!$AJ:$AJ,"Manufactura",'MARE MX'!$BC:$BC,"*OK*") -> 0 | Z29: =COUNTIFS('MARE MX'!$I:$I,"ENTERPRISE",'MARE MX'!$AJ:$AJ,"Outsourcing",'MARE MX'!$BC:$BC,"*OK*") -> 0 | AA29: =COUNTIFS('MARE MX'!$I:$I,"ENTERPRISE",'MARE MX'!$AJ:$AJ,"Retail",'MARE MX'!$BC:$BC,"*OK*") -> 0 | AB29: =COUNTIFS('MARE MX'!$I:$I,"ENTERPRISE",'MARE MX'!$AJ:$AJ,"Salud",'MARE MX'!$BC:$BC,"*OK*") -> 0 | AC29: =COUNTIFS('MARE MX'!$I:$I,"ENTERPRISE",'MARE MX'!$AJ:$AJ,"Seguridad Privada",'MARE MX'!$BC:$BC,"*OK*") -> 0 | AD29: =COUNTIFS('MARE MX'!$I:$I,"ENTERPRISE",'MARE MX'!$AJ:$AJ,"Servicios",'MARE MX'!$BC:$BC,"*OK*") -> 0 | AE29: =COUNTIFS('MARE MX'!$I:$I,"ENTERPRISE",'MARE MX'!$AJ:$AJ,"Tecnología",'MARE MX'!$BC:$BC,"*OK*") -> 0 | AF29: =COUNTIFS('MARE MX'!$I:$I,"ENTERPRISE",'MARE MX'!$AJ:$AJ,"Transporte",'MARE MX'!$BC:$BC,"*OK*") -> 0 | AG29: =COUNTIFS('MARE MX'!$I:$I,"ENTERPRISE",'MARE MX'!$AJ:$AJ,"Turismo y Gastronomía",'MARE MX'!$BC:$BC,"*OK*") -> 0
A30: Cartera | B30: SMB | G30: Expandir | H30: 5 | J30: 1210.5227 | L30: Marcaje WPP | M30: =COUNTIFS('MARE MX'!$I:$I,"ENTERPRISE",'MARE MX'!$BD:$BD,"*OK*") -> 1 | N30: =COUNTIFS('MARE MX'!$I:$I,"SMB",'MARE MX'!$BD:$BD,"*OK*") -> 4 | P30: Marcaje WPP | Q30: =COUNTIFS('MARE MX'!$I:$I,"ENTERPRISE",'MARE MX'!$AJ:$AJ,"Agrícola",'MARE MX'!$BD:$BD,"*OK*") -> 0 | R30: =COUNTIFS('MARE MX'!$I:$I,"ENTERPRISE",'MARE MX'!$AJ:$AJ,"Automotriz",'MARE MX'!$BD:$BD,"*OK*") -> 0 | S30: =COUNTIFS('MARE MX'!$I:$I,"ENTERPRISE",'MARE MX'!$AJ:$AJ,"Banca y Finanzas",'MARE MX'!$BD:$BD,"*OK*") -> 0 | T30: =COUNTIFS('MARE MX'!$I:$I,"ENTERPRISE",'MARE MX'!$AJ:$AJ,"Construcción",'MARE MX'!$BD:$BD,"*OK*") -> 0 | U30: =COUNTIFS('MARE MX'!$I:$I,"ENTERPRISE",'MARE MX'!$AJ:$AJ,"Educación",'MARE MX'!$BD:$BD,"*OK*") -> 0 | V30: =COUNTIFS('MARE MX'!$I:$I,"ENTERPRISE",'MARE MX'!$AJ:$AJ,"Energía",'MARE MX'!$BD:$BD,"*OK*") -> 0 | W30: =COUNTIFS('MARE MX'!$I:$I,"ENTERPRISE",'MARE MX'!$AJ:$AJ,"Gobierno",'MARE MX'!$BD:$BD,"*OK*") -> 0 | X30: =COUNTIFS('MARE MX'!$I:$I,"ENTERPRISE",'MARE MX'!$AJ:$AJ,"Logística",'MARE MX'!$BD:$BD,"*OK*") -> 0 | Y30: =COUNTIFS('MARE MX'!$I:$I,"ENTERPRISE",'MARE MX'!$AJ:$AJ,"Manufactura",'MARE MX'!$BD:$BD,"*OK*") -> 1 | Z30: =COUNTIFS('MARE MX'!$I:$I,"ENTERPRISE",'MARE MX'!$AJ:$AJ,"Outsourcing",'MARE MX'!$BD:$BD,"*OK*") -> 0 | AA30: =COUNTIFS('MARE MX'!$I:$I,"ENTERPRISE",'MARE MX'!$AJ:$AJ,"Retail",'MARE MX'!$BD:$BD,"*OK*") -> 0 | AB30: =COUNTIFS('MARE MX'!$I:$I,"ENTERPRISE",'MARE MX'!$AJ:$AJ,"Salud",'MARE MX'!$BD:$BD,"*OK*") -> 0 | AC30: =COUNTIFS('MARE MX'!$I:$I,"ENTERPRISE",'MARE MX'!$AJ:$AJ,"Seguridad Privada",'MARE MX'!$BD:$BD,"*OK*") -> 0 | AD30: =COUNTIFS('MARE MX'!$I:$I,"ENTERPRISE",'MARE MX'!$AJ:$AJ,"Servicios",'MARE MX'!$BD:$BD,"*OK*") -> 0 | AE30: =COUNTIFS('MARE MX'!$I:$I,"ENTERPRISE",'MARE MX'!$AJ:$AJ,"Tecnología",'MARE MX'!$BD:$BD,"*OK*") -> 0 | AF30: =COUNTIFS('MARE MX'!$I:$I,"ENTERPRISE",'MARE MX'!$AJ:$AJ,"Transporte",'MARE MX'!$BD:$BD,"*OK*") -> 0 | AG30: =COUNTIFS('MARE MX'!$I:$I,"ENTERPRISE",'MARE MX'!$AJ:$AJ,"Turismo y Gastronomía",'MARE MX'!$BD:$BD,"*OK*") -> 0
